Workbook

Sheet README
A2: SN | B2: Particulars | C2: Remarks
A3: 1 | B3: Deferred Tax Working + Effective Tax Reconciliation
A4: 2 | B4: Inter Company Loan Outstanding Balance Current Year and PY - Please reconcile once. We believe there is some mismatch to the tune of INR 388000. | D4: Done

Sheet Input
B1: BVC Specialities Private Limited | C1: CIN : U24230GJ2021PTC123855 | E1: Decimal
B2: Rounding Off | C2: 100000 | D2: =IF(C2=100000,"(₹ in Lakh)","(₹ in '000)") -> (₹ in Lakh) | E2: 0
B4: Date - CY | C4: 31 March 2024 | D4: 1 April 2024 | E4: =UPPER(C4) -> 31 MARCH 2024 | F4: =UPPER(D4) -> 1 APRIL 2024 | H4: 2023-24
B5: Date - PY | C5: 31 March 2023 | D5: 1 April 2023 | E5: =UPPER(C5) -> 31 MARCH 2023 | F5: =UPPER(D5) -> 1 APRIL 2023 | H5: 2022-23
C6: 31 March 2022 | D6: 1 April 2022 | E6: =UPPER(C6) -> 31 MARCH 2022 | F6: =UPPER(D6) -> 1 APRIL 2022 | H6: 2021-22
C7: 31 March 2021
C8: 1 April 2021 | E8: =UPPER(C8) -> 1 APRIL 2021 | F8: 5 July 2021 | H8: 2020-21
C10: Corporate Information | D10: 1
C11: Significant Accounting Policies | D11: =D10+1 -> 2
B12: Non Current Assets
B13: (a) | C13: Property, Plant and Equipment | D13: =D11+1 -> 3
B14: (b) | C14: Right of Use Assets
B15: (c) | C15: Capital work-in-progress
B16: (d) | C16: Intangible Assets
B17: (e) | C17: Financial Assets
C18: Loans | D18: 5
C19: Other Financial Assets | D19: 6
B20: (f) | C20: Deferred Tax Assets (Net) | D20: =D13+1 -> 4
B21: (g) | C21: Other Non Current Assets | D21: =D20+1 -> 5
C22: Total Non Current Assets
B23: Current Assets
B24: (a) | C24: Inventories | D24: 7
B25: (a) | C25: Financial Assets
C26: Trade Receivables | D26: 8
C27: Cash and Cash Equivalents | D27: 9
C28: Other Bank Balance | D28: 10
C29: Loans
C30: Other Financial Assets
B31: (b) | C31: Other Current Assets | D31: 11
C32: Total Current Assets
C33: Total Assets
B34: EQUITY AND LIABILITIES
B35: Equity
B36: (a) | C36: Equity Share Capital | D36: 12
B37: (b) | C37: Other Equity | D37: 13
C38: Total Equity
B39: Liabilities
B40: Non Current Liabilities
B41: (a) | C41: Financial Liabilities
C42: Borrowings | D42: =D37+1 -> 14
C43: Lease Liability
B44: (b) | C44: Provisions
B45: (c) | C45: Deferred Tax Liabilities (Net) | D45: =D20 -> 4
C46: Total Non Current Liabilities
B47: Current Liabilities
B48: (a) | C48: Financial Liabilities
C49: Borrowings | D49: =D42 -> 14
C50: Lease Liability
C51: Trade Payables | D51: 15
C52: -Dues of micro enterprises and small enterprises
C53: -Dues of creditors other than micro enterprises and small enterprises
C54: Other Financial Liabilities | D54: 16
B55: (b) | C55: Provisions
B56: (d) | C56: Other Current Liabilities | D56: 17
C57: Total Current Liabilities
C58: Total Liabilities
C59: Total Equity and Liabilities
B61: I | C61: Revenue from Operations | D61: 18
B62: II | C62: Other Income | D62: 19
B63: III | C63: Total Income (I+II)
B64: IV | C64: Expenses:
C65: Cost of material consumed | D65: 20
C66: Changes in inventories of finished goods and work-in-progress | D66: 21
C67: Employee Benefits Expense | D67: 22
C68: Finance Costs | D68: 23
C69: Depreciation and Amortization Expenses | D69: =D13 -> 3
C70: Other Expenses | D70: =D68+1 -> 24
C71: Total Expense (IV)
B72: V | C72: Profit Before Tax (III-IV)
B73: VI | C73: Tax Expenses
C74: (a) Current Tax | D74: =D20 -> 4
C75: (b) Deferred Tax Expense/(Benefit) | D75: =D74 -> 4
C77: Total Tax Expenses
B78: VII | C78: Profit for the Year (V-VI)
B79: VIII | C79: Other Comprehensive Income | D79: =D20 -> 4
C80: Earnings Per Share (Face Value of ₹ 10 each) | D80: =D70+1 -> 25
C87: Other Statutory Information | D87: =D94+1 -> 27
C88: Segment Reporting | D88: =D87+1 -> 28
C89: Leases | D89: =D88+1 -> 29
C90: BORROWING COSTS CAPITALISATION | D90: =D89+1 -> 30
C91: Revenue from contracts with customers
C92: Employee Benefits
C93: Derivative Instrument
C94: Related party transactions | D94: =D80+1 -> 26
C95: Share based payments
C96: Contingent Liabilties
C97: Capital Commitments
C98: Financial Instruments | D98: =D90+1 -> 31
C99: Financial Ratios | D99: =D98+1 -> 32
C100: Ind AS 101 Note
C101: Capital Management | D101: 33
C109: Checks
B110: Balance sheet | C110: =BS!$G$62 -> 0
C111: =BS!$H$62 -> 0
B112: P & L | C112: =PL!$G$18 -> 15404670
C113: =PL!$H$18 -> 0
B114: SOCIE | C114: =SOCIE!$G$31 -> #REF!
C115: =SOCIE!$G$36 -> 25683.576
B116: Cash flow | C116: =#REF! -> #REF!
C117: =#REF! -> #REF!
...

Sheet Pivot
D3: Values
A4: Type | B4: Note | C4: Ind AS Head | D4: Sum of Current | E4: Sum of Non-Current | F4: Sum of Total
A5: Equity | B5: 13 | C5: Equity share capital | D5: 0 | E5: -1365970 | F5: -1365970
C6: Other equity | D6: 0 | E6: -1999973649 | F6: -1999973649 | I6: CY Profit
B7: 14 | C7: Other equity | D7: 0 | E7: -8.7918109e+08 | F7: -8.7918109e+08 | H7: =-823214.934735809*1000 -> -8.2321493e+08 | I7: =F7-H7 -> -55966159
A8: Equity Total | D8: 0 | E8: -2.8805207e+09 | F8: -2.8805207e+09
A9: Liabilities | B9: 4 | C9: Deferred Tax Liabilities (Net) | D9: -142606.21 | E9: 0 | F9: -142606.21
B10: 7 | C10: Other Tax Assets (Net) | D10: 0 | E10: 0 | F10: 0
B11: 15 | C11: Borrowings | D11: -2.4152271e+08 | E11: -2.6059553e+09 | F11: -2.8474781e+09
B12: 16 | C12: Provisions | D12: -388605 | E12: -1839333 | F12: -2227938
B13: 17 | C13: Trade payables | D13: -1.2661909e+08 | E13: 0 | F13: -1.2661909e+08
B14: 18 | C14: Other financial liabilities | D14: -1.4259158e+08 | E14: 0 | F14: -1.4259158e+08
B15: 19 | C15: Other Current Liabilities | D15: -5827827.9 | E15: 0 | F15: -5827827.9
A16: Liabilities Total | D16: -5.1709242e+08 | E16: -2.6077947e+09 | F16: -3.1248871e+09
A17: Asset | B17: 3 | C17: Property, Plant and Equipment | D17: 0 | E17: 5.3252185e+09 | F17: 5.3252185e+09
B18: 6 | C18: Other financial assets | D18: 0 | E18: 33715121 | F18: 33715121
B19: 7 | C19: Other Tax Assets (Net) | D19: 0 | E19: 1012555 | F19: 1012555
B20: 8 | C20: Non Current Assets | D20: 0 | E20: 0 | F20: 0
B21: 9 | C21: Inventories | D21: 45600578 | E21: 0 | F21: 45600578
B22: 10 | C22: Trade receivables | D22: 13928477 | E22: 0 | F22: 13928477
B23: 11 | C23: Cash & Cash Equivalents | D23: 8972905.8 | E23: 0 | F23: 8972905.8
B24: 12 | C24: Other Current Assets | D24: 5.2099744e+08 | E24: 0 | F24: 5.2099744e+08
A25: Asset Total | D25: 5.894994e+08 | E25: 5.3599461e+09 | F25: 5.9494455e+09
A26: Expenses | B26: 3 | C26: Depreciation and Amortisation Expense | D26: 0 | E26: 0 | F26: 51221254
B27: 22 | C27: Cost of material consumed | D27: 0 | E27: 0 | F27: 44815227
B28: 23 | C28: Changes in inventories of finished goods and work-in-progress | D28: 0 | E28: 0 | F28: -2769259.9
B29: 24 | C29: Employee benefits expense | D29: 0 | E29: 0 | F29: 7060372
B30: 25 | C30: Finance costs | D30: 0 | E30: 0 | F30: 14199565
B31: 26 | C31: Other expenses | D31: 0 | E31: 0 | F31: 14492003
B32: - | C32: Current income tax | D32: 0 | E32: 0 | F32: 1495489
C33: Tax Expense | D33: 0 | E33: 0 | F33: 0
A34: Expenses Total | D34: 0 | E34: 0 | F34: 1.3051465e+08
A35: Income | B35: 20 | C35: Other Income | D35: 0 | E35: 0 | F35: -67940.18
C36: Revenue from operations | D36: 0 | E36: 0 | F36: -68979137
B37: 21 | C37: Other Income | D37: 0 | E37: 0 | F37: -5505299.5
A38: Income Total | D38: 0 | E38: 0 | F38: -74552377 | I38: =F38+F34 -> 55962273 | J38: =-PL!D34*1000 -> 5945240 | K38: =I38-J38 -> 50017033
A39: Grand Total | D39: 72406975 | E39: -1.2836925e+08 | F39: -1.6385689e-05

Sheet Master Grouping
A1: Code | B1: INDAS Head | C1: INDAS Sub Head
A2: 10000000 | B2: Equity share capital | C2: =VLOOKUP(A2,'TB BVS 31.03.26'!B:E,4,0) -> 315,940 (previous year: 315,940) equity shares of Rs 10 each fully paid up
A3: 10000004 | B3: Equity share capital | C3: =VLOOKUP(A3,'TB BVS 31.03.26'!B:E,4,0) -> Pref Shar CCPS-BVCPL
A4: 10100000 | B4: Other equity | C4: =VLOOKUP(A4,'TB BVS 31.03.26'!B:E,4,0) -> Closing balance - Securities Premium
A5: 10100001 | B5: Other equity | C5: =VLOOKUP(A5,'TB BVS 31.03.26'!B:E,4,0) -> Closing balance - Retained Earnings
A6: 10100002 | B6: Other equity | C6: =VLOOKUP(A6,'TB BVS 31.03.26'!B:E,4,0) -> Closing balance - Retained Earnings
A7: 10100009 | B7: Other equity | C7: =VLOOKUP(A7,'TB BVS 31.03.26'!B:E,4,0) -> Closing balance - Retained Earnings
A8: 10200015 | B8: Borrowings | C8: =VLOOKUP(A8,'TB BVS 31.03.26'!B:E,4,0) -> Term Loan from Bank*
A9: 10200016 | B9: Borrowings | C9: =VLOOKUP(A9,'TB BVS 31.03.26'!B:E,4,0) -> Term Loan from Bank*
A10: 10200018 | B10: Borrowings | C10: =VLOOKUP(A10,'TB BVS 31.03.26'!B:E,4,0) -> Term Loan from Bank*
A11: 10300002 | B11: Borrowings | C11: =VLOOKUP(A11,'TB BVS 31.03.26'!B:E,4,0) -> Term Loan from Bank*
A12: 10400001 | B12: Deferred Tax Liabilities (Net) | C12: =VLOOKUP(A12,'TB BVS 31.03.26'!B:E,4,0) -> Deferred Tax
A13: 10500000 | B13: Provisions | C13: =VLOOKUP(A13,'TB BVS 31.03.26'!B:E,4,0) -> Provision for employee benefits - Gratuity
... A237: 10000001 | B237: Equity share capital | C237: =VLOOKUP(A237,'TB BVS 31.03.26'!B:E,4,0) -> #N/A

Sheet TB BVS 31.3.25
G1: BS | H1: CFS
G2: =BS!G61 -> 0.54886832 | H2: =#REF! -> #REF!
A3: =Input!B1 -> BVC Specialities Private Limited | G3: 0
A4: Trial Balance as on 31 March 2024 | G4: =SUBTOTAL(9,G7:G1096) -> 1.5739688e+10 | H4: =SUBTOTAL(9,H7:H1096) -> -1.5739688e+10 | I4: =SUBTOTAL(9,I7:I1096) -> 2.1457672e-06 | J4: =SUBTOTAL(9,J7:J1096) -> -1.009453e+08 | K4: =SUBTOTAL(9,K7:K1096) -> -95868897 | L4: =SUBTOTAL(9,L7:L115) -> 0
C5: Ind AS
A6: Type | B6: Code No. | C6: Note | D6: Ind AS Head | E6: Ind AS Sub Head | F6: Particulars | G6: Debit | H6: Credit | I6: Total | J6: Current | K6: Non-Current | L6: Check
A7: Equity | B7: 10000000 | C7: 13 | D7: Equity share capital | E7: 315,940 (previous year: 315,940) equity shares of Rs 10 each fully paid up | F7: Equity Share Capital | G7: 0 | H7: -1365970 | I7: =G7+H7 -> -1365970 | J7: 0 | K7: =I7-J7 -> -1365970 | L7: =I7-J7-K7 -> 0
A8: Equity | B8: 10000004 | C8: 13 | D8: Equity share capital | E8: Pref Shar CCPS-BVCPL | F8: 0.01% Non-Cumulative CCPS | G8: 0 | H8: -868680 | I8: =G8+H8 -> -868680 | J8: 0 | K8: =I8-J8 -> -868680 | L8: =I8-J8-K8 -> 0
A9: Equity | B9: 10100000 | C9: 14 | D9: Other equity | E9: Closing balance - Securities Premium | F9: Security Premium Account | G9: 0 | H9: -2.8885604e+09 | I9: =G9+H9 -> -2.8885604e+09 | J9: 0 | K9: =I9-J9 -> -2.8885604e+09 | L9: =I9-J9-K9 -> 0 | P9: Opening | Q9: CY | R9: Closing
A10: Equity | B10: 10100001 | C10: 14 | D10: Other equity | E10: Closing balance - Retained Earnings | F10: Retained earnings | G10: 2371971.4 | H10: 0 | I10: =G10+H10 -> 2371971.4 | J10: 0 | K10: =I10-J10 -> 2371971.4 | L10: =I10-J10-K10 -> 0 | P10: =-'BS Notes 3-18'!H243*1000 -> 2029035.2 | Q10: 386615.03 | R10: =SUBTOTAL(9,P10:Q10) -> 2415650.2
A11: Equity | B11: 10100002 | C11: 14 | D11: Other equity | E11: Closing balance - Retained Earnings | F11: Profit & Loss Account | G11: 7941080.5 | H11: 0 | I11: =G11+H11 -> 7941080.5 | J11: 0 | K11: =I11-J11 -> 7941080.5 | L11: =I11-J11-K11 -> 0 | P11: =I11 -> 7941080.5 | R11: =SUBTOTAL(9,P11:Q11) -> 7941080.5
A12: Equity | B12: 10100009 | C12: 14 | D12: Other equity | E12: Closing balance - Retained Earnings | F12: IND AS - Opening Balance - Retained Earnings | G12: 0 | H12: -38668.9 | I12: =G12+H12 -> -38668.9 | J12: 0 | K12: =I12-J12 -> -38668.9 | L12: =I12-J12-K12 -> 0
A13: Liabilities | B13: 10200015 | C13: 15 | D13: Borrowings | E13: Term Loan from Bank | F13: IND AS - Transaction Cost Impact on TL | G13: 1284522.4 | H13: 0 | I13: =G13+H13 -> 1284522.4 | J13: 0 | K13: =I13-J13 -> 1284522.4 | L13: =I13-J13-K13 -> 0 | P13: =I13 -> 1284522.4 | R13: =SUBTOTAL(9,P13:Q13) -> 1284522.4
A14: Liabilities | B14: 10200016 | C14: 15 | D14: Borrowings | E14: Term Loan from Bank | F14: TL_AXIS_ 923060053143888 | G14: 0 | H14: -2000000000 | I14: =G14+H14 -> -2000000000 | J14: -233100000 | K14: =I14-J14 -> -1766900000 | L14: =I14-J14-K14 -> 0
A15: Liabilities | B15: 10200018 | C15: 15 | D15: Borrowings | E15: Term Loan from Bank | F15: TL_AXIS_924060051723539 | G15: 0 | H15: -400000000 | I15: =G15+H15 -> -400000000 | J15: -46900000 | K15: =I15-J15 -> -353100000 | L15: =I15-J15-K15 -> 0
A16: Liabilities | B16: 10300002 | C16: 15 | D16: Borrowings | E16: Term Loan from Bank | F16: TL_HDFC_02400930000746 | G16: 0 | H16: -2.474626e+08 | I16: =G16+H16 -> -2.474626e+08 | J16: -30932825 | K16: =I16-J16 -> -2.1652978e+08 | L16: =I16-J16-K16 -> 0
A17: Liabilities | B17: 10400001 | C17: 4 | D17: Deferred Tax Liabilities (Net) | E17: Deferred Tax | F17: IND AS - Deferred Tax Liability | G17: 0 | H17: -238523.49 | I17: =G17+H17 -> -238523.49 | J17: =I17 -> -238523.49 | K17: =I17-J17 -> 0 | L17: =I17-J17-K17 -> 0
A18: Liabilities | B18: 10500000 | C18: 16 | D18: Provisions | E18: Provision for employee benefits - Gratuity | F18: Provision for Gratuity | G18: 0 | H18: -1940219 | I18: =G18+H18 -> -1940219 | J18: -198583 | K18: =I18-J18 -> -1741636 | L18: =I18-J18-K18 -> 0
A19: Liabilities | B19: 10500001 | C19: 16 | D19: Provisions | E19: Provision for compensated absences | F19: Provision for Leave Salary | G19: 0 | H19: -2662538 | I19: =G19+H19 -> -2662538 | J19: -506035 | K19: =I19-J19 -> -2156503 | L19: =I19-J19-K19 -> 0
A20: Liabilities | B20: 10600010 | C20: 15 | D20: Borrowings | E20: Unsecured loan from related parties | F20: Best Value Chem Pvt Ltd. | G20: 0 | H20: -2.6596834e+08 | I20: =G20+H20 -> -2.6596834e+08 | J20: 0 | K20: =I20-J20 -> -2.6596834e+08 | L20: =I20-J20-K20 -> 0
A21: Liabilities | B21: 10800000 | C21: 17 | D21: Trade payables | E21: Total outstanding dues of creditors other than micro enterprises and small enterprises | F21: Payable - Raw Material Import | G21: 0 | H21: -23799281 | I21: =G21+H21 -> -23799281 | J21: =I21 -> -23799281 | K21: =I21-J21 -> 0 | L21: =I21-J21-K21 -> 0
A22: Liabilities | B22: 10800001 | C22: 17 | D22: Trade payables | E22: Total outstanding dues of creditors other than micro enterprises and small enterprises | F22: Payable - Raw Material Domestic | G22: 0 | H22: -53207756 | I22: =G22+H22 -> -53207756 | J22: =I22 -> -53207756 | K22: =I22-J22 -> 0 | L22: =I22-J22-K22 -> 0
A23: Liabilities | B23: 10800002 | C23: 17 | D23: Trade payables | E23: Total outstanding dues of creditors other than micro enterprises and small enterprises | F23: Payable - Packing Material | G23: 0 | H23: -6382962 | I23: =G23+H23 -> -6382962 | J23: =I23 -> -6382962 | K23: =I23-J23 -> 0 | L23: =I23-J23-K23 -> 0
A24: Liabilities | B24: 10800003 | C24: 17 | D24: Trade payables | E24: Total outstanding dues of creditors other than micro enterprises and small enterprises | F24: Payable - Fuel | G24: 0 | H24: -7927826 | I24: =G24+H24 -> -7927826 | J24: =I24 -> -7927826 | K24: =I24-J24 -> 0 | L24: =I24-J24-K24 -> 0
A25: Liabilities | B25: 10800004 | C25: 17 | D25: Trade payables | E25: Total outstanding dues of creditors other than micro enterprises and small enterprises | F25: Payable - Others | G25: 0 | H25: -1.6782554e+08 | I25: =G25+H25 -> -1.6782554e+08 | J25: =I25 -> -1.6782554e+08 | K25: =I25-J25 -> 0 | L25: =I25-J25-K25 -> 0
A26: Liabilities | B26: 10800005 | C26: 18 | D26: Other financial liabilities | E26: Employee benefits payable | F26: Payables - Employees | G26: 0 | H26: -78704.78 | I26: =G26+H26 -> -78704.78 | J26: =I26 -> -78704.78 | K26: =I26-J26 -> 0 | L26: =I26-J26-K26 -> 0
A27: Liabilities | B27: 10900000 | C27: 17 | D27: Trade payables | E27: Total outstanding dues of creditors other than micro enterprises and small enterprises | F27: Provision_Other Expenses | G27: 0 | H27: -48270630 | I27: =G27+H27 -> -48270630 | J27: =I27 -> -48270630 | K27: =I27-J27 -> 0 | L27: =I27-J27-K27 -> 0
A28: Liabilities | B28: 20100001 | C28: 17 | D28: Trade payables | E28: Total outstanding dues of creditors other than micro enterprises and small enterprises | F28: Capital Advances | G28: 11010528 | H28: 0 | I28: =G28+H28 -> 11010528 | J28: =I28 -> 11010528 | K28: =I28-J28 -> 0 | L28: =I28-J28-K28 -> 0
A29: Liabilities | B29: 10900003 | C29: 18 | D29: Other financial liabilities | E29: Employee benefits payable | F29: Provision_PF and ESIC Contribution by Company | G29: 0 | H29: -311807 | I29: =G29+H29 -> -311807 | J29: =I29 -> -311807
A30: Liabilities | B30: 10900018 | C30: 18 | D30: Other financial liabilities | E30: Employee benefits payable | F30: Salary Payable | G30: 0 | H30: -6010926 | I30: =G30+H30 -> -6010926 | J30: =I30 -> -6010926 | K30: =I30-J30 -> 0 | L30: =I30-J30-K30 -> 0
A31: Liabilities | B31: 11000001 | C31: 19 | D31: Other Current Liabilities | E31: Statutory liabilities | F31: TDS_Professional and Consulting_194J | G31: 0 | H31: -604915.06 | I31: =G31+H31 -> -604915.06 | J31: =I31 -> -604915.06 | K31: =I31-J31 -> 0 | L31: =I31-J31-K31 -> 0
A32: Liabilities | B32: 11000002 | C32: 19 | D32: Other Current Liabilities | E32: Statutory liabilities | F32: TDS_Contractors_194C | G32: 0 | H32: -1218102.8 | I32: =G32+H32 -> -1218102.8 | J32: =I32 -> -1218102.8 | K32: =I32-J32 -> 0 | L32: =I32-J32-K32 -> 0
A33: Liabilities | B33: 11000003 | C33: 19 | D33: Other Current Liabilities | E33: Statutory liabilities | F33: TDS_Interest on borrowing_194A | G33: 0 | H33: -995290.17 | I33: =G33+H33 -> -995290.17 | J33: =I33 -> -995290.17 | K33: =I33-J33 -> 0 | L33: =I33-J33-K33 -> 0
A34: Liabilities | B34: 11000005 | C34: 19 | D34: Other Current Liabilities | E34: Statutory liabilities | F34: TDS_Rent_194I | G34: 0 | H34: -21113 | I34: =G34+H34 -> -21113 | J34: =I34 -> -21113 | K34: =I34-J34 -> 0 | L34: =I34-J34-K34 -> 0
A35: Liabilities | B35: 11000006 | C35: 19 | D35: Other Current Liabilities | E35: Statutory liabilities | F35: TDS_Purchase on Goods_194Q | G35: 0 | H35: -64627 | I35: =G35+H35 -> -64627 | J35: =I35 -> -64627 | K35: =I35-J35 -> 0 | L35: =I35-J35-K35 -> 0
A36: Liabilities | B36: 11000007 | C36: 19 | D36: Other Current Liabilities | E36: Statutory liabilities | F36: TDS_Salary_192 | G36: 0 | H36: -627704 | I36: =G36+H36 -> -627704 | J36: =I36 -> -627704 | K36: =I36-J36 -> 0 | L36: =I36-J36-K36 -> 0
A37: Liabilities | B37: 11000011 | C37: 19 | D37: Other Current Liabilities | E37: Statutory liabilities | F37: PF Employee Contribution | G37: 0 | H37: -288873 | I37: =G37+H37 -> -288873 | J37: =I37 -> -288873 | K37: =I37-J37 -> 0 | L37: =I37-J37-K37 -> 0
A38: Liabilities | B38: 11000012 | C38: 19 | D38: Other Current Liabilities | E38: Statutory liabilities | F38: Professional Tax | G38: 0 | H38: -31400 | I38: =G38+H38 -> -31400 | J38: =I38 -> -31400 | K38: =I38-J38 -> 0 | L38: =I38-J38-K38 -> 0
A39: Liabilities | B39: 11100002 | C39: 18 | D39: Other financial liabilities | E39: Payable for capital goods (including retention amount) | F39: Retention Money | G39: 0 | H39: -1.0417368e+08 | I39: =G39+H39 -> -1.0417368e+08 | J39: =I39 -> -1.0417368e+08 | K39: =I39-J39 -> 0 | L39: =I39-J39-K39 -> 0
A40: Liabilities | B40: 21000008 | C40: 19 | D40: Other Current Liabilities | E40: Statutory liabilities | F40: CGST Payable | G40: 0 | H40: -16738.64 | I40: =G40+H40 -> -16738.64 | J40: =I40 -> -16738.64 | K40: =I40-J40 -> 0 | L40: =I40-J40-K40 -> 0
A41: Liabilities | B41: 21000009 | C41: 19 | D41: Other Current Liabilities | E41: Statutory liabilities | F41: SGST Payable | G41: 0 | H41: -16738.64 | I41: =G41+H41 -> -16738.64 | J41: =I41 -> -16738.64 | K41: =I41-J41 -> 0 | L41: =I41-J41-K41 -> 0
... A51: Liabilities | B51: 10900015 | C51: 7 | D51: Other Tax Assets (Net) | E51: Income tax liabilities (Net) | F51: Provision_Income Tax | G51: 0 | H51: 0 | I51: =G51+H51 -> 0 | J51: =I51 -> 0 | K51: =I51-J51 -> 0 | L51: =I51-J51-K51 -> 0
A52: Asset | B52: 20000000 | C52: 3 | D52: Property, Plant and Equipment | E52: Property, plant & equipment | F52: Freehold land | G52: 93599471 | H52: 0 | I52: =G52+H52 -> 93599471 | J52: 0 | K52: =I52-J52 -> 93599471 | L52: =I52-J52-K52 -> 0
A53: Asset | B53: 20000001 | C53: 3 | D53: Property, Plant and Equipment | E53: Building | F53: Building | G53: 1.5176937e+09 | H53: 0 | I53: =G53+H53 -> 1.5176937e+09 | J53: 0 | K53: =I53-J53 -> 1.5176937e+09 | L53: 0
A54: Asset | B54: 20000002 | C54: 3 | D54: Property, Plant and Equipment | E54: Building | F54: ACC_DEP_Building | G54: 0 | H54: -23940315 | I54: =G54+H54 -> -23940315 | J54: 0 | K54: =I54-J54 -> -23940315 | L54: 0
A55: Asset | B55: 20000003 | C55: 3 | D55: Property, Plant and Equipment | E55: Property, plant & equipment | F55: Plant and machinery | G55: 3.3851696e+09 | H55: 0 | I55: =G55+H55 -> 3.3851696e+09 | J55: 0 | K55: =I55-J55 -> 3.3851696e+09 | L55: =I55-J55-K55 -> 0
A56: Asset | B56: 20000004 | C56: 3 | D56: Property, Plant and Equipment | E56: Property, plant & equipment | F56: ACC_DEP_Plant and machinery | G56: 0 | H56: -98387308 | I56: =G56+H56 -> -98387308 | J56: 0 | K56: =I56-J56 -> -98387308 | L56: =I56-J56-K56 -> 0
A57: Asset | B57: 20000007 | C57: 3 | D57: Property, Plant and Equipment | E57: Computers | F57: Computers | G57: 16903686 | H57: 0 | I57: =G57+H57 -> 16903686 | J57: 0 | K57: =I57-J57 -> 16903686 | L57: =I57-J57-K57 -> 0
A58: Asset | B58: 20000008 | C58: 3 | D58: Property, Plant and Equipment | E58: Computers | F58: ACC_DEP_Computers | G58: 0 | H58: -1509878.1 | I58: =G58+H58 -> -1509878.1 | J58: 0 | K58: =I58-J58 -> -1509878.1 | L58: =I58-J58-K58 -> 0
A59: Asset | B59: 20000006 | C59: 3 | D59: Property, Plant and Equipment | E59: Office Equipment | F59: ACC_DEP_Office equim | G59: 0 | H59: -1127057.1 | I59: =G59+H59 -> -1127057.1
A60: Asset | B60: 20000010 | C60: 3 | D60: Property, Plant and Equipment | E60: Furniture & Fixture | F60: ACC_DEP_Furniture an | G60: 0 | H60: -594660.1 | I60: =G60+H60 -> -594660.1
A61: Asset | B61: 20000012 | C61: 3 | D61: Property, Plant and Equipment | E61: Electrical Fittings | F61: ACC_DEP_Electrical f | G61: 0 | H61: -3890620.1 | I61: =G61+H61 -> -3890620.1
A62: Asset | B62: 20000016 | C62: 3 | D62: Property, Plant and Equipment | E62: Computer Software | F62: ACC_DEP_Computer Sof | G62: 0 | H62: -314295.85 | I62: =G62+H62 -> -314295.85
A63: Asset | B63: 20000017 | C63: 3 | D63: Property, Plant and Equipment | E63: Right of Use Assets | F63: Leasehold Land | G63: 324389641 | H63: 0 | I63: =G63+H63 -> 324389641 | J63: 0 | K63: =I63-J63 -> 324389641 | L63: =I63-J63-K63 -> 0
A64: Asset | B64: 20000018 | C64: 3 | D64: Property, Plant and Equipment | E64: Right of Use Assets | F64: ACC_DEP_Leased Land | G64: 0 | H64: -9297332.9 | I64: =G64+H64 -> -9297332.9 | J64: 0 | K64: =I64-J64 -> -9297332.9 | L64: =I64-J64-K64 -> 0
A65: Asset | B65: 20100000 | C65: 3 | D65: Property, Plant and Equipment | E65: Capital work-in-progress | F65: Capital Work In Progress | G65: 60.24 | H65: 0 | I65: =G65+H65 -> 60.24 | J65: 0 | K65: =I65-J65 -> 60.24 | L65: =I65-J65-K65 -> 0
A66: Asset | B66: 20100002 | C66: 3 | D66: Property, Plant and Equipment | E66: Capital work-in-progress | F66: Capital Work In Progress - Internal Orders | G66: 0 | H66: 0 | I66: =G66+H66 -> 0 | J66: 0 | K66: =I66-J66 -> 0 | L66: =I66-J66-K66 -> 0
A67: Asset | B67: 20100004 | C67: 3 | D67: Property, Plant and Equipment | E67: Capital work-in-progress | F67: AUC Cost | G67: 41000 | H67: 0 | I67: =G67+H67 -> 41000 | J67: 0 | K67: =I67-J67 -> 41000 | L67: =I67-J67-K67 -> 0
A68: Asset | B68: 40700034 | C68: 3 | D68: Property, Plant and Equipment | E68: Capital work-in-progress | F68: Project Expenses | G68: 0 | H68: 0 | I68: =G68+H68 -> 0 | J68: 0 | K68: =I68-J68 -> 0 | L68: =I68-J68-K68 -> 0
A69: Asset | B69: 20000005 | C69: 3 | D69: Property, Plant and Equipment | E69: Office Equipment | F69: Office Equipment | G69: 19595727 | H69: 0 | I69: =G69+H69 -> 19595727 | J69: 0 | K69: =I69-J69 -> 19595727
A70: Asset | B70: 20000009 | C70: 3 | D70: Property, Plant and Equipment | E70: Furniture & Fixture | F70: Furniture & Fixture | G70: 20587570 | H70: 0 | I70: =G70+H70 -> 20587570 | J70: 0 | K70: =I70-J70 -> 20587570
A71: Asset | B71: 20000011 | C71: 3 | D71: Property, Plant and Equipment | E71: Electrical Fittings | F71: Electrical Fittings | G71: 1.3349476e+08 | H71: 0 | I71: =G71+H71 -> 1.3349476e+08 | J71: 0 | K71: =I71-J71 -> 1.3349476e+08
A72: Asset | B72: 20000015 | C72: 3 | D72: Property, Plant and Equipment | E72: Computer Software | F72: Computer Software | G72: 4679369.2 | H72: 0 | I72: =G72+H72 -> 4679369.2 | J72: 0 | K72: =I72-J72 -> 4679369.2
A73: Asset | B73: 20100003 | C73: 3 | D73: Property, Plant and Equipment | E73: Capital work-in-progress | F73: Capita Adv Audit Adj | G73: 0 | H73: -41060 | I73: =G73+H73 -> -41060 | J73: 0 | K73: =I73-J73 -> -41060
A74: Asset | B74: 20300000 | C74: =VLOOKUP(D74,[4]Input!C:D,2,0) -> 6 | D74: Other financial assets | E74: Security deposits | F74: Deposit_Other | G74: 27413904 | H74: 0 | I74: =G74+H74 -> 27413904 | J74: 0 | K74: =I74-J74 -> 27413904 | L74: =I74-J74-K74 -> 0
A75: Asset | B75: 20300004 | C75: =VLOOKUP(D75,[4]Input!C:D,2,0) -> 6 | D75: Other financial assets | E75: Security deposits | F75: Deposit_Prohibition and Excise | G75: 1000 | H75: 0 | I75: =G75+H75 -> 1000 | J75: 0 | K75: =I75-J75 -> 1000 | L75: =I75-J75-K75 -> 0
A76: Liabilities | B76: 20400001 | C76: =VLOOKUP(D76,[4]Input!C:D,2,0) -> 4 | D76: Deferred Tax Liabilities (Net) | E76: Deferred Tax Liabilities (Net) | F76: IND AS - Deferred Tax Assets | G76: 95917.28 | H76: 0 | I76: =G76+H76 -> 95917.28 | J76: =I76 -> 95917.28 | K76: =I76-J76 -> 0 | L76: =I76-J76-K76 -> 0
A77: Asset | B77: 20500000 | C77: 9 | D77: Inventories | E77: Raw materials | F77: Raw Material Stock | G77: 32146506 | H77: 0 | I77: =G77+H77 -> 32146506 | J77: =I77 -> 32146506 | K77: =I77-J77 -> 0 | L77: =I77-J77-K77 -> 0
A78: Asset | B78: 20500001 | C78: 9 | D78: Inventories | E78: Packing material | F78: Packing Material Stock | G78: 2090466.1 | H78: 0 | I78: =G78+H78 -> 2090466.1 | J78: =I78 -> 2090466.1 | K78: =I78-J78 -> 0 | L78: =I78-J78-K78 -> 0
A79: Asset | B79: 20500002 | C79: 9 | D79: Inventories | E79: Stores and spares | F79: Fuel Stock | G79: 1514975.2 | H79: 0 | I79: =G79+H79 -> 1514975.2 | J79: =I79 -> 1514975.2 | K79: =I79-J79 -> 0 | L79: =I79-J79-K79 -> 0
A80: Asset | B80: 20500003 | C80: 9 | D80: Inventories | E80: Work-in-progress | F80: SFG Stock in Plants | G80: 0 | H80: 0 | I80: =G80+H80 -> 0 | J80: =I80 -> 0 | K80: =I80-J80 -> 0 | L80: =I80-J80-K80 -> 0
A81: Asset | B81: 20500005 | C81: 9 | D81: Inventories | E81: Stores and spares | F81: Store and Spares - | G81: 5470168.6 | H81: 0 | I81: =G81+H81 -> 5470168.6 | J81: =I81 -> 5470168.6 | K81: =I81-J81 -> 0 | L81: =I81-J81-K81 -> 0
A82: Asset | B82: 20500006 | C82: 9 | D82: Inventories | E82: Finished goods* | F82: Goods In Transit - Sales | G82: 0 | H82: 0 | I82: =G82+H82 -> 0 | J82: =I82 -> 0 | K82: =I82-J82 -> 0 | L82: =I82-J82-K82 -> 0
A83: Asset | B83: 20500008 | C83: 9 | D83: Inventories | E83: Work-in-progress | F83: Inventory_Manual Entry | G83: 39908784 | H83: 0 | I83: =G83+H83 -> 39908784 | J83: =I83 -> 39908784 | K83: =I83-J83 -> 0 | L83: =I83-J83-K83 -> 0
A84: Asset | B84: 20600001 | C84: 10 | D84: Trade receivables | E84: Considered good - unsecured | F84: Receivables-Domestic | G84: 44942032 | H84: 0 | I84: =G84+H84 -> 44942032 | J84: =I84 -> 44942032 | K84: =I84-J84 -> 0 | L84: =I84-J84-K84 -> 0
A85: Asset | B85: 20600004 | C85: 10 | D85: Trade receivables | E85: Considered good - unsecured | F85: Receivables- Scrap | G85: 633961.3 | H85: 0 | I85: =G85+H85 -> 633961.3 | J85: =I85 -> 633961.3 | K85: =I85-J85 -> 0 | L85: =I85-J85-K85 -> 0
A86: Asset | B86: 20600006 | C86: 10 | D86: Trade receivables | E86: Considered good - unsecured | F86: Receivables- GIT | G86: 0 | H86: 0 | I86: =G86+H86 -> 0 | J86: =I86 -> 0 | K86: =I86-J86 -> 0 | L86: =I86-J86-K86 -> 0
A87: Asset | B87: 20600009 | C87: 10 | D87: Trade receivables | E87: Considered good - unsecured | F87: Receivables- Advance | G87: 0 | H87: -191373.5 | I87: =G87+H87 -> -191373.5 | J87: =I87 -> -191373.5 | K87: =I87-J87 -> 0 | L87: =I87-J87-K87 -> 0
A88: Asset | B88: 20800110 | C88: 11 | D88: Borrowings | E88: Working Capital Loans from Bank | F88: CA_HDFC_57500000732637 | G88: 475424.48 | H88: 0 | I88: =G88+H88 -> 475424.48 | J88: =I88 -> 475424.48 | K88: =I88-J88 -> 0 | L88: =I88-J88-K88 -> 0
... A92: Asset | B92: 20800122 | C92: 11 | D92: Cash & Cash Equivalents | E92: Balance with banks | F92: CA_Axis_923020022099965 | G92: 0 | H92: -5.6675218e+09 | I92: =G92+H92 -> -5.6675218e+09 | J92: =I92 -> -5.6675218e+09 | K92: =I92-J92 -> 0 | L92: =I92-J92-K92 -> 0
A93: Asset | B93: 20900003 | C93: 6 | D93: Other financial assets | E93: Bank Deposit with more than 12 months of maturity | F93: FD_Axis | G93: 5036678 | H93: 0 | I93: =G93+H93 -> 5036678 | J93: 0 | K93: =I93-J93 -> 5036678 | L93: =I93-J93-K93 -> 0
A94: Asset | B94: 21000003 | C94: 7 | D94: Other Tax Assets (Net) | E94: Other Tax Asset (Net) | F94: TDS Receiveable_194Q | G94: 35799 | H94: 0 | I94: =G94+H94 -> 35799 | J94: 0 | K94: =I94-J94 -> 35799 | L94: =I94-J94-K94 -> 0
A95: Asset | B95: 21000004 | C95: 7 | D95: Other Tax Assets (Net) | E95: Other Tax Asset (Net) | F95: TDS Receivable_Other | G95: 1281187.1 | H95: 0 | I95: =G95+H95 -> 1281187.1 | J95: 0 | K95: =I95-J95 -> 1281187.1 | L95: =I95-J95-K95 -> 0
A96: Asset | B96: 21000011 | C96: 12 | D96: Other Current Assets | E96: Balances with Government Authorities | F96: CGST Receivable | G96: 2.1211277e+08 | H96: 0 | I96: =G96+H96 -> 2.1211277e+08 | J96: =I96 -> 2.1211277e+08 | K96: =I96-J96 -> 0 | L96: =I96-J96-K96 -> 0
A97: Asset | B97: 21000012 | C97: 12 | D97: Other Current Assets | E97: Balances with Government Authorities | F97: IGST Receivable | G97: 87084777 | H97: 0 | I97: =G97+H97 -> 87084777 | J97: =I97 -> 87084777 | K97: =I97-J97 -> 0 | L97: =I97-J97-K97 -> 0
A98: Asset | B98: 21000013 | C98: 12 | D98: Other Current Assets | E98: Balances with Government Authorities | F98: SGST Receivable | G98: 2.1211277e+08 | H98: 0 | I98: =G98+H98 -> 2.1211277e+08 | J98: =I98 -> 2.1211277e+08 | K98: =I98-J98 -> 0 | L98: =I98-J98-K98 -> 0
A99: Asset | B99: 21000016 | C99: 7 | D99: Other Tax Assets (Net) | E99: Other Tax Asset (Net) | F99: TCS Receivable | G99: 24208.97 | H99: 0 | I99: =G99+H99 -> 24208.97 | J99: 0 | K99: =I99-J99 -> 24208.97 | L99: =I99-J99-K99 -> 0
A100: Asset | B100: 21000018 | C100: 12 | D100: Other Current Assets | E100: Balances with Government Authorities | F100: ITC not in GSTR 2B | G100: 1497682 | H100: 0 | I100: =G100+H100 -> 1497682 | J100: =I100 -> 1497682 | K100: =I100-J100 -> 0 | L100: =I100-J100-K100 -> 0
A101: Asset | B101: 21100004 | C101: 12 | D101: Other Current Assets | E101: Advance to employees | F101: Advances to Employees_IOU | G101: 758 | H101: 0 | I101: =G101+H101 -> 758 | J101: =I101 -> 758 | K101: =I101-J101 -> 0 | L101: =I101-J101-K101 -> 0
A102: Asset | B102: 21100008 | C102: 12 | D102: Other Current Assets | E102: Prepaid Expenses | F102: Prepaid Expenses | G102: 6901653.5 | H102: 0 | I102: =G102+H102 -> 6901653.5 | J102: =I102 -> 6901653.5 | K102: =I102-J102 -> 0 | L102: =I102-J102-K102 -> 0
A103: Liabilities | B103: 21100011 | C103: 17 | D103: Trade payables | E103: Total outstanding dues of creditors other than micro enterprises and small enterprises | F103: Advance to Vendor | G103: 1424896.1 | H103: 0 | I103: =G103+H103 -> 1424896.1 | J103: =I103 -> 1424896.1 | K103: =I103-J103 -> 0 | L103: =I103-J103-K103 -> 0
A104: Asset | B104: 21100014 | C104: =VLOOKUP(D104,[4]Input!C:D,2,0) -> 6 | D104: Other financial assets | E104: Finance lease receivable (Unsecured - considered good) | F104: IND AS - Receivable from employee (Finance Lease) | G104: 1230728.4 | H104: 0 | I104: =G104+H104 -> 1230728.4 | J104: 0 | K104: =I104-J104 -> 1230728.4 | L104: =I104-J104-K104 -> 0
A105: Income | B105: 30000000 | C105: 20 | D105: Revenue from operations | E105: Sales of Products | F105: Sales Export | G105: 0 | H105: -2896800 | I105: =G105+H105 -> -2896800 | J105: 0 | K105: 0 | L105: 0
A106: Income | B106: 30000001 | C106: 20 | D106: Revenue from operations | E106: Sales of Products | F106: Domestic Sales | G106: 0 | H106: -36004816 | I106: =G106+H106 -> -36004816 | J106: 0 | K106: 0 | L106: 0
A107: Income | B107: 30000004 | C107: 20 | D107: Revenue from operations | E107: Sales of Products | F107: Scrap Sales | G107: 0 | H107: -4811525 | I107: =G107+H107 -> -4811525 | J107: 0 | K107: 0 | L107: 0
A108: Income | B108: 30000007 | C108: 20 | D108: Revenue from operations | E108: Sales of Products | F108: Sales In transit | G108: 0 | H108: -1375000 | I108: =G108+H108 -> -1375000 | J108: 0 | K108: 0 | L108: 0 | M108: Re-Class Entry
A109: Income | B109: 30000008 | C109: 20 | D109: Revenue from operations | E109: Sales of Products | F109: Domestic Sales Inter Company | G109: 0 | H109: -69165987 | I109: =G109+H109 -> -69165987 | J109: 0 | K109: 0 | L109: 0 | M109: Re-Class Entry
A110: Income | B110: 30100001 | C110: 21 | D110: Other Income | E110: Foreign exchange gain (net) | F110: Realised Forex Gain/loss | G110: 0 | H110: -226317.04 | I110: =G110+H110 -> -226317.04 | J110: 0 | K110: 0 | L110: 0
A111: Income | B111: 30100004 | C111: 21 | D111: Other Income | E111: - From banks | F111: Interest on Bank Deposit | G111: 0 | H111: -250440 | I111: =G111+H111 -> -250440 | J111: 0 | K111: 0 | L111: 0
A112: Income | B112: 30100005 | C112: 21 | D112: Other Income | E112: - From others | F112: Other Income | G112: 0 | H112: -67940.18 | I112: =G112+H112 -> -67940.18 | J112: 0 | K112: 0 | L112: 0
...

Sheet TB BVS 31.03.26
G1: BS | H1: CFS | I1: =I4/100000 -> -23491.916 | J1: =+('TB BVS 31.03.26'!I17+'TB BVS 31.03.26'!I76)/1000 -> -142.60621
G2: 106141.52 | H2: #REF! | I2: =I3+I4 -> -1.3965967e+09
A3: =Input!B1 -> BVC Specialities Private Limited | I3: 952594932 | J3: -19095.661
A4: Trial Balance as on 31st March 2026 | I4: =SUBTOTAL(9,I7:I971) -> -2.3491916e+09 | J4: =SUBTOTAL(9,J7:J971) -> 0 | K4: =SUBTOTAL(9,K7:K971) -> 0 | L4: =SUBTOTAL(9,L7:L971) -> 0 | O4: =O5/1000000 -> 0 | P4: =P5/1000000 -> 0 | AC4: =I4/1000000 -> -2349.1916 | AD4: 3151
C5: Ind AS | D5: Ind AS | E5: Ind AS | O5: =SUBTOTAL(9,O130:O217) -> 0 | P5: =SUBTOTAL(9,P130:P217) -> 0
A6: Type | B6: Code No. | C6: Note | D6: Ind AS Head | E6: Ind AS Sub Head | F6: Particulars | G6: Debit | H6: Credit | I6: Total | J6: Current | K6: Non-Current | L6: Check | O6: Nov | P6: July
A7: Equity | B7: 10000000 | C7: 12 | D7: Equity share capital | E7: 315,940 (previous year: 315,940) equity shares of Rs 10 each fully paid up | F7: Equity Share Capital | G7: =IFERROR(VLOOKUP(B7,[5]Sheet1!$C:$M,8,0),0) -> 0 | H7: =IFERROR(VLOOKUP(B7,[5]Sheet1!$C:$M,9,0),0) -> -1597890 | I7: =G7+H7 -> -1597890 | J7: 0 | K7: 0 | M7: =VLOOKUP(B7,[6]Sheet1!$D:$M,10,0) -> -1365970 | N7: =I7-M7 -> -231920 | T7: =VLOOKUP(B7,[7]!Table1[GLAccountNo],1,0) -> #REF!
A8: Equity | B8: 10000004 | C8: 12 | D8: Other equity | E8: Pref Shar CCPS-BVCPL | F8: 0.01% Non-Cumulative CCPS | G8: =IFERROR(VLOOKUP(B8,[5]Sheet1!$C:$M,8,0),0) -> 0 | H8: =IFERROR(VLOOKUP(B8,[5]Sheet1!$C:$M,9,0),0) -> -1999973649 | I8: =G8+H8 -> -1999973649 | J8: 0 | K8: 0 | M8: =VLOOKUP(B8,[6]Sheet1!$D:$M,10,0) -> -868680 | N8: =I8-M8 -> -1999104969
A9: Equity | B9: 10100000 | C9: 13 | D9: Other equity | E9: Closing balance - Securities Premium | F9: Security Premium Account | G9: =IFERROR(VLOOKUP(B9,[5]Sheet1!$C:$M,8,0),0) -> 0 | H9: =IFERROR(VLOOKUP(B9,[5]Sheet1!$C:$M,9,0),0) -> -1.5602377e+09 | I9: =G9+H9 -> -1.5602377e+09 | J9: 0 | K9: 0 | M9: =VLOOKUP(B9,[6]Sheet1!$D:$M,10,0) -> -2.8885604e+09 | N9: =I9-M9 -> 1328322752 | P9: Opening | Q9: CY | R9: Closing
A10: Equity | B10: 10100001 | C10: 13 | D10: Other equity | E10: Closing balance - Retained Earnings | F10: Retained earnings | G10: =IFERROR(VLOOKUP(B10,[5]Sheet1!$C:$M,8,0),0) -> 2.0525541e+08 | H10: =IFERROR(VLOOKUP(B10,[5]Sheet1!$C:$M,9,0),0) -> 0 | I10: =G10+H10 -> 2.0525541e+08 | J10: 0 | K10: 0 | M10: =VLOOKUP(B10,[6]Sheet1!$D:$M,10,0) -> 2.0525541e+08 | N10: =I10-M10 -> 0 | P10: =-'BS Notes 3-18'!H243*1000 -> 2029035.2 | Q10: 386615.03 | R10: =SUBTOTAL(9,P10:Q10) -> 0
A11: Equity | B11: 10100002 | C11: 13 | D11: Other equity | E11: Closing balance - Retained Earnings | F11: Profit & Loss Account | G11: =IFERROR(VLOOKUP(B11,[5]Sheet1!$C:$M,8,0),0) -> 7941080.5 | H11: =IFERROR(VLOOKUP(B11,[5]Sheet1!$C:$M,9,0),0) -> 0 | I11: =G11+H11 -> 7941080.5 | J11: 0 | K11: 0 | M11: =VLOOKUP(B11,[6]Sheet1!$D:$M,10,0) -> 7941080.5 | N11: =I11-M11 -> 0 | P11: =I11 -> 7941080.5 | R11: =SUBTOTAL(9,P11:Q11) -> 0
A12: Equity | B12: 10100009 | C12: 13 | D12: Other equity | E12: Closing balance - Retained Earnings | F12: IND AS - Opening Balance - Retained Earnings | G12: =IFERROR(VLOOKUP(B12,[5]Sheet1!$C:$M,8,0),0) -> 0 | H12: =IFERROR(VLOOKUP(B12,[5]Sheet1!$C:$M,9,0),0) -> -38668.9 | I12: =G12+H12 -> -38668.9 | J12: 0 | K12: 0 | M12: =VLOOKUP(B12,[6]Sheet1!$D:$M,10,0) -> -38668.9 | N12: =I12-M12 -> 0 | P12: =I12 -> -38668.9 | R12: =SUBTOTAL(9,P12:Q12) -> 0
A13: Liabilities | B13: 10200015 | C13: 14 | D13: Borrowings | E13: Term Loan from Bank* | F13: IND AS - Transaction Cost Impact on TL | G13: =IFERROR(VLOOKUP(B13,[5]Sheet1!$C:$M,8,0),0) -> 2147916.4 | H13: =IFERROR(VLOOKUP(B13,[5]Sheet1!$C:$M,9,0),0) -> 0 | I13: =G13+H13 -> 2147916.4 | J13: 0 | K13: =I13-J13 -> 2147916.4 | L13: =I13-J13-K13 -> 0 | M13: =VLOOKUP(B13,[6]Sheet1!$D:$M,10,0) -> 1223808.4 | N13: =I13-M13 -> 924108
A14: Liabilities | B14: 10200016 | C14: 14 | D14: Borrowings | E14: Term Loan from Bank* | F14: TL_AXIS_ 923060053143888 | G14: =IFERROR(VLOOKUP(B14,[5]Sheet1!$C:$M,8,0),0) -> 0 | H14: =IFERROR(VLOOKUP(B14,[5]Sheet1!$C:$M,9,0),0) -> -1.7669e+09 | I14: =G14+H14 -> -1.7669e+09 | J14: -399600000 | K14: =I14-J14 -> -1.3673e+09 | L14: =I14-J14-K14 -> 0 | M14: =VLOOKUP(B14,[6]Sheet1!$D:$M,10,0) -> -2000000000 | N14: =I14-M14 -> 2.331e+08
A15: Liabilities | B15: 10200018 | C15: 14 | D15: Borrowings | E15: Term Loan from Bank* | F15: TL_AXIS_924060051723539 | G15: =IFERROR(VLOOKUP(B15,[5]Sheet1!$C:$M,8,0),0) -> 0 | H15: =IFERROR(VLOOKUP(B15,[5]Sheet1!$C:$M,9,0),0) -> -362015481 | I15: =G15+H15 -> -362015481 | J15: -80400000 | K15: =I15-J15 -> -281615481 | L15: =I15-J15-K15 -> 0 | M15: =VLOOKUP(B15,[6]Sheet1!$D:$M,10,0) -> -400000000 | N15: =I15-M15 -> 37984519
A16: Liabilities | B16: 10300002 | C16: 14 | D16: Borrowings | E16: Term Loan from Bank* | F16: TL_HDFC_02400930000746 | G16: =IFERROR(VLOOKUP(B16,[5]Sheet1!$C:$M,8,0),0) -> 0 | H16: =IFERROR(VLOOKUP(B16,[5]Sheet1!$C:$M,9,0),0) -> -3.4999916e+08 | I16: =G16+H16 -> -3.4999916e+08 | J16: -99999761 | K16: =I16-J16 -> -2.499994e+08 | L16: =I16-J16-K16 -> 0 | M16: =VLOOKUP(B16,[6]Sheet1!$D:$M,10,0) -> -3.9999904e+08 | N16: =I16-M16 -> 49999880
A17: Liabilities | B17: 10400001 | C17: 16 | D17: Deferred Tax Liabilities (Net) | E17: Deferred Tax | F17: IND AS - Deferred Tax Liability | G17: 0 | H17: -238523.49 | I17: =G17+H17 -> -238523.49 | K17: =I17-J17 -> -238523.49 | L17: =I17-J17-K17 -> 0 | M17: =VLOOKUP(B17,[6]Sheet1!$D:$M,10,0) -> -238523.49 | N17: =I17-M17 -> 0
A18: Liabilities | B18: 10500000 | C18: 15 | D18: Provisions | E18: Provision for employee benefits - Gratuity | F18: Provision for Gratuity | G18: =IFERROR(VLOOKUP(B18,[5]Sheet1!$C:$M,8,0),0) -> 0 | H18: =IFERROR(VLOOKUP(B18,[5]Sheet1!$C:$M,9,0),0) -> -4499741 | I18: =G18+H18 -> -4499741 | J18: -443965 | K18: =I18-J18 -> -4055776 | L18: =I18-J18-K18 -> 0 | M18: =VLOOKUP(B18,[6]Sheet1!$D:$M,10,0) -> -2120219 | N18: =I18-M18 -> -2379522
A19: Liabilities | B19: 10500001 | C19: 15 | D19: Provisions | E19: Provision for compensated absences | F19: Provision for Leave Salary | G19: =IFERROR(VLOOKUP(B19,[5]Sheet1!$C:$M,8,0),0) -> 0 | H19: =IFERROR(VLOOKUP(B19,[5]Sheet1!$C:$M,9,0),0) -> -4772879 | I19: =G19+H19 -> -4772879 | J19: -824137 | K19: =I19-J19 -> -3948742 | L19: =I19-J19-K19 -> 0 | M19: =VLOOKUP(B19,[6]Sheet1!$D:$M,10,0) -> -2607951 | N19: =I19-M19 -> -2164928
A20: Liabilities | B20: 10600010 | C20: 14 | D20: Borrowings | E20: Unsecured loan from related parties | F20: Best Value Chem Pvt Ltd. | G20: =IFERROR(VLOOKUP(B20,[5]Sheet1!$C:$M,8,0),0) -> 0 | H20: =IFERROR(VLOOKUP(B20,[5]Sheet1!$C:$M,9,0),0) -> -0.41 | I20: =G20+H20 -> -0.41 | J20: 0 | K20: 0 | M20: =VLOOKUP(B20,[6]Sheet1!$D:$M,10,0) -> -2.6596834e+08 | N20: =I20-M20 -> 265968343
A21: Liabilities | B21: 10800000 | C21: 17 | D21: Trade payables | E21: Total outstanding dues of creditors other than micro enterprises and small enterprises | F21: Payable - Raw Material Import | G21: =IFERROR(VLOOKUP(B21,[5]Sheet1!$C:$M,8,0),0) -> 0 | H21: =IFERROR(VLOOKUP(B21,[5]Sheet1!$C:$M,9,0),0) -> -1.263965e+08 | I21: =G21+H21 -> -1.263965e+08 | J21: 0 | K21: 0 | M21: =VLOOKUP(B21,[6]Sheet1!$D:$M,10,0) -> -84434755 | N21: =I21-M21 -> -41961748
A22: Liabilities | B22: 10800001 | C22: 17 | D22: Trade payables | E22: Total outstanding dues of creditors other than micro enterprises and small enterprises | F22: Payable - Raw Material Domestic | G22: =IFERROR(VLOOKUP(B22,[5]Sheet1!$C:$M,8,0),0) -> 0 | H22: =IFERROR(VLOOKUP(B22,[5]Sheet1!$C:$M,9,0),0) -> -1.5433134e+08 | I22: =G22+H22 -> -1.5433134e+08 | J22: 0 | K22: 0 | M22: =VLOOKUP(B22,[6]Sheet1!$D:$M,10,0) -> -99935999 | N22: =I22-M22 -> -54395339 | Q22: ='[8]BVC Sale'!$D$272*0 -> 0
A23: Liabilities | B23: 10800002 | C23: 17 | D23: Trade payables | E23: Total outstanding dues of creditors other than micro enterprises and small enterprises | F23: Payable - Packing Material | G23: =IFERROR(VLOOKUP(B23,[5]Sheet1!$C:$M,8,0),0) -> 0 | H23: =IFERROR(VLOOKUP(B23,[5]Sheet1!$C:$M,9,0),0) -> -14985765 | I23: =G23+H23 -> -14985765 | J23: 0 | K23: 0 | M23: =VLOOKUP(B23,[6]Sheet1!$D:$M,10,0) -> -7862613.2 | N23: =I23-M23 -> -7123152.1 | AD23: 6106184 | AE23: Packing Material Adj - Out of books
A24: Liabilities | B24: 10800003 | C24: 17 | D24: Trade payables | E24: Total outstanding dues of creditors other than micro enterprises and small enterprises | F24: Payable - Fuel | G24: =IFERROR(VLOOKUP(B24,[5]Sheet1!$C:$M,8,0),0) -> 0 | H24: =IFERROR(VLOOKUP(B24,[5]Sheet1!$C:$M,9,0),0) -> -18468224 | I24: =G24+H24 -> -18468224 | J24: 0 | K24: 0 | M24: =VLOOKUP(B24,[6]Sheet1!$D:$M,10,0) -> -7541013.5 | N24: =I24-M24 -> -10927211
A25: Liabilities | B25: 10800004 | C25: 17 | D25: Trade payables | E25: Total outstanding dues of creditors other than micro enterprises and small enterprises | F25: Payable - Others | G25: =IFERROR(VLOOKUP(B25,[5]Sheet1!$C:$M,8,0),0) -> 0 | H25: =IFERROR(VLOOKUP(B25,[5]Sheet1!$C:$M,9,0),0) -> -6.7466306e+08 | I25: =G25+H25 -> -6.7466306e+08 | J25: 0 | K25: 0 | M25: =VLOOKUP(B25,[6]Sheet1!$D:$M,10,0) -> -3.1699296e+08 | N25: =I25-M25 -> -3.5767009e+08
A26: Liabilities | B26: 10800005 | C26: 18 | D26: Other financial liabilities | E26: Employee benefits payable | F26: Payables - Employees | G26: =IFERROR(VLOOKUP(B26,[5]Sheet1!$C:$M,8,0),0) -> 42051.22 | H26: =IFERROR(VLOOKUP(B26,[5]Sheet1!$C:$M,9,0),0) -> 0 | I26: =G26+H26 -> 42051.22 | J26: 0 | K26: 0 | M26: =VLOOKUP(B26,[6]Sheet1!$D:$M,10,0) -> 35924.22 | N26: =I26-M26 -> 6127
A27: Liabilities | B27: 10900000 | C27: 17 | D27: Trade payables | E27: Total outstanding dues of creditors other than micro enterprises and small enterprises | F27: Provision_Other Expenses | G27: =IFERROR(VLOOKUP(B27,[5]Sheet1!$C:$M,8,0),0) -> 0 | H27: =IFERROR(VLOOKUP(B27,[5]Sheet1!$C:$M,9,0),0) -> -6785728.3 | I27: =G27+H27 -> -6785728.3 | J27: 0 | K27: 0 | M27: =VLOOKUP(B27,[6]Sheet1!$D:$M,10,0) -> -8925974 | N27: =I27-M27 -> 2140245.7
A28: Liabilities | B28: 20100001 | C28: 17 | D28: Trade payables | E28: Total outstanding dues of creditors other than micro enterprises and small enterprises | F28: Capital Advances | G28: =IFERROR(VLOOKUP(B28,[5]Sheet1!$C:$M,8,0),0) -> 1224019.4 | H28: =IFERROR(VLOOKUP(B28,[5]Sheet1!$C:$M,9,0),0) -> 0 | I28: =G28+H28 -> 1224019.4 | J28: 0 | K28: 0 | M28: =VLOOKUP(B28,[6]Sheet1!$D:$M,10,0) -> 8778690 | N28: =I28-M28 -> -7554670.6
A29: Liabilities | B29: 10900003 | C29: 19 | D29: Other Current Liabilities | E29: Statutory liabilities | F29: Provision_PF and ESIC Contribution by Company | G29: =IFERROR(VLOOKUP(B29,[5]Sheet1!$C:$M,8,0),0) -> 0 | H29: =IFERROR(VLOOKUP(B29,[5]Sheet1!$C:$M,9,0),0) -> -461147 | I29: =G29+H29 -> -461147 | J29: 0 | K29: 0 | M29: =VLOOKUP(B29,[6]Sheet1!$D:$M,10,0) -> -311807 | N29: =I29-M29 -> -149340
A30: Liabilities | B30: 10900018 | C30: 18 | D30: Other financial liabilities | E30: Employee benefits payable | F30: Salary Payable | G30: =IFERROR(VLOOKUP(B30,[5]Sheet1!$C:$M,8,0),0) -> 0 | H30: =IFERROR(VLOOKUP(B30,[5]Sheet1!$C:$M,9,0),0) -> -119680.01 | I30: =G30+H30 -> -119680.01 | J30: 0 | K30: 0 | M30: =VLOOKUP(B30,[6]Sheet1!$D:$M,10,0) -> -9835879.2 | N30: =I30-M30 -> 9716199.2
A31: Liabilities | B31: 11000001 | C31: 19 | D31: Other Current Liabilities | E31: Statutory liabilities | F31: TDS_Professional and Consulting_194J | G31: =IFERROR(VLOOKUP(B31,[5]Sheet1!$C:$M,8,0),0) -> 0 | H31: =IFERROR(VLOOKUP(B31,[5]Sheet1!$C:$M,9,0),0) -> -382362.06 | I31: =G31+H31 -> -382362.06 | J31: 0 | K31: 0 | M31: =VLOOKUP(B31,[6]Sheet1!$D:$M,10,0) -> 53941.44 | N31: =I31-M31 -> -436303.5
A32: Liabilities | B32: 11000002 | C32: 19 | D32: Other Current Liabilities | E32: Statutory liabilities | F32: TDS_Contractors_194C | G32: =IFERROR(VLOOKUP(B32,[5]Sheet1!$C:$M,8,0),0) -> 0 | H32: =IFERROR(VLOOKUP(B32,[5]Sheet1!$C:$M,9,0),0) -> -3257917.5 | I32: =G32+H32 -> -3257917.5 | J32: 0 | K32: 0 | M32: =VLOOKUP(B32,[6]Sheet1!$D:$M,10,0) -> -336176.31 | N32: =I32-M32 -> -2921741.2
A33: Liabilities | B33: 11000003 | C33: 19 | D33: Other Current Liabilities | E33: Statutory liabilities | F33: TDS_Interest on borrowing_194A | G33: =IFERROR(VLOOKUP(B33,[5]Sheet1!$C:$M,8,0),0) -> 0 | H33: =IFERROR(VLOOKUP(B33,[5]Sheet1!$C:$M,9,0),0) -> -0.17 | I33: =G33+H33 -> -0.17 | J33: 0 | K33: 0 | M33: =VLOOKUP(B33,[6]Sheet1!$D:$M,10,0) -> 501331.83 | N33: =I33-M33 -> -501332
A34: Liabilities | B34: 11000005 | C34: 19 | D34: Other Current Liabilities | E34: Statutory liabilities | F34: TDS_Rent_194I | G34: =IFERROR(VLOOKUP(B34,[5]Sheet1!$C:$M,8,0),0) -> 0 | H34: =IFERROR(VLOOKUP(B34,[5]Sheet1!$C:$M,9,0),0) -> -75369 | I34: =G34+H34 -> -75369 | J34: 0 | K34: 0 | M34: =VLOOKUP(B34,[6]Sheet1!$D:$M,10,0) -> 9503 | N34: =I34-M34 -> -84872
A35: Liabilities | B35: 11000006 | C35: 19 | D35: Other Current Liabilities | E35: Statutory liabilities | F35: TDS_Purchase on Goods_194Q | G35: =IFERROR(VLOOKUP(B35,[5]Sheet1!$C:$M,8,0),0) -> 0 | H35: =IFERROR(VLOOKUP(B35,[5]Sheet1!$C:$M,9,0),0) -> -224723.73 | I35: =G35+H35 -> -224723.73 | J35: 0 | K35: 0 | M35: =VLOOKUP(B35,[6]Sheet1!$D:$M,10,0) -> -63397.5 | N35: =I35-M35 -> -161326.23
... A67: Asset | B67: 20100004 | C67: 3 | D67: Property, Plant and Equipment | E67: Capital work-in-progress | F67: AUC Cost | G67: =IFERROR(VLOOKUP(B67,[5]Sheet1!$C:$M,8,0),0) -> 41000 | H67: =IFERROR(VLOOKUP(B67,[5]Sheet1!$C:$M,9,0),0) -> 0 | I67: =G67+H67 -> 41000 | J67: 0 | K67: 0 | M67: =VLOOKUP(B67,[6]Sheet1!$D:$M,10,0) -> 41000 | N67: =I67-M67 -> 0
A68: Asset | B68: 40700034 | C68: 3 | D68: Property, Plant and Equipment | E68: Capital work-in-progress | F68: Project Expenses | G68: =IFERROR(VLOOKUP(B68,[5]Sheet1!$C:$M,8,0),0) -> 0 | H68: =IFERROR(VLOOKUP(B68,[5]Sheet1!$C:$M,9,0),0) -> 0 | I68: =G68+H68 -> 0 | J68: 0 | K68: 0 | M68: =VLOOKUP(B68,[6]Sheet1!$D:$M,10,0) -> -32419216 | N68: =I68-M68 -> 32419216 | Q68: =VLOOKUP(B68,[7]!Table1[GLAccountNo],1,0) -> #REF!
A69: Asset | B69: 20000005 | C69: 3 | D69: Property, Plant and Equipment | E69: Office Equipment | F69: Office Equipment | G69: =IFERROR(VLOOKUP(B69,[5]Sheet1!$C:$M,8,0),0) -> 19595727 | H69: =IFERROR(VLOOKUP(B69,[5]Sheet1!$C:$M,9,0),0) -> 0 | I69: =G69+H69 -> 19595727 | J69: 0 | K69: 0 | M69: =VLOOKUP(B69,[6]Sheet1!$D:$M,10,0) -> 19595727 | N69: =I69-M69 -> 0
A70: Asset | B70: 20000009 | C70: 3 | D70: Property, Plant and Equipment | E70: Furniture & Fixture | F70: Furniture & Fixture | G70: =IFERROR(VLOOKUP(B70,[5]Sheet1!$C:$M,8,0),0) -> 20587570 | H70: =IFERROR(VLOOKUP(B70,[5]Sheet1!$C:$M,9,0),0) -> 0 | I70: =G70+H70 -> 20587570 | J70: 0 | K70: 0 | M70: =VLOOKUP(B70,[6]Sheet1!$D:$M,10,0) -> 20587570 | N70: =I70-M70 -> 0
A71: Asset | B71: 20000011 | C71: 3 | D71: Property, Plant and Equipment | E71: Electrical Fittings | F71: Electrical Fittings | G71: =IFERROR(VLOOKUP(B71,[5]Sheet1!$C:$M,8,0),0) -> 1.3395587e+08 | H71: =IFERROR(VLOOKUP(B71,[5]Sheet1!$C:$M,9,0),0) -> 0 | I71: =G71+H71 -> 1.3395587e+08 | J71: 0 | K71: 0 | M71: =VLOOKUP(B71,[6]Sheet1!$D:$M,10,0) -> 1.3349476e+08 | N71: =I71-M71 -> 461110.11
A72: Asset | B72: 20000015 | C72: 3 | D72: Property, Plant and Equipment | E72: Intangible Assets | F72: Computer Software | G72: =IFERROR(VLOOKUP(B72,[5]Sheet1!$C:$M,8,0),0) -> 4679369.2 | H72: =IFERROR(VLOOKUP(B72,[5]Sheet1!$C:$M,9,0),0) -> 0 | I72: =G72+H72 -> 4679369.2 | J72: 0 | K72: 0 | M72: =VLOOKUP(B72,[6]Sheet1!$D:$M,10,0) -> 4679369.2 | N72: =I72-M72 -> 0
A73: Asset | B73: 20100003 | C73: 3 | D73: Property, Plant and Equipment | E73: Capital work-in-progress | F73: Capita Adv Audit Adj | G73: =IFERROR(VLOOKUP(B73,[5]Sheet1!$C:$M,8,0),0) -> 0 | H73: =IFERROR(VLOOKUP(B73,[5]Sheet1!$C:$M,9,0),0) -> -41060 | I73: =G73+H73 -> -41060 | J73: 0 | K73: 0 | M73: =VLOOKUP(B73,[6]Sheet1!$D:$M,10,0) -> -41060 | N73: =I73-M73 -> 0
A74: Asset | B74: 20300000 | C74: 5 | D74: Other financial assets | E74: Security deposits | F74: Deposit_Other | G74: =IFERROR(VLOOKUP(B74,[5]Sheet1!$C:$M,8,0),0) -> 34062382 | H74: =IFERROR(VLOOKUP(B74,[5]Sheet1!$C:$M,9,0),0) -> 0 | I74: =G74+H74 -> 34062382 | J74: 0 | K74: 0 | M74: =VLOOKUP(B74,[6]Sheet1!$D:$M,10,0) -> 28163904 | N74: =I74-M74 -> 5898477.9
A75: Asset | B75: 20300004 | C75: 5 | D75: Other financial assets | E75: Security deposits | F75: Deposit_Prohibition and Excise | G75: =IFERROR(VLOOKUP(B75,[5]Sheet1!$C:$M,8,0),0) -> 1000 | H75: =IFERROR(VLOOKUP(B75,[5]Sheet1!$C:$M,9,0),0) -> 0 | I75: =G75+H75 -> 1000 | J75: 0 | K75: 0 | M75: =VLOOKUP(B75,[6]Sheet1!$D:$M,10,0) -> 1000 | N75: =I75-M75 -> 0
A76: Liabilities | B76: 20400001 | C76: 16 | D76: Deferred Tax Liabilities (Net) | E76: Deferred Tax Liabilities (Net) | F76: IND AS - Deferred Tax Assets | G76: 95917.28 | H76: 0 | I76: =G76+H76 -> 95917.28 | K76: =I76-J76 -> 95917.28 | L76: =I76-J76-K76 -> 0 | M76: =VLOOKUP(B76,[6]Sheet1!$D:$M,10,0) -> 95917.28 | N76: =I76-M76 -> 0
A77: Asset | B77: 20500000 | C77: 8 | D77: Inventories | E77: Raw materials** | F77: Raw Material Stock | G77: =IFERROR(VLOOKUP(B77,[5]Sheet1!$C:$M,8,0),0) -> 1.5218483e+08 | H77: =IFERROR(VLOOKUP(B77,[5]Sheet1!$C:$M,9,0),0) -> 0 | I77: =G77+H77 -> 1.5218483e+08 | J77: 0 | K77: 0 | M77: =VLOOKUP(B77,[6]Sheet1!$D:$M,10,0) -> 1.1644048e+08 | N77: =I77-M77 -> 35744343
A78: Asset | B78: 20500001 | C78: 8 | D78: Inventories | E78: Packing material | F78: Packing Material Stock | G78: =IFERROR(VLOOKUP(B78,[5]Sheet1!$C:$M,8,0),0) -> 1251509 | H78: =IFERROR(VLOOKUP(B78,[5]Sheet1!$C:$M,9,0),0) -> 0 | I78: =G78+H78 -> 1251509 | J78: 0 | K78: 0 | M78: =VLOOKUP(B78,[6]Sheet1!$D:$M,10,0) -> 5085105.7 | N78: =I78-M78 -> -3833596.7
A79: Asset | B79: 20500002 | C79: 8 | D79: Inventories | E79: Stores and spares | F79: Fuel Stock | G79: =IFERROR(VLOOKUP(B79,[5]Sheet1!$C:$M,8,0),0) -> 4992246 | H79: =IFERROR(VLOOKUP(B79,[5]Sheet1!$C:$M,9,0),0) -> 0 | I79: =G79+H79 -> 4992246 | J79: 0 | K79: 0 | M79: =VLOOKUP(B79,[6]Sheet1!$D:$M,10,0) -> 2473584.6 | N79: =I79-M79 -> 2518661.4
A80: Asset | B80: 20500003 | C80: 8 | D80: Inventories | E80: Work-in-progress | F80: SFG Stock in Plants | G80: =IFERROR(VLOOKUP(B80,[5]Sheet1!$C:$M,8,0),0) -> 1.8632331e+08 | H80: =IFERROR(VLOOKUP(B80,[5]Sheet1!$C:$M,9,0),0) -> 0 | I80: =G80+H80 -> 1.8632331e+08 | J80: 0 | K80: 0 | M80: =VLOOKUP(B80,[6]Sheet1!$D:$M,10,0) -> 1.4725579e+08 | N80: =I80-M80 -> 39067510
A81: Asset | B81: 20500005 | C81: 8 | D81: Inventories | E81: Stores and spares | F81: Store and Spares - | G81: =IFERROR(VLOOKUP(B81,[5]Sheet1!$C:$M,8,0),0) -> 31250536 | H81: =IFERROR(VLOOKUP(B81,[5]Sheet1!$C:$M,9,0),0) -> 0 | I81: =G81+H81 -> 31250536 | J81: 0 | K81: 0 | M81: =VLOOKUP(B81,[6]Sheet1!$D:$M,10,0) -> 11148096 | N81: =I81-M81 -> 20102441
A82: Asset | B82: 20500006 | C82: 8 | D82: Inventories | E82: Finished goods* | F82: Goods In Transit - Sales | G82: =IFERROR(VLOOKUP(B82,[5]Sheet1!$C:$M,8,0),0) -> 2.2735989e+08 | H82: =IFERROR(VLOOKUP(B82,[5]Sheet1!$C:$M,9,0),0) -> 0 | I82: =G82+H82 -> 2.2735989e+08 | J82: 0 | K82: 0 | M82: =VLOOKUP(B82,[6]Sheet1!$D:$M,10,0) -> 0 | N82: =I82-M82 -> 2.2735989e+08
A83: Asset | B83: 20500008 | C83: 8 | D83: Inventories | E83: Work-in-progress | F83: Inventory_Manual Entry | G83: =IFERROR(VLOOKUP(B83,[5]Sheet1!$C:$M,8,0),0) -> 0 | H83: =IFERROR(VLOOKUP(B83,[5]Sheet1!$C:$M,9,0),0) -> -3185656.1 | I83: =G83+H83 -> -3185656.1 | J83: 0 | K83: 0 | M83: =VLOOKUP(B83,[6]Sheet1!$D:$M,10,0) -> -117896 | N83: =I83-M83 -> -3067760.1 | R83: =-R181 -> -18995242
A84: Asset | B84: 20600001 | C84: 9 | D84: Trade receivables | E84: Considered good - unsecured | F84: Receivables-Domestic | G84: =IFERROR(VLOOKUP(B84,[5]Sheet1!$C:$M,8,0),0) -> 1.0866381e+08 | H84: =IFERROR(VLOOKUP(B84,[5]Sheet1!$C:$M,9,0),0) -> 0 | I84: =G84+H84 -> 1.0866381e+08 | J84: 0 | K84: 0 | M84: =VLOOKUP(B84,[6]Sheet1!$D:$M,10,0) -> 62518613 | N84: =I84-M84 -> 46145194
A85: Asset | B85: 20600004 | C85: 9 | D85: Trade receivables | E85: Considered good - unsecured | F85: Receivables- Scrap | G85: =IFERROR(VLOOKUP(B85,[5]Sheet1!$C:$M,8,0),0) -> 162126.5 | H85: =IFERROR(VLOOKUP(B85,[5]Sheet1!$C:$M,9,0),0) -> 0 | I85: =G85+H85 -> 162126.5 | J85: 0 | K85: 0 | M85: =VLOOKUP(B85,[6]Sheet1!$D:$M,10,0) -> 561124.7 | N85: =I85-M85 -> -398998.2
A86: Asset | B86: 20600006 | C86: 9 | D86: Trade receivables | E86: Considered good - unsecured | F86: Receivables- GIT | G86: =IFERROR(VLOOKUP(B86,[5]Sheet1!$C:$M,8,0),0) -> 0 | H86: =IFERROR(VLOOKUP(B86,[5]Sheet1!$C:$M,9,0),0) -> -2.6538313e+08 | I86: =G86+H86 -> -2.6538313e+08 | J86: 0 | K86: 0 | M86: =VLOOKUP(B86,[6]Sheet1!$D:$M,10,0) -> #N/A | N86: =I86-M86 -> #N/A
A87: Asset | B87: 20600009 | C87: 9 | D87: Trade receivables | E87: Considered good - unsecured | F87: Receivables- Advance | G87: =IFERROR(VLOOKUP(B87,[5]Sheet1!$C:$M,8,0),0) -> 0 | H87: =IFERROR(VLOOKUP(B87,[5]Sheet1!$C:$M,9,0),0) -> -901805.08 | I87: =G87+H87 -> -901805.08 | J87: 0 | K87: 0 | M87: =VLOOKUP(B87,[6]Sheet1!$D:$M,10,0) -> -3393920.4 | N87: =I87-M87 -> 2492115.3
A88: Asset | B88: 20800110 | C88: 10 | D88: Cash & Cash Equivalents | E88: Balance with banks | F88: CA_HDFC_57500000732637 | G88: =IFERROR(VLOOKUP(B88,[5]Sheet1!$C:$M,8,0),0) -> 475424.48 | H88: =IFERROR(VLOOKUP(B88,[5]Sheet1!$C:$M,9,0),0) -> 0 | I88: =G88+H88 -> 475424.48 | J88: 0 | K88: 0 | M88: =VLOOKUP(B88,[6]Sheet1!$D:$M,10,0) -> 475424.48 | N88: =I88-M88 -> 0
A89: Asset | B89: 20800111 | C89: 10 | D89: Cash & Cash Equivalents | E89: Balance with banks | F89: CA_HDFC_57500000732637 | G89: =IFERROR(VLOOKUP(B89,[5]Sheet1!$C:$M,8,0),0) -> 3.5100398e+09 | H89: =IFERROR(VLOOKUP(B89,[5]Sheet1!$C:$M,9,0),0) -> 0 | I89: =G89+H89 -> 3.5100398e+09 | J89: 0 | K89: 0 | M89: =VLOOKUP(B89,[6]Sheet1!$D:$M,10,0) -> 1.4281416e+09 | N89: =I89-M89 -> 2.0818982e+09
A90: Asset | B90: 20800112 | C90: 10 | D90: Cash & Cash Equivalents | E90: Balance with banks | F90: CA_HDFC_57500000732637 | G90: =IFERROR(VLOOKUP(B90,[5]Sheet1!$C:$M,8,0),0) -> 0 | H90: =IFERROR(VLOOKUP(B90,[5]Sheet1!$C:$M,9,0),0) -> -3.5074381e+09 | I90: =G90+H90 -> -3.5074381e+09 | J90: 0 | K90: 0 | M90: =VLOOKUP(B90,[6]Sheet1!$D:$M,10,0) -> -1.4742666e+09 | N90: =I90-M90 -> -2.0331715e+09
A91: Asset | B91: 20800121 | C91: 10 | D91: Cash & Cash Equivalents | E91: Balance with banks | F91: CA_Axis_923020022099965 | G91: =IFERROR(VLOOKUP(B91,[5]Sheet1!$C:$M,8,0),0) -> 6.3245968e+09 | H91: =IFERROR(VLOOKUP(B91,[5]Sheet1!$C:$M,9,0),0) -> 0 | I91: =G91+H91 -> 6.3245968e+09 | J91: 0 | K91: 0 | M91: =VLOOKUP(B91,[6]Sheet1!$D:$M,10,0) -> 5.7016109e+09 | N91: =I91-M91 -> 6.2298593e+08
A92: Asset | B92: 20800122 | C92: 10 | D92: Cash & Cash Equivalents | E92: Balance with banks | F92: CA_Axis_923020022099965 | G92: =IFERROR(VLOOKUP(B92,[5]Sheet1!$C:$M,8,0),0) -> 0 | H92: =IFERROR(VLOOKUP(B92,[5]Sheet1!$C:$M,9,0),0) -> -6.3245968e+09 | I92: =G92+H92 -> -6.3245968e+09 | J92: 0 | K92: 0 | M92: =VLOOKUP(B92,[6]Sheet1!$D:$M,10,0) -> -5.6983986e+09 | N92: =I92-M92 -> -6.261982e+08
A93: Asset | B93: 20900003 | C93: 5 | D93: Cash & Cash Equivalents | E93: Deposits with original maturity for more than 3 months and less than 12 Months | F93: FD_Axis | G93: =IFERROR(VLOOKUP(B93,[5]Sheet1!$C:$M,8,0),0) -> 5409283 | H93: =IFERROR(VLOOKUP(B93,[5]Sheet1!$C:$M,9,0),0) -> 0 | I93: =G93+H93 -> 5409283 | J93: 0 | K93: 0 | M93: =VLOOKUP(B93,[6]Sheet1!$D:$M,10,0) -> 5194985 | N93: =I93-M93 -> 214298
A94: Asset | B94: 21000003 | C94: 6 | D94: Other Tax Assets (Net) | E94: Other Tax Asset (Net) | F94: TDS Receiveable_194Q | G94: =IFERROR(VLOOKUP(B94,[5]Sheet1!$C:$M,8,0),0) -> 594710.96 | H94: =IFERROR(VLOOKUP(B94,[5]Sheet1!$C:$M,9,0),0) -> 0 | I94: =G94+H94 -> 594710.96 | J94: 0 | K94: 0 | M94: =VLOOKUP(B94,[6]Sheet1!$D:$M,10,0) -> 36492 | N94: =I94-M94 -> 558218.96
A95: Asset | B95: 21000004 | C95: 6 | D95: Other Tax Assets (Net) | E95: Other Tax Asset (Net) | F95: TDS Receivable_Other | G95: =IFERROR(VLOOKUP(B95,[5]Sheet1!$C:$M,8,0),0) -> 15229.08 | H95: =IFERROR(VLOOKUP(B95,[5]Sheet1!$C:$M,9,0),0) -> 0 | I95: =G95+H95 -> 15229.08 | J95: 0 | K95: 0 | M95: =VLOOKUP(B95,[6]Sheet1!$D:$M,10,0) -> 1298777.1 | N95: =I95-M95 -> -1283548
A96: Asset | B96: 21000011 | C96: 11 | D96: Other Current Assets | E96: Balances with Government Authorities | F96: CGST Receivable | G96: =IFERROR(VLOOKUP(B96,[5]Sheet1!$C:$M,8,0),0) -> 2.2000979e+08 | H96: =IFERROR(VLOOKUP(B96,[5]Sheet1!$C:$M,9,0),0) -> 0 | I96: =G96+H96 -> 2.2000979e+08 | J96: 0 | K96: 0 | M96: =VLOOKUP(B96,[6]Sheet1!$D:$M,10,0) -> 2.3655336e+08 | N96: =I96-M96 -> -16543572 | AC96: 2.1211277e+08
A97: Asset | B97: 21000012 | C97: 11 | D97: Other Current Assets | E97: Balances with Government Authorities | F97: IGST Receivable | G97: =IFERROR(VLOOKUP(B97,[5]Sheet1!$C:$M,8,0),0) -> 0 | H97: =IFERROR(VLOOKUP(B97,[5]Sheet1!$C:$M,9,0),0) -> -4.78 | I97: =G97+H97 -> -4.78 | J97: 0 | K97: 0 | M97: =VLOOKUP(B97,[6]Sheet1!$D:$M,10,0) -> 75621196 | N97: =I97-M97 -> -75621201 | AC97: 87084777
A98: Asset | B98: 21000013 | C98: 11 | D98: Other Current Assets | E98: Balances with Government Authorities | F98: SGST Receivable | G98: =IFERROR(VLOOKUP(B98,[5]Sheet1!$C:$M,8,0),0) -> 3.025804e+08 | H98: =IFERROR(VLOOKUP(B98,[5]Sheet1!$C:$M,9,0),0) -> 0 | I98: =G98+H98 -> 3.025804e+08 | J98: 0 | K98: 0 | M98: =VLOOKUP(B98,[6]Sheet1!$D:$M,10,0) -> 2.3655336e+08 | N98: =I98-M98 -> 66027033 | AC98: 2.1211277e+08
A99: Asset | B99: 21000016 | C99: 6 | D99: Other Tax Assets (Net) | E99: Other Tax Asset (Net) | F99: TCS Receivable | G99: =IFERROR(VLOOKUP(B99,[5]Sheet1!$C:$M,8,0),0) -> 0 | H99: =IFERROR(VLOOKUP(B99,[5]Sheet1!$C:$M,9,0),0) -> -0.42 | I99: =G99+H99 -> -0.42 | J99: 0 | K99: 0 | M99: =VLOOKUP(B99,[6]Sheet1!$D:$M,10,0) -> 38961.16 | N99: =I99-M99 -> -38961.58 | AC99: 1497682
A100: Asset | B100: 21000018 | C100: 11 | D100: Other Current Assets | E100: Balances with Government Authorities | F100: ITC not in GSTR 2B | G100: =IFERROR(VLOOKUP(B100,[5]Sheet1!$C:$M,8,0),0) -> 3547736 | H100: =IFERROR(VLOOKUP(B100,[5]Sheet1!$C:$M,9,0),0) -> 0 | I100: =G100+H100 -> 3547736 | J100: 0 | K100: 0 | M100: =VLOOKUP(B100,[6]Sheet1!$D:$M,10,0) -> 2582494 | N100: =I100-M100 -> 965242 | AC100: 1497682
A101: Asset | B101: 21100004 | C101: 11 | D101: Other Current Assets | E101: Advance to employees | F101: Advances to Employees_IOU | G101: =IFERROR(VLOOKUP(B101,[5]Sheet1!$C:$M,8,0),0) -> 0 | H101: =IFERROR(VLOOKUP(B101,[5]Sheet1!$C:$M,9,0),0) -> 0 | I101: =G101+H101 -> 0 | J101: 0 | K101: 0 | M101: =VLOOKUP(B101,[6]Sheet1!$D:$M,10,0) -> 758 | N101: =I101-M101 -> -758
A102: Asset | B102: 21100008 | C102: 11 | D102: Other Current Assets | E102: Prepaid Expenses | F102: Prepaid Expenses | G102: =IFERROR(VLOOKUP(B102,[5]Sheet1!$C:$M,8,0),0) -> 16044032 | H102: =IFERROR(VLOOKUP(B102,[5]Sheet1!$C:$M,9,0),0) -> 0 | I102: =G102+H102 -> 16044032 | J102: 317019 | K102: 7370695.5 | M102: =VLOOKUP(B102,[6]Sheet1!$D:$M,10,0) -> 4976027.6 | N102: =I102-M102 -> 11068004
A103: Liabilities | B103: 21100011 | C103: 17 | D103: Trade payables | E103: Total outstanding dues of creditors other than micro enterprises and small enterprises | F103: Advance to Vendor | G103: =IFERROR(VLOOKUP(B103,[5]Sheet1!$C:$M,8,0),0) -> 2145379.2 | H103: =IFERROR(VLOOKUP(B103,[5]Sheet1!$C:$M,9,0),0) -> 0 | I103: =G103+H103 -> 2145379.2 | J103: 0 | K103: 0 | M103: =VLOOKUP(B103,[6]Sheet1!$D:$M,10,0) -> 11377080 | N103: =I103-M103 -> -9231700.4
A104: Asset | B104: 21100014 | C104: 5 | D104: Other financial assets | E104: Finance lease receivable (Unsecured - considered good) | F104: IND AS - Receivable from employee (Finance Lease) | G104: =IFERROR(VLOOKUP(B104,[5]Sheet1!$C:$M,8,0),0) -> 905891.45 | H104: =IFERROR(VLOOKUP(B104,[5]Sheet1!$C:$M,9,0),0) -> 0 | I104: =G104+H104 -> 905891.45 | J104: 0 | K104: 0 | M104: =VLOOKUP(B104,[6]Sheet1!$D:$M,10,0) -> 1141673.9 | N104: =I104-M104 -> -235782.45
A105: Income | B105: 30000000 | C105: 20 | D105: Revenue from operations | E105: Sales of Products | F105: Sales Export | G105: =IFERROR(VLOOKUP(B105,[5]Sheet1!$C:$M,8,0),0) -> 0 | H105: =IFERROR(VLOOKUP(B105,[5]Sheet1!$C:$M,9,0),0) -> -1.0367137e+09 | I105: =G105+H105 -> -1.0367137e+09 | J105: 0 | K105: 0 | M105: =VLOOKUP(B105,[6]Sheet1!$D:$M,10,0) -> -60037787 | N105: =I105-M105 -> -9.7667591e+08 | Q105: =VLOOKUP(B105,[7]!Table1[GLAccountNo],1,0) -> #REF!
A106: Income | B106: 30000001 | C106: 20 | D106: Revenue from operations | E106: Sales of Products | F106: Domestic Sales | G106: =IFERROR(VLOOKUP(B106,[5]Sheet1!$C:$M,8,0),0) -> 0 | H106: =IFERROR(VLOOKUP(B106,[5]Sheet1!$C:$M,9,0),0) -> -1.0192144e+09 | I106: =G106+H106 -> -1.0192144e+09 | J106: 0 | K106: 0 | M106: =VLOOKUP(B106,[6]Sheet1!$D:$M,10,0) -> -60396509 | N106: =I106-M106 -> -9.5881793e+08 | Q106: =VLOOKUP(B106,[7]!Table1[GLAccountNo],1,0) -> #REF!
A107: Income | B107: 30000004 | C107: 20 | D107: Revenue from operations | E107: Scrap Sales | F107: Scrap Sales | G107: =IFERROR(VLOOKUP(B107,[5]Sheet1!$C:$M,8,0),0) -> 0 | H107: =IFERROR(VLOOKUP(B107,[5]Sheet1!$C:$M,9,0),0) -> -2878000 | I107: =G107+H107 -> -2878000 | J107: 0 | K107: 0 | M107: =VLOOKUP(B107,[6]Sheet1!$D:$M,10,0) -> -824220 | N107: =I107-M107 -> -2053780 | Q107: =VLOOKUP(B107,[7]!Table1[GLAccountNo],1,0) -> #REF!
A108: Income | B108: 30000007 | C108: 20 | D108: Revenue from operations | E108: Sales of Products | F108: Sales In transit | G108: =IFERROR(VLOOKUP(B108,[5]Sheet1!$C:$M,8,0),0) -> 2.6538313e+08 | H108: =IFERROR(VLOOKUP(B108,[5]Sheet1!$C:$M,9,0),0) -> 0 | I108: =G108+H108 -> 2.6538313e+08 | J108: 0 | K108: 0 | M108: =VLOOKUP(B108,[6]Sheet1!$D:$M,10,0) -> #N/A | N108: =I108-M108 -> #N/A | Q108: =VLOOKUP(B108,[7]!Table1[GLAccountNo],1,0) -> #REF!
A109: Income | B109: 30000008 | C109: 20 | D109: Revenue from operations | E109: Sales of Products | F109: Domestic Sales Inter Company | G109: =IFERROR(VLOOKUP(B109,[5]Sheet1!$C:$M,8,0),0) -> 0 | H109: =IFERROR(VLOOKUP(B109,[5]Sheet1!$C:$M,9,0),0) -> -5.5132447e+08 | I109: =G109+H109 -> -5.5132447e+08 | J109: 0 | K109: 0 | M109: =VLOOKUP(B109,[6]Sheet1!$D:$M,10,0) -> -1.580755e+08 | N109: =I109-M109 -> -3.9324897e+08 | Q109: =VLOOKUP(B109,[7]!Table1[GLAccountNo],1,0) -> #REF!
A110: Income | B110: 30100001 | C110: 21 | D110: Other Income | E110: Foreign exchange gain (net) | F110: Realised Forex Gain/loss | G110: =IFERROR(VLOOKUP(B110,[5]Sheet1!$C:$M,8,0),0) -> 0 | H110: =IFERROR(VLOOKUP(B110,[5]Sheet1!$C:$M,9,0),0) -> -14334689 | I110: =G110+H110 -> -14334689 | J110: 0 | K110: 0 | M110: =VLOOKUP(B110,[6]Sheet1!$D:$M,10,0) -> 1189802.4 | N110: =I110-M110 -> -15524491 | Q110: =VLOOKUP(B110,[7]!Table1[GLAccountNo],1,0) -> #REF!
A111: Income | B111: 30100004 | C111: 21 | D111: Other Income | E111: - From banks | F111: Interest on Bank Deposit | G111: =IFERROR(VLOOKUP(B111,[5]Sheet1!$C:$M,8,0),0) -> 0 | H111: =IFERROR(VLOOKUP(B111,[5]Sheet1!$C:$M,9,0),0) -> -414006 | I111: =G111+H111 -> -414006 | J111: 0 | K111: 0 | M111: =VLOOKUP(B111,[6]Sheet1!$D:$M,10,0) -> -175897 | N111: =I111-M111 -> -238109 | Q111: =VLOOKUP(B111,[7]!Table1[GLAccountNo],1,0) -> #REF!
A112: Income | B112: 30100005 | C112: 21 | D112: Other Income | E112: - From others | F112: Other Income | G112: =IFERROR(VLOOKUP(B112,[5]Sheet1!$C:$M,8,0),0) -> 0 | H112: =IFERROR(VLOOKUP(B112,[5]Sheet1!$C:$M,9,0),0) -> -1670492.5 | I112: =G112+H112 -> -1670492.5 | J112: 0 | K112: 0 | M112: =VLOOKUP(B112,[6]Sheet1!$D:$M,10,0) -> #N/A | N112: =I112-M112 -> #N/A | Q112: =VLOOKUP(B112,[7]!Table1[GLAccountNo],1,0) -> #REF!
A113: Income | B113: 30100013 | C113: 21 | D113: Other Income | E113: Profit on Sale of Mutual Fund | F113: Gain / Loss from MF Investment | G113: =IFERROR(VLOOKUP(B113,[5]Sheet1!$C:$M,8,0),0) -> 0 | H113: =IFERROR(VLOOKUP(B113,[5]Sheet1!$C:$M,9,0),0) -> 0 | I113: =G113+H113 -> 0 | J113: 0 | K113: 0 | M113: =VLOOKUP(B113,[6]Sheet1!$D:$M,10,0) -> #N/A | N113: =I113-M113 -> #N/A | Q113: =VLOOKUP(B113,[7]!Table1[GLAccountNo],1,0) -> #REF!
A114: Income | B114: 30100015 | C114: 21 | D114: Other Income | E114: - From others | F114: IND AS - Interest Income | G114: =IFERROR(VLOOKUP(B114,[5]Sheet1!$C:$M,8,0),0) -> 0 | H114: =IFERROR(VLOOKUP(B114,[5]Sheet1!$C:$M,9,0),0) -> -192594.37 | I114: =G114+H114 -> -192594.37 | J114: 0 | K114: 0 | M114: =VLOOKUP(B114,[6]Sheet1!$D:$M,10,0) -> -21228.68 | N114: =I114-M114 -> -171365.69 | Q114: =VLOOKUP(B114,[7]!Table1[GLAccountNo],1,0) -> #REF!
A115: Income | B115: 30100000 | C115: 21 | D115: Other Income | E115: Foreign exchange gain (net) | F115: Unrealised Forex Gain/loss | G115: =IFERROR(VLOOKUP(B115,[5]Sheet1!$C:$M,8,0),0) -> 0 | H115: =IFERROR(VLOOKUP(B115,[5]Sheet1!$C:$M,9,0),0) -> -7123642.8 | I115: =G115+H115 -> -7123642.8 | J115: 0 | K115: 0 | M115: =VLOOKUP(B115,[6]Sheet1!$D:$M,10,0) -> -1326437.2 | N115: =I115-M115 -> -5797205.6 | Q115: =VLOOKUP(B115,[7]!Table1[GLAccountNo],1,0) -> #REF!
A116: Expenses | B116: 40100000 | C116: 22 | D116: Cost of material consumed | E116: Add : Purchases -RM | F116: Custom Duty | G116: =IFERROR(VLOOKUP(B116,[5]Sheet1!$C:$M,8,0),0) -> 614628 | H116: =IFERROR(VLOOKUP(B116,[5]Sheet1!$C:$M,9,0),0) -> 0 | I116: =G116+H116 -> 614628 | J116: 0 | K116: 0 | M116: =VLOOKUP(B116,[6]Sheet1!$D:$M,10,0) -> -1.57 | N116: =I116-M116 -> 614629.57 | O116: =VLOOKUP(B116,'[9]TB BVS 30.11.25'!$B:$I,8,0) -> 0 | Q116: =I116-O116 -> 614628
A117: Expenses | B117: 40100001 | C117: 22 | D117: Cost of material consumed | E117: Add : Purchases -RM | F117: Import Cost on Material | G117: =IFERROR(VLOOKUP(B117,[5]Sheet1!$C:$M,8,0),0) -> 3912006.7 | H117: =IFERROR(VLOOKUP(B117,[5]Sheet1!$C:$M,9,0),0) -> 0 | I117: =G117+H117 -> 3912006.7 | J117: 0 | K117: 0 | M117: =VLOOKUP(B117,[6]Sheet1!$D:$M,10,0) -> -893101.08 | N117: =I117-M117 -> 4805107.8 | O117: =VLOOKUP(B117,'[9]TB BVS 30.11.25'!$B:$I,8,0) -> 713455.53 | Q117: =I117-O117 -> 3198551.2
A118: Expenses | B118: 40100002 | C118: 22 | D118: Cost of material consumed | E118: Add : Purchases -RM | F118: Freight Inward Local | G118: =IFERROR(VLOOKUP(B118,[5]Sheet1!$C:$M,8,0),0) -> 2084498.9 | H118: =IFERROR(VLOOKUP(B118,[5]Sheet1!$C:$M,9,0),0) -> 0 | I118: =G118+H118 -> 2084498.9 | J118: 0 | K118: 0 | M118: =VLOOKUP(B118,[6]Sheet1!$D:$M,10,0) -> 248255 | N118: =I118-M118 -> 1836243.9 | O118: =VLOOKUP(B118,'[9]TB BVS 30.11.25'!$B:$I,8,0) -> 852951.93 | Q118: =I118-O118 -> 1231547
A119: Expenses | B119: 40100005 | C119: 22 | D119: Cost of material consumed | E119: Add : Purchases -RM | F119: Interest on Custom Duty | G119: =IFERROR(VLOOKUP(B119,[5]Sheet1!$C:$M,8,0),0) -> 16312 | H119: =IFERROR(VLOOKUP(B119,[5]Sheet1!$C:$M,9,0),0) -> 0 | I119: =G119+H119 -> 16312 | J119: 0 | K119: 0 | M119: =VLOOKUP(B119,[6]Sheet1!$D:$M,10,0) -> 3990 | N119: =I119-M119 -> 12322 | O119: =VLOOKUP(B119,'[9]TB BVS 30.11.25'!$B:$I,8,0) -> 10307 | Q119: =I119-O119 -> 6005
A120: Expenses | B120: 40100008 | C120: 22 | D120: Cost of material consumed | E120: Add : Purchases -RM | F120: Consumption of Raw Material | G120: =IFERROR(VLOOKUP(B120,[5]Sheet1!$C:$M,8,0),0) -> 1.5400042e+09 | H120: =IFERROR(VLOOKUP(B120,[5]Sheet1!$C:$M,9,0),0) -> 0 | I120: =G120+H120 -> 1.5400042e+09 | J120: 0 | K120: 0 | M120: =VLOOKUP(B120,[6]Sheet1!$D:$M,10,0) -> 1.7230555e+08 | N120: =I120-M120 -> 1.3676986e+09 | O120: =VLOOKUP(B120,'[9]TB BVS 30.11.25'!$B:$I,8,0) -> 6.9990285e+08 | Q120: =I120-O120 -> 8.4010135e+08
A121: Expenses | B121: 40200003 | C121: 22 | D121: Cost of material consumed | E121: Add : Purchases -RM | F121: Price Difference Material | G121: =IFERROR(VLOOKUP(B121,[5]Sheet1!$C:$M,8,0),0) -> 2866265.8 | H121: =IFERROR(VLOOKUP(B121,[5]Sheet1!$C:$M,9,0),0) -> 0 | I121: =G121+H121 -> 2866265.8 | J121: 0 | K121: 0 | M121: =VLOOKUP(B121,[6]Sheet1!$D:$M,10,0) -> -17550.34 | N121: =I121-M121 -> 2883816.1 | O121: =VLOOKUP(B121,'[9]TB BVS 30.11.25'!$B:$I,8,0) -> 2640906.3 | Q121: =I121-O121 -> 225359.47
A122: Expenses | B122: 40100011 | C122: 22 | D122: Cost of material consumed | E122: Add : Purchases -PM | F122: Consumption of Packing Material | G122: =IFERROR(VLOOKUP(B122,[5]Sheet1!$C:$M,8,0),0) -> 27957276 | H122: =IFERROR(VLOOKUP(B122,[5]Sheet1!$C:$M,9,0),0) -> 0 | I122: =G122+H122 -> 27957276 | J122: 0 | K122: 0 | M122: =VLOOKUP(B122,[6]Sheet1!$D:$M,10,0) -> 3447559 | N122: =I122-M122 -> 24509717 | O122: =VLOOKUP(B122,'[9]TB BVS 30.11.25'!$B:$I,8,0) -> 13985212 | Q122: =I122-O122 -> 13972064
A123: Expenses | B123: 40100007 | C123: 23 | D123: Changes in inventories of finished goods and work-in-progress | E123: Changes in inventories of finished goods and work in progress | F123: COGS SFG and FG | G123: =IFERROR(VLOOKUP(B123,[5]Sheet1!$C:$M,8,0),0) -> 2.452209e+09 | H123: =IFERROR(VLOOKUP(B123,[5]Sheet1!$C:$M,9,0),0) -> 0 | I123: =G123+H123 -> 2.452209e+09 | J123: 0 | K123: 0 | M123: =VLOOKUP(B123,[6]Sheet1!$D:$M,10,0) -> 2.1496574e+08 | N123: =I123-M123 -> 2.2372432e+09 | O123: =VLOOKUP(B123,'[9]TB BVS 30.11.25'!$B:$I,8,0) -> 1.3875668e+09 | Q123: =I123-O123 -> 1.0646421e+09
A124: Expenses | B124: 40100009 | C124: 23 | D124: Changes in inventories of finished goods and work-in-progress | E124: Changes in inventories of finished goods and work in progress | F124: Consumption of Semi-Finished Goods | G124: =IFERROR(VLOOKUP(B124,[5]Sheet1!$C:$M,8,0),0) -> 9.2665818e+09 | H124: =IFERROR(VLOOKUP(B124,[5]Sheet1!$C:$M,9,0),0) -> 0 | I124: =G124+H124 -> 9.2665818e+09 | J124: 0 | K124: 0 | M124: =VLOOKUP(B124,[6]Sheet1!$D:$M,10,0) -> 7.5870385e+08 | N124: =I124-M124 -> 8.5078779e+09 | O124: =VLOOKUP(B124,'[9]TB BVS 30.11.25'!$B:$I,8,0) -> 4.9922453e+09 | Q124: =I124-O124 -> 4.2743365e+09
A125: Expenses | B125: 40200000 | C125: 23 | D125: Changes in inventories of finished goods and work-in-progress | E125: Changes in inventories of finished goods and work in progress | F125: COGM Material | G125: =IFERROR(VLOOKUP(B125,[5]Sheet1!$C:$M,8,0),0) -> 0 | H125: =IFERROR(VLOOKUP(B125,[5]Sheet1!$C:$M,9,0),0) -> -9.1283623e+09 | I125: =G125+H125 -> -9.1283623e+09 | J125: 0 | K125: 0 | M125: =VLOOKUP(B125,[6]Sheet1!$D:$M,10,0) -> -7.8051228e+08 | N125: =I125-M125 -> -8.3478501e+09 | O125: =VLOOKUP(B125,'[9]TB BVS 30.11.25'!$B:$I,8,0) -> -4.8712777e+09 | Q125: =I125-O125 -> -4.2570846e+09
A126: Expenses | B126: 40200001 | C126: 23 | D126: Changes in inventories of finished goods and work-in-progress | E126: Changes in inventories of finished goods and work in progress | F126: COGM SFG and FG | G126: =IFERROR(VLOOKUP(B126,[5]Sheet1!$C:$M,8,0),0) -> 0 | H126: =IFERROR(VLOOKUP(B126,[5]Sheet1!$C:$M,9,0),0) -> -1.6989376e+09 | I126: =G126+H126 -> -1.6989376e+09 | J126: 0 | K126: 0 | M126: =VLOOKUP(B126,[6]Sheet1!$D:$M,10,0) -> -1.624943e+08 | N126: =I126-M126 -> -1.5364433e+09 | O126: =VLOOKUP(B126,'[9]TB BVS 30.11.25'!$B:$I,8,0) -> -8.8516189e+08 | Q126: =I126-O126 -> -8.1377575e+08
A127: Expenses | B127: 40200004 | C127: 23 | D127: Changes in inventories of finished goods and work-in-progress | E127: Changes in inventories of finished goods and work in progress | F127: Price difference SFG and FG | G127: =IFERROR(VLOOKUP(B127,[5]Sheet1!$C:$M,8,0),0) -> 1353458.7 | H127: =IFERROR(VLOOKUP(B127,[5]Sheet1!$C:$M,9,0),0) -> 0 | I127: =G127+H127 -> 1353458.7 | J127: 0 | K127: 0 | M127: =VLOOKUP(B127,[6]Sheet1!$D:$M,10,0) -> 4853183.9 | N127: =I127-M127 -> -3499725.3 | O127: =VLOOKUP(B127,'[9]TB BVS 30.11.25'!$B:$I,8,0) -> 1394647.2 | Q127: =I127-O127 -> -41188.5
... A129: Expenses | B129: 40200011 | C129: 23 | D129: Changes in inventories of finished goods and work-in-progress | E129: Changes in inventories of finished goods and work in progress | F129: COGM Material_Manual Entry | G129: =IFERROR(VLOOKUP(B129,[5]Sheet1!$C:$M,8,0),0) -> 33154745 | H129: =IFERROR(VLOOKUP(B129,[5]Sheet1!$C:$M,9,0),0) -> 0 | I129: =G129+H129 -> 33154745 | J129: 0 | K129: 0 | M129: =VLOOKUP(B129,[6]Sheet1!$D:$M,10,0) -> 39813643 | N129: =I129-M129 -> -6658897.9 | O129: =VLOOKUP(B129,'[9]TB BVS 30.11.25'!$B:$I,8,0) -> 39813643 | Q129: =I129-O129 -> -6658897.9
A130: Expenses | B130: 40300004 | C130: 24 | D130: Employee benefits expense | E130: Salary, Wages, Allowances and Bonus | F130: Basic Salary | G130: =IFERROR(VLOOKUP(B130,[5]Sheet1!$C:$M,8,0),0) -> 56968542 | H130: =IFERROR(VLOOKUP(B130,[5]Sheet1!$C:$M,9,0),0) -> 0 | I130: =G130+H130 -> 56968542 | J130: 0 | K130: 0 | M130: =VLOOKUP(B130,[6]Sheet1!$D:$M,10,0) -> 12114521 | N130: =I130-M130 -> 44854021 | O130: =VLOOKUP(B130,'[10]TB BVS 30.6.25'!$B:$I,8,0) -> 12114521 | P130: #N/A | Q130: =VLOOKUP(B130,[7]!Table1[GLAccountNo],1,0) -> #REF!
A131: Expenses | B131: 40400009 | C131: 25 | D131: Finance costs | E131: - From Bank (Secured Loan) | F131: Interest on Term Loan | G131: =IFERROR(VLOOKUP(B131,[5]Sheet1!$C:$M,8,0),0) -> 195923162 | H131: =IFERROR(VLOOKUP(B131,[5]Sheet1!$C:$M,9,0),0) -> 0 | I131: =G131+H131 -> 195923162 | J131: 0 | K131: 0 | M131: =VLOOKUP(B131,[6]Sheet1!$D:$M,10,0) -> 53157933 | N131: =I131-M131 -> 142765229 | Q131: =VLOOKUP(B131,[7]!Table1[GLAccountNo],1,0) -> #REF!
A132: Expenses | B132: 40400014 | C132: 25 | D132: Finance costs | E132: Other Borrowing Cost | F132: Processing and Stamp Duty Expense | G132: =IFERROR(VLOOKUP(B132,[5]Sheet1!$C:$M,8,0),0) -> 26479574 | H132: =IFERROR(VLOOKUP(B132,[5]Sheet1!$C:$M,9,0),0) -> 0 | I132: =G132+H132 -> 26479574 | J132: 0 | K132: 0 | M132: =VLOOKUP(B132,[6]Sheet1!$D:$M,10,0) -> 24999 | N132: =I132-M132 -> 26454575 | Q132: =VLOOKUP(B132,[7]!Table1[GLAccountNo],1,0) -> #REF!
...

Sheet BS
A1: =Input!$B$1 -> BVC Specialities Private Limited
A2: Balance Sheet as at 31 March 2026
E3: =Input!$D$2 -> (₹ in Lakh) | F3: =Input!$D$2 -> (₹ in Lakh)
A4: Particulars | C4: Note | D4: As at | E4: As at | F4: As at | I4: As at
D5: 31 March 2026 | E5: 31 March 2025 | F5: =Input!C6 -> 31 March 2022 | H5: =D8*1000 -> 47317815 | I5: 31 March 2026 | R5: =H5/100000 -> 473.17815
B6: ASSETS | H6: =5344-5331 -> 13
B7: Non Current Assets
A8: (a) | B8: Property, Plant & Equipment | C8: =Input!$D$13 -> 3 | D8: ='PPE- note 3'!J17 -> 47317.815 | E8: =5019438.923/100 -> 50194.389 | F8: 0 | H8: =E8-D8 -> 2876.5741 | I8: 47317.315 | J8: =D8-I8 -> 0.5 | K8: =D8-I8 -> 0.5 | N8: =ROUND(SUMIF('TB BVS 31.3.22'!E:E,BS!B8,'TB BVS 31.3.22'!N:N)/Input!$C$2,Input!$E$2)-F8 -> 0 | O8: Check | R8: Sampling done we have not received samples yet
A9: (b) | B9: Right of Use Assets | C9: =Input!$D$13 -> 3 | D9: ='PPE- note 3'!J23 -> 3116.3267 | E9: =315093/100 -> 3150.93 | F9: ='PPE- note 3'!K127 -> 1646 | H9: =E9-D9 -> 34.603343 | I9: 3116.3267 | J9: =D9-I9 -> 0
A10: (c) | B10: Capital work-in-progress | C10: =Input!$D$13 -> 3 | D10: ='PPE- note 3'!J18 -> 1149.427 | E10: 0 | F10: ='PPE- note 3'!K123 -> 0 | G10: =D10-[4]BS!$D$10 -> -3160244.4 | H10: =E10-D10 -> -1149.427 | I10: 1149.427 | J10: =D10-I10 -> 0 | R10: =D10/1000 -> 1.149427
A11: (d) | B11: Intangible assets | C11: =Input!$D$13 -> 3 | D11: ='PPE- note 3'!J27 -> 29.181997 | E11: =4365/100 -> 43.65 | F11: 0 | H11: =E11-D11 -> 14.468003 | I11: 29.181997 | J11: =D11-I11 -> 0
A12: (e) | B12: Financial Assets | H12: =E12-D12 -> 0 | J12: =D12-I12 -> 0
B13: (i) Investments | C13: 4 | D13: ='BS Notes 3-18'!G11 -> 17 | E13: 0 | H13: =E13-D13 -> -17 | I13: 17 | J13: =D13-I13 -> 0
B14: (ii) Loans | C14: 5 | D14: ='BS Notes 3-18'!G21 -> 0 | E14: ='BS Notes 3-18'!H21 -> 0 | H14: =E14-D14 -> 0 | I14: 0 | J14: =D14-I14 -> 0
B15: (ii) Other Financial Assets | C15: 5 | D15: ='BS Notes 3-18'!G33 -> 307 | E15: ='BS Notes 3-18'!H33 -> 352 | H15: =E15-D15 -> 45 | I15: 307 | J15: =D15-I15 -> 0 | R15: Done
A16: (f) | B16: Deferred Tax Assets (Net) | C16: 16 | D16: ='BS Notes 3-18'!G328 -> 1586.3847 | E16: ='BS Notes 3-18'!H329 -> 0 | F16: =-'BS Notes 3-18'!I328 -> 0 | H16: =E16-D16 -> -1586.3847 | I16: 0 | J16: =D16-I16 -> 1586.3847
A17: (g) | B17: Other Tax Assets (Net) | C17: 6 | D17: ='BS Notes 3-18'!G44 -> 5.5 | E17: ='BS Notes 3-18'!H44 -> 13 | H17: =E17-D17 -> 7.5 | I17: 5.5 | J17: =D17-I17 -> 0 | R17: Rahul
A18: (h) | B18: Other Non Current Assets | C18: 7 | D18: ='BS Notes 3-18'!G54 -> 75.5 | E18: ='BS Notes 3-18'!H54 -> 84 | H18: =E18-D18 -> 8.5 | I18: 76.5 | J18: =D18-I18 -> -1
B19: Total Non Current Assets | D19: =SUM(D8:D18) -> 53604.135 | E19: =SUM(E8:E18) -> 53837.969 | F19: =SUM(F8:F11) -> 1646 | I19: 52018.251 | J19: =D19-I19 -> 1585.8847
J20: =D20-I20 -> 0
B21: Current Assets | J21: =D21-I21 -> 0
A22: (a) | B22: Inventories | C22: 8 | D22: ='BS Notes 3-18'!G76 -> 6638 | E22: ='BS Notes 3-18'!H76 -> 811 | H22: =E22-D22 -> -5827 | I22: 6638 | J22: =D22-I22 -> 0 | R22: Pending
A23: (b) | B23: Financial Assets | H23: =E23-D23 -> 0 | J23: =D23-I23 -> 0
B24: (i) Trade Receivables | C24: 9 | D24: ='BS Notes 3-18'!G90 -> 3026 | E24: ='BS Notes 3-18'!H90 -> 454 | H24: =E24-D24 -> -2572 | I24: 3026 | J24: =D24-I24 -> 0 | R24: done
B25: (ii) Cash and Cash Equivalents | C25: 10 | D25: ='BS Notes 3-18'!G118 -> 31 | E25: ='BS Notes 3-18'!H118 -> 22 | F25: ='BS Notes 3-18'!I118 -> 24 | H25: =E25-D25 -> -9 | I25: 31 | J25: =D25-I25 -> 0 | R25: done | S25: reclass pending
A26: (c) | B26: Current Tax Assets (net) | C26: 7 | D26: ='BS Notes 3-18'!G48 -> 0 | E26: 0 | H26: =E26-D26 -> 0 | I26: 0 | J26: =D26-I26 -> 0
B27: (iii) Other Financial Assets | D27: ='BS Notes 3-18'!G36 -> 0 | I27: 0 | J27: =D27-I27 -> 0 | R27: pending
B28: (iii) Bank balances other than (ii) above | C28: 10 | D28: ='BS Notes 3-18'!G122 -> 54 | E28: 0 | H28: =E28-D28 -> -54 | I28: 54 | J28: =D28-I28 -> 0
A29: (c) | B29: Other Current Assets | C29: 11 | D29: ='BS Notes 3-18'!G131 -> 6155.5 | E29: ='BS Notes 3-18'!H131 -> 5212 | F29: ='BS Notes 3-18'!I131 -> 296 | G29: navaz | H29: =E29-D29 -> -943.5 | I29: 6155 | J29: =D29-I29 -> 0.5 | R29: Done
B30: Total Current Assets | D30: =SUM(D22:D29) -> 15904.5 | E30: =SUM(E22:E29) -> 6499 | F30: =SUM(F23:F29) -> 320 | G30: =D30/10000 -> 1.59045 | I30: 15904 | J30: =D30-I30 -> 0.5
B31: Total Assets | D31: =D19+D30 -> 69508.635 | E31: =E19+E30 -> 60336.969 | F31: =F19+F30 -> 1966 | H31: 6.424212e+09 | I31: 67922.251 | J31: =D31-I31 -> 1586.3847 | R31: =D31*1000 -> 69508635 | S31: =R31-H31 -> -6.3547033e+09 | T31: =S31/1000 -> -6354703.3
J32: =D32-I32 -> 0
B33: EQUITY AND LIABILITIES | J33: =D33-I33 -> 0
B34: Equity | J34: =D34-I34 -> 0
A35: (a) | B35: Equity Share Capital | C35: 12 | D35: ='BS Notes 3-18'!G146 -> 15.9789 | E35: ='BS Notes 3-18'!H146 -> 13.6597 | F35: ='BS Notes 3-18'!I146 -> 100 | H35: =D35-E35 -> 2.3192 | I35: 15.9789 | J35: =D35-I35 -> 0
A36: (b) | B36: Instrument entirely equity in nature | C36: 12 | D36: ='BS Notes 3-18'!G197 -> 9.1868 | E36: ='BS Notes 3-18'!H181+'BS Notes 3-18'!H188 -> 9.1868 | H36: =D36-E36 -> 0 | I36: 8.6868 | J36: =D36-I36 -> 0.5
A37: (c) | B37: Other Equity | C37: 13 | D37: ='BS Notes 3-18'!G227 -> 27519.019 | E37: ='BS Notes 3-18'!H227 -> 26755.436 | F37: ='BS Notes 3-18'!I227 -> #REF! | H37: =D37-E37 -> 763.58221 | I37: 25906.759 | J37: =D37-I37 -> 1612.26 | L37: ='BS Notes 3-18'!L224 -> 0 | N37: =H35 -> 2.3192 | O37: Equity component of Compound Financial Instruments | R37: =E37-D37 -> -763.58221
B38: Total Equity | D38: =SUM(D35:D37) -> 27544.184 | E38: =SUM(E35:E37) -> 26778.283 | F38: =SUM(F35:F37) -> #REF! | G38: =D38-E38 -> 765.90141 | H38: =D38-E38 -> 765.90141 | I38: 25931.424 | J38: =D38-I38 -> 1612.76 | L38: ='BS Notes 3-18'!L225 -> 6708.8222 | N38: ='BS Notes 3-18'!O225 -> 6708.8222 | O38: Securities premium
J39: =D39-I39 -> 0 | L39: ='BS Notes 3-18'!L226 -> -5945.24 | N39: ='BS Notes 3-18'!O226 -> -5945.24 | O39: Retained earnings
B40: Liabilities | J40: =D40-I40 -> 0 | L40: =SUM(L37:L39) -> 763.58221
B41: Non Current Liabilities | J41: =D41-I41 -> 0
A42: (a) | B42: Financial Liabilities | J42: =D42-I42 -> 0 | R42: =D43/1000+D50/1000 -> 31.442
B43: (i) Borrowings | C43: 14 | D43: ='BS Notes 3-18'!G263 -> 19691 | E43: ='BS Notes 3-18'!H263 -> 26013 | F43: ='BS Notes 3-18'!I263 -> 495 | H43: =D43-E43 -> -6322 | I43: 19702 | J43: =D43-I43 -> -11 | K43: 2605955 | P43: =D43 -> 19691 | Q43: =K43-P43 -> 2586264 | R43: repayment schedule pending
B44: (ii) Lease Liabilities | C44: 32 | D44: =-ROUND(SUMIF('TB BVS 31.03.26'!E:E,BS!B44,'TB BVS 31.03.26'!K:K)/Input!$C$2,Input!$E$2) -> 0 | H44: =D44-E44 -> 0 | I44: 0 | J44: =D44-I44 -> 0
A45: (b) | B45: Provisions | C45: 15 | D45: ='BS Notes 3-18'!G306 -> 80 | E45: ='BS Notes 3-18'!H306 -> 39 | H45: =D45-E45 -> 41 | I45: 80 | J45: =D45-I45 -> 0 | R45: pending
B46: Total Non Current Liabilities | D46: =SUM(D43:D45) -> 19771 | E46: =SUM(E43:E45) -> 26052 | F46: =SUM(F43:F45) -> 495 | I46: 19782 | J46: =D46-I46 -> -11
J47: =D47-I47 -> 0
B48: Current Liabilities | H48: =D50+D43 -> 31442 | J48: =D48-I48 -> 0 | R48: =H48/10 -> 3144.2
A49: (a) | B49: Financial Liabilities | J49: =D49-I49 -> 0
B50: (i) Borrowings | C50: 14 | D50: ='BS Notes 3-18'!G275 -> 11751 | E50: ='BS Notes 3-18'!H275 -> 3140 | F50: ='BS Notes 3-18'!I275 -> 30 | H50: =D50-E50 -> 8611 | I50: 11751 | J50: =D50-I50 -> 0 | K50: 241523 | P50: =D50 -> 11751 | Q50: =K50-P50 -> 229772 | R50: repayment schedule pending
B51: (ii) Lease Liabilities | C51: 32 | D51: =-ROUND(SUMIF('TB BVS 31.03.26'!E:E,BS!B51,'TB BVS 31.03.26'!J:J)/Input!$C$2,Input!$E$2) -> 0 | E51: 0 | H51: =D51-E51 -> 0 | I51: 0 | J51: =D51-I51 -> 0
B52: (ii) Trade Payables | J52: =D52-I52 -> 0
B53: - Dues of micro enterprises and small enterprises | C53: 17 | D53: ='BS Notes 3-18'!G421 -> 123.01883 | E53: ='BS Notes 3-18'!H421 -> 158.37 | F53: ='BS Notes 3-18'!I421 -> 0 | H53: =D53-E53 -> -35.35117 | I53: 123.01883 | J53: =D53-I53 -> 0
B54: - Dues of creditors other than micro enterprises and small enterprises | D54: ='BS Notes 3-18'!G422 -> 9796.9812 | E54: ='BS Notes 3-18'!H422 -> 1654.63 | F54: ='BS Notes 3-18'!I422 -> 14 | G54: navaz | H54: =D54-E54 -> 8142.3512 | I54: 9811.9812 | J54: =D54-I54 -> -15 | R54: Done
B55: (iii) Other Financial Liabilities | C55: 18 | D55: ='BS Notes 3-18'!G469 -> 445 | E55: ='BS Notes 3-18'!H469 -> 2508 | H55: =D55-E55 -> -2063 | I55: 445 | J55: =D55-I55 -> 0 | R55: Done
A56: (b) | B56: Other Current Liabilities | C56: 19 | D56: ='BS Notes 3-18'!G475 -> 66 | E56: ='BS Notes 3-18'!H475 -> 39 | F56: ='BS Notes 3-18'!I475 -> 0 | G56: navaz | H56: =D56-E56 -> 27 | I56: 66 | J56: =D56-I56 -> 0 | K56: =D31-D60 -> 27543.635 | R56: Done entry needs to be checked once
A57: (c) | B57: Current tax liabilities (Net) | C57: 7 | D57: 0 | E57: 0 | H57: =D57-E57 -> 0 | I57: 0 | J57: =D57-I57 -> 0
A58: (d) | B58: Provisions | C58: 15 | D58: ='BS Notes 3-18'!G311 -> 12 | E58: ='BS Notes 3-18'!H311 -> 7 | H58: =D58-E58 -> 5 | I58: 12 | J58: =D58-I58 -> 0 | R58: pending
B59: Total Current Liabilities | D59: =SUM(D50:D58) -> 22194 | E59: =SUM(E50:E58) -> 7507 | F59: =SUM(F50:F56) -> 44 | H59: =SUM(H8:H58) -> 6.4242442e+09 | I59: 22209 | J59: =D59-I59 -> -15
B60: Total Liabilities | D60: =+D46+D59 -> 41965 | E60: =+E46+E59 -> 33559 | F60: =+F46+F59 -> 539 | I60: 41991 | J60: =D60-I60 -> -26
B61: Total Equity and Liabilities | D61: =+D38+D60 -> 69509.184 | E61: =+E38+E60 -> 60337.283 | F61: =+F38+F60 -> #REF! | G61: =D61-D31 -> 0.54886832 | H61: =D61-D31 -> 0.54886832 | I61: 67922.424 | K61: =E61-E31 -> 0.3136903 | R61: =E61-E31 -> 0.3136903
A62: Corporate Information & Material Accounting Policies | C62: =Input!D10&" & "&Input!D11 -> 1 & 2
A63: The accompanying notes are integral part of the Financial Statements. | H63: =H61*1000 -> 548.86832
A64: As per our report of even date attached.
A66: For B S R and Co | D66: For and on behalf of Board of | I66: For and on behalf of Board of
A67: Chartered Accountants | D67: BVC Specialities Private Limited | I67: BVC Specialities Private Limited
A68: Firm's Registration No: 128510W | D68: =Input!$C$1 -> CIN : U24230GJ2021PTC123855 | I68: CIN : U24230GJ2021PTC123855
A71: Jeyur Shah | D71: Shishir Srivastava | E71: Shaju Ouseph Chazhoor | I71: Shishir Srivastava
A72: Partner | D72: Director | E72: Director | I72: Director
A73: Membership No. 045754 | D73: DIN: 00330342 | E73: DIN: 01482035 | I73: DIN: 00330342
D77: Ambrish Dixit | E77: Mukesh Lodha | I77: Ambrish Dixit
D78: CEO | E78: CFO | I78: CEO
A81: =" "
A82: Place: Ahmedabad | D82: Place: Vadodara | E82: Place: Vadodara | I82: Place: Vadodara
A83: Date: 17 July 2026 | D83: =A83 -> Date: 17 July 2026 | E83: =D83 -> Date: 17 July 2026 | I83: Date: 17 July 2026

Sheet PL
A1: =Input!$B$1 -> BVC Specialities Private Limited
A2: Statement of Profit and Loss for the Year Ended 31 March 2026
E3: =Input!$D$2 -> (₹ in Lakh) | F3: =Input!$D$2 -> (₹ in Lakh)
A4: Particulars | C4: Note | D4: Year Ended | E4: Year Ended | F4: Year Ended
D5: =BS!D5 -> 31 March 2026 | E5: =BS!E5 -> 31 March 2025 | F5: March 31,2022
B7: Income
A8: I | B8: Revenue from Operations | C8: 20 | D8: ='PL Notes 19-27'!C17 -> 23491 | E8: ='PL Notes 19-27'!D17 -> 1094 | F8: ='[2]PL Notes 19-26'!E17 -> 0 | G8: 70109.418 | H8: =E8-G8 -> -69015.418 | I8: Ok | Q8: Tomorrow | R8: 40277
A9: II | B9: Other Income | C9: 21 | D9: ='PL Notes 19-27'!C36 -> 238 | E9: ='PL Notes 19-27'!D36 -> 73 | F9: ='[2]PL Notes 19-26'!E34 -> 0 | G9: 682.34518 | H9: =E9-G9 -> -609.34518 | I9: Refer Note | Q9: Tomorrow | R9: =R11/R8 -> 0.38246817 | S9: =S11/E8 -> 0.37463633
A10: III | B10: Total Income (I+II) | D10: =SUM(D8:D9) -> 23729 | E10: =SUM(E8:E9) -> 1167 | F10: =SUM(F8:F9) -> 0 | G10: =SUM(G8:G9) -> 70791.763 | H10: =SUM(H8:H9) -> -69624.763
R11: =D13+D15 -> 15404.67 | S11: =E13+E15 -> 409.85214
A12: II | B12: Expenses | G12: =D10*1000 -> 23729000
B13: Cost of materials consumed | C13: =C9+1 -> 22 | D13: ='PL Notes 19-27'!C51 -> 19619.67 | E13: ='PL Notes 19-27'!D51-E14 -> 796.74214 | F13: ='[2]PL Notes 19-26'!E42+'[2]PL Notes 19-26'!E47 -> 0 | G13: 44527.472 | H13: =E13-G13 -> -43730.73 | I13: Due to Impact of Change in Inv method | Q13: Tomorrow | T13: =(D13+D15)/$D$10 -> 0.64919172 | U13: =(E13+E15)/$E$10 -> 0.35120149
B14: Purchase of stock-in-trade (traded goods) | C14: - | D14: 2112.3297 | E14: =115.837859278726 -> 115.83786 | R14: =D14*100000 -> 2.1123297e+08
B15: Changes in inventories of finished goods and work-in-progress | C15: =C13+1 -> 23 | D15: ='PL Notes 19-27'!C64 -> -4215 | E15: ='PL Notes 19-27'!D64 -> -386.89 | F15: ='[2]PL Notes 19-26'!E62 -> 0 | G15: -1566.3014 | H15: =E15-G15 -> 1179.4114 | I15: Due to Impact of Change in Inv method | Q15: Tomorrow
B16: Employee Benefits Expense | C16: =C15+1 -> 24 | D16: ='PL Notes 19-27'!C74 -> 1989.5569 | E16: ='PL Notes 19-27'!D74 -> 147.7747 | Q16: Navaz | R16: =D19/10 -> 588.3 | T16: =D16/$D$10 -> 0.083844955 | U16: =E16/$E$10 -> 0.12662785
B17: Finance Costs | C17: =C16+1 -> 25 | D17: ='PL Notes 19-27'!C86 -> 2699 | E17: ='PL Notes 19-27'!D86 -> 763.08652 | F17: ='PL Notes 19-27'!E86 -> 38 | G17: =D13+D15 -> 15404.67 | Q17: Tomorrow | R17: =D21/10*12 -> -9048.288 | S17: =R17/1000 -> -9.048288 | T17: =D17/$D$10 -> 0.11374268 | U17: =E17/$E$10 -> 0.65388734
B18: Depreciation and Amortisation Expense | C18: =Input!D69 -> 3 | D18: ='PPE- note 3'!G17+'PPE- note 3'!G23+'PPE- note 3'!G27 -> 3180.683 | E18: =129491/100 -> 1294.91 | F18: ='PPE- note 3'!I141 -> 6 | G18: =G17*1000 -> 15404670 | Q18: Tomorrow | T18: =D18/$D$10 -> 0.13404202 | U18: =E18/$E$10 -> 1.1096058
B19: Other Expenses | C19: =C17+1 -> 26 | D19: ='PL Notes 19-27'!C111 -> 5883 | E19: ='PL Notes 19-27'!D111 -> 466 | F19: ='PL Notes 19-27'!E111 -> 38 | G19: 348000 | Q19: Navaz | R19: =D19*1000 -> 5883000 | S19: =D21+D18+D17 -> -1660.5569 | T19: =D19/$D$10 -> 0.24792448 | U19: =E19/$E$10 -> 0.39931448
B20: Total Expense (II) | D20: =SUM(D13:D19) -> 31269.24 | E20: =SUM(E13:E19) -> 3197.4612 | F20: =SUM(F17:F19) -> 82 | I20: PBT As per IND AS | J20: PBT As per IGAAP | K20: Difference | L20: Reco | M20: Head | N20: Remark | R20: -2.0562767e+08
A21: III | B21: (Loss) Before Tax (I-II) | D21: =D10-D20 -> -7540.24 | E21: =E10-E20 -> -2030.4612 | F21: =#REF!-F20 -> #REF! | G21: =D21+D17+D18 -> -1660.5569 | I21: =E21 -> -2030.4612 | J21: =487303222.278789/10^5 -> 4873.0322 | K21: =I21-J21 -> -6903.4934 | L21: ='TB BVS 31.3.23'!J173/10^5 -> 0 | M21: Employee Compensation - ESOP | N21: Not Considered in IGAAP | R21: 1.3109907e+08 | T21: =D21+S21 -> -7540.24
A22: IV | B22: Tax Expenses | L22: =5550219/10^5 -> 55.50219 | M22: Pharma Related Expenses Provision | N22: Not considered in IND AS | R22: =D26*1000 -> -5952240 | T22: =R22-S22 -> -5952240
B23: (a) Current Tax | C23: 16 | D23: =ROUND(SUMIF('TB BVS 31.03.26'!$E:$E,B23,'TB BVS 31.03.26'!$I:$I)/Input!$C$2,Input!$E$2) -> 0 | E23: 0 | F23: 0 | L23: =L22-L21 -> 55.50219 | R23: =D21+D18+D17 -> -1660.5569 | S23: =E21+E18+E17 -> 27.5353
B24: (b) Deferred Tax | C24: =BS!C16 -> 16 | D24: =ROUND(SUMIF('TB BVS 31.03.26'!$E:$E,B24,'TB BVS 31.03.26'!$I:$I)/Input!$C$2,Input!$E$2) -> -1588 | E24: =-142.606394191297/100 -> -1.4260639 | F24: =ROUND(SUMIF('TB BVS 31.3.22'!$E:$E,B24,'TB BVS 31.3.22'!$L:$L)/Input!$C$2,Input!$E$2) -> -1
B25: Total Tax Expenses | D25: =SUM(D23:D24) -> -1588 | E25: =SUM(E23:E24) -> -1.4260639 | F25: =SUM(F23:F24) -> -1 | R25: 1.847648e+08 | S25: =R25/1000 -> 184764.8
A26: V | B26: (Loss) for the Year (III-IV) | D26: =D21-D25 -> -5952.24 | E26: =E21-E25 -> -2029.0352 | F26: =F21-F25 -> #REF! | S26: =S25+D26 -> 178812.56
A28: VI | B28: Other Comprehensive Income
B29: (i) Item that will not be reclassified to profit or loss
B30: Remeasurement of defined benefit plans | C30: =C24 -> 16 | D30: =-ROUND(SUMIF('TB BVS 31.03.26'!$E:$E,B30,'TB BVS 31.03.26'!$I:$I)/Input!$C$2,Input!$E$2) -> 9 | E30: =ROUND(SUMIF('TB BVS 31.3.25'!$E:$E,B30,'TB BVS 31.3.25'!$I:$I)/Input!$C$2,Input!$E$2) -> 2
B31: Income tax relating to items that will not be reclassified to profit or loss | C31: =C30 -> 16 | D31: =ROUND(SUMIF('TB BVS 31.03.26'!$E:$E,B31,'TB BVS 31.03.26'!$I:$I)/Input!$C$2,Input!$E$2) -> -2 | E31: 0
B33: Other Comprehensive Income for the Year | D33: =SUM(D30:D32) -> 7 | E33: =SUM(E30:E32) -> 2 | F33: =F28 -> 0
B34: Total Comprehensive Income/(Loss) for the Year (V+VI) | D34: =D26+D33 -> -5945.24 | E34: =E26+E33 -> -2027.0352 | F34: =F26+F33 -> #REF!
A36: VII | B36: Earnings Per Share (Face Value of ₹ 10 each)
B37: - Basic & Diluted | C37: 27 | D37: ='PL Notes 19-27'!C120 -> -2082 | E37: ='PL Notes 19-27'!D120 -> -961 | F37: ='PL Notes 19-27'!E120 -> #REF!
A38: Corporate Information & Material Accounting Policies | C38: =BS!C62 -> 1 & 2
A39: The accompanying notes are integral part of the Financial Statements.
A40: As per our report of even date attached.
A42: =BS!$A$66 -> For B S R and Co | D42: =BS!D66 -> For and on behalf of Board of
A43: =BS!$A$67 -> Chartered Accountants | D43: =BS!D67 -> BVC Specialities Private Limited
A44: =BS!$A$68 -> Firm's Registration No: 128510W | D44: =BS!D68 -> CIN : U24230GJ2021PTC123855
A47: =BS!$A$71 -> Jeyur Shah | D47: =BS!D71 -> Shishir Srivastava | E47: =BS!E71 -> Shaju Ouseph Chazhoor
A48: =BS!$A$72 -> Partner | D48: =BS!D72 -> Director | E48: =BS!E72 -> Director
A49: =BS!$A$73 -> Membership No. 045754 | D49: =BS!D73 -> DIN: 00330342 | E49: =BS!E73 -> DIN: 01482035
D53: =BS!D77 -> Ambrish Dixit | E53: =BS!E77 -> Mukesh Lodha
D54: =BS!D78 -> CEO | E54: =BS!E78 -> CFO
A59: =BS!$A$82 -> Place: Ahmedabad | D59: =BS!D82 -> Place: Vadodara | E59: =BS!E82 -> Place: Vadodara
A60: =BS!$A$83 -> Date: 17 July 2026 | D60: =BS!D83 -> Date: 17 July 2026 | E60: =BS!E83 -> Date: 17 July 2026

Sheet CFS Working
B1: Total Interest in Finance Cost
B2: - Preference shares | C2: ='PL Notes 19-27'!C83 -> 0
B3: Other Borrowing Cost | C3: ='PL Notes 19-27'!C84 -> 232
B4: Other Interest Expenses* | C4: ='PL Notes 19-27'!C85 -> 0
C5: =SUM(C2:C4) -> 232
B8: Interest Accrued
B9: - Preference shares | C9: =C2 -> 0 | E9: DTL >>> Other Equity
B10: Other Interest Expenses* | C10: =C4 -> 0 | E10: Provision other expe >>> Trade Payable

Sheet IT Computation_FY24
B2: Name : | C2: BVC Specialities Private Limited | E2: PAN : | F2: AAJCB9629E
B3: Address : | C3: 801 to 809, 824, 8th FLOOR, BLOCK 1, BUILDING 73, EST AVENUE, SARABHAI COMPOUND VADODARA - 390023 | E3: A.Y. : | F3: 2023 - 2024
E4: P.Y. : | F4: 2022 - 2023
B7: STATEMENT SHOWING COMPUTATION OF INCOME
B8: PARTICULARS | E8: Amt In INR | F8: Amt In INR
B10: I | C10: Income From Business
C11: Net Profit as per Statement of Profit and Loss before tax | F11: =PL!D21*1000 -> -7540240 | L11: =PL!F21*1000 -> #REF!
B13: Add: | C13: Items disallowed
C14: Expenditure relating to trading activities/Other disallowances | E14: 0
C15: Interest on late payment of TDS | E15: 0 | K15: ='TB BVS 31.3.22'!L23 -> 164
C16: Interest on MSME | E16: ='TB BVS 31.3.25'!G114 -> 0 | G16: =(+E16+E17+E26+E27)*17.16% -> -8487.336 | H16: =E16+E17+E18 -> 3180683
C17: Interest on borrowings measured at amortised cost - Preference Shares (notional) | E17: ='PL Notes 19-27'!$C$83*1000 -> 0 | H17: =H16*17.16% -> 545805.21 | K17: ='PL Notes 19-27'!$E$83*A1 -> 0
C18: Depreciation as per P&L | E18: =PL!D18*1000 -> 3180683 | G18: This is related to lease
C19: Miscellaneosus expenses | E19: ='PL Notes 19-27'!C109*1000*0 -> 0 | G19: 17.16
C20: Expenditure relating to lease (deferred) | E20: 0 | G20: =+E18+E24 -> 3227634 | K20: =PL!F18*A1 -> 0
C21: Expenditure relating to manufacturing (deferred) | E21: 0 | F21: =SUM(E14:E21) -> 3180683 | L21: =SUM(K14:K21) -> 164
B23: Less: | C23: Income considered under other head/ignored for tax
C24: Depreciation as per IT Act | E24: =-'IT Comp workings_FY24'!E21 -> 46950.993
C25: Capital gain on redemption of units of mutual fund | E25: ='TB BVS 31.3.25'!I72 -> 4679369.2 | G25: =+E25+E26 -> 4638309.2
C26: IND AS - Interest | E26: ='TB BVS 31.3.25'!I73 -> -41060
C27: 35D - Preliminary expenses (3rd year) | E27: -8400
C28: Interest Income HDFC BANK LIMITED - as per 26AS | E28: =-'PL Notes 19-27'!C28*1000 -> -4000
C29: Interest Income AXIS BANK LIMITED - as per 26AS
C30: Leasehold amortisation | E30: =-'IT Comp workings_FY24'!C62 -> -17876.795
F31: =SUM(E24:E31) -> 4654983.4
C33: Income from business / profession | F33: =SUM(F11:F31) -> 295426.5
B35: III | C35: Income From Capital Gains
C36: Gain redemption of units of mutual fund
C37: Sale consideration | E37: ='IT Comp workings_FY24'!D30 -> 13741618
C38: Less:- Cost of acquisition | F38: =E37-E38 -> 13741618
C40: Gain redemption of units of Debt mutual fund | E40: ='IT Comp workings_FY24'!D28+'IT Comp workings_FY24'!D34 -> 3479670.3
C41: Sale consideration | F41: =E40-E41 -> 3479670.3
C42: Less:- Cost of acquisition
B44: III | C44: Income From Other Sources
C45: Interest Income | D45: =E30*0 -> 0
C46: ICD Interest (BVO) | D46: =12674410.7755109 -> 12674411 | G46: Krishna to update
C47: Interest Income HDFC BANK LIMITED - as per 26AS | D47: =91096*0 -> 0
C48: Interest Income AXIS BANK LIMITED - as per 26AS | D48: =1532699*0-E28 -> 4000
D49: =SUM(D45:D48) -> 12678411
D50: 11686977 | E50: =D49-D50 -> 991433.8 | F50: =SUM(E45:E50) -> 991433.8 | G50: =F50*17.16% -> 170130.04 | H50: =D46-D50 -> 987433.8
H51: =H50*25.167% -> 248507.46 | I51: =H51+H17 -> 794312.67
C52: Total | F52: =F33+F38+F41+F50 -> 18508148
G53: =+F52*17.16% -> 3175998.2
G54: =+G53-F65 -> -381703.77
B55: STATEMENT SHOWING COMPUTATION OF TAX
B56: PARTICULARS | E56: =E8 -> Amt In INR | F56: =F8 -> Amt In INR
C57: TOTAL INCOME | F57: 0
G58: =+E59*17.16% -> 2358061.6 | H58: =+E60*D60 -> 1048636.7
C59: Income Subject To Normal Rates | D59: 0.15 | E59: =F38 -> 13741618 | F59: =D59*E59 -> 2061242.6 | G59: =+F59+F60 -> 3109879.4 | H59: =15 -> 15 | I59: 22
C60: Income Subject To Special Rates | D60: 0.22 | E60: =F33+F41+F50 -> 4766530.6 | F60: =D60*E60 -> 1048636.7 | G60: =E60*H63% -> 817936.65 | H60: =H59*10% -> 1.5 | I60: =I59*10% -> 2.2
C61: Income Subject To Special Rates | D61: 0.1 | F61: 0 | G61: =E60*I63% -> 1199640.4 | H61: =H59+H60 -> 16.5 | I61: =I59+I60 -> 24.2
C62: Total Income Tax | F62: =SUM(F59:F61) -> 3109879.4 | G62: =G61-G60 -> 381703.77 | H62: =H61*4% -> 0.66 | I62: =I61*4% -> 0.968
B63: Add : | C63: Surcharge @ 10% | F63: =F62*10% -> 310987.94 | H63: =H61+H62 -> 17.16 | I63: =I61+I62 -> 25.168
B64: Add : | C64: Education Cess @ 4% | F64: =(F62+F63)*4% -> 136834.69 | H64: 0.15 | I64: =($F$65-$E$75)*H64 -> -2.4116032e+08 | J64: 3 | K64: =I64*J64% -> -7234809.5
C65: Total Income Tax | F65: =SUM(F62:F64) -> 3557702 | H65: 0.45 | I65: =($F$65-$E$75)*H65 -> -7.2348095e+08 | J65: 3 | K65: =I65*J65% -> -21704428
H66: 0.75 | I66: =($F$65-$E$75)*H66 -> -1.2058016e+09 | J66: 3 | K66: =I66*J66% -> -36174047
B67: Add : | C67: Interest Payable | H67: 1 | I67: =($F$65-$E$75)*H67 -> -1.6077354e+09 | J67: 1 | K67: =I67*J67% -> -16077354
C68: Interest Under Section 234 A | E68: 0 | K68: =SUM(K64:K67) -> -81190640
C69: Interest Under Section 234 B | E69: =F65*2% -> 71154.04
C70: Interest Under Section 234 C | E70: =K68 -> -81190640 | F70: =SUM(E69:E70)*0 -> 0
C71: Total Tax Payable | F71: =F65+F70 -> 3557702
B73: Less: | C73: Prepaid Taxes
C74: Advance Tax
C75: TDS | E75: ='TB BVS 31.3.25'!I52+'TB BVS 31.3.25'!I53+E46*0.1 -> 1.6112931e+09
C76: Self Assessment Tax Paid | F76: =SUM(E74:E76) -> 1.6112931e+09
F78: =F71-F76 -> -1.6077354e+09
E83: FY22
C84: Particulars | D84: BVO | E84: BVS
C85: Loss as per Financial | D85: -16656915 | E85: -7940372.2
C87: *Expense Disallowed | D87: 2204673 | E87: 356064
C88: Expense Disallowed in Current FY but allowed in Subsequent FY | D88: 14144259 | E88: 7276273.6
C90: Preliminery expense claimed 1st Year of 5 Year | E90: 33600
C91: Preliminery expense claimed in 2nd Year of 5 Year | D91: -1000 | E91: 0
C92: Net Loss Carried Forward in Current FY | D92: -308982.95 | E92: -274434.53

Sheet IT Comp workings_FY24
A1: IT Computation workings
A4: Earlier disallowances
A5: AY 2023-24
A6: Expenditure deferred relating to manufacturing | B6: 4519228
A7: Expenditure deferred relating to leasehold rights amortisation | B7: 1752790 | C7: =SUM(B6:B7) -> 6272018
A10: AY 2022-23
A11: Expenditure deferred relating to manufacturing | B11: 3321551
A12: Expenditure deferred relating to leasehold rights amortisation | B12: 3954723 | C12: =SUM(B11:B12) -> 7276274
A16: Particulars | B16: Additions during FY 2023-24 | C16: Allocation of deferred manufacturing exp | D16: Total | E16: Depreciation | F16: ITWDV | G16: Book WDV
A17: Plant and machinery | B17: ='PPE- note 3'!C94*1000 -> -60000 | C17: =$C$21/$B$21*B17 -> -434220.98 | D17: =B17+C17 -> -494220.98 | E17: =D17*15%/2 -> -37066.574 | F17: =D17-E17 -> -457154.41 | G17: ='PPE- note 3'!E94*1000 -> -60000 | H17: =F17-G17 -> -397154.41
A18: Building | B18: ='PPE- note 3'!C93*1000 -> 0 | C18: =$C$21/$B$21*B18 -> 0 | D18: =B18+C18 -> 0 | E18: =D18*10%/2 -> 0 | F18: =D18-E18 -> 0 | G18: ='PPE- note 3'!E93*1000 -> 0 | H18: =F18-G18 -> 0
A19: Computers | B19: ='PPE- note 3'!C95*1000 -> -6000 | C19: =$C$21/$B$21*B19 -> -43422.098 | D19: =B19+C19 -> -49422.098 | E19: =D19*40%/2 -> -9884.4196 | F19: =D19-E19 -> -39537.678 | G19: ='PPE- note 3'!E95*1000 -> -6000 | H19: =F19-G19 -> -33537.678
A20: CWIP | B20: =BS!D10*1000 -> 1149427 | C20: =$C$21/$B$21*B20 -> 8318422.1 | D20: =B20+C20 -> 9467849.1 | F20: =SUM(F17:F19) -> -496692.09 | G20: =SUM(G17:G19) -> -66000 | H20: =SUM(H17:H19) -> -430692.09 | I20: =H20*25.168% -> -108396.58
B21: =SUM(B17:B20) -> 1083427 | C21: =B11+B6 -> 7840779 | D21: =B21+C21 -> 8924206 | E21: =SUM(E17:E20) -> -46950.993 | F21: =-(F17+F19) -> 496692.09 | G21: =('PPE- note 3'!J96-'PPE- note 3'!J92)*1000 -> -149000 | H21: =G21+F21 -> 347692.09 | I21: =H21*17.168% -> 59691.777
F22: =-F21*17.168% -> -85272.097 | G22: =-G21*17.168% -> 25580.32 | H22: =F22+G22 -> -59691.777
A25: Capital gains
A26: HDFC Overnight Fund - Direct Plan - Growth Option | B26: 875943.49 | D26: =B26+C26 -> 875943.49
A27: HDFC Liquid Fund-Direct Plan-Growth Option Cash, | B27: 2658651.4 | D27: =B27+C27 -> 2658651.4
B28: =SUM(B26:B27) -> 3534594.9 | D28: =SUM(D26:D27) -> 3534594.9
A30: HDFC Arbitrage Fund - Wholesale Plan - Growth - Direct Plan Arbitrage Fund, | B30: 13736481 | C30: =250+500+1000+500+1000+500+1387 -> 5137 | D30: =B30+C30 -> 13741618
B32: =B30+B28 -> 17271075 | D32: =D30+D28 -> 17276212
D33: =-'[12]TB BVS 31.3.24'!I73 -> 17331137
D34: =D32-D33 -> -54924.59 | E34: diff
A38: Leasehold
A39: Expenditure deferred relating to leasehold rights amortisation (AY 2023-24)
A40: Amortisation | B40: 1752790
A43: Expenditure deferred relating to leasehold rights amortisation (AY 2022-23)
A44: Int on borrowing | B44: 3344847.9 | C44: =B44 -> 3344847.9
A45: Amortisation | B45: 609875
A49: Leasehold land
A50: Cost of acquisition | B50: ='PPE- note 3'!E100*1000 -> 3244000 | C50: =B50 -> 3244000
C53: =SUM(C40:C52) -> 6588847.9
A55: Lease period
A56: 42789
A57: =(99*365)+A56 -> 78924 | B57: =(A57-A56)/365 -> 99
A58: Balance lease period
A59: 45292
A60: =A57 -> 78924 | B60: =(A60-A59)/365 -> 92.142466 | C60: =C53/B60/12 -> 5958.9317 | D60: Per month
A62: Jan 24 to March 24 | C62: =C60*3 -> 17876.795

Sheet Cash Flow_FY26
A1: =Input!$B$1 -> BVC Specialities Private Limited
A2: Statement of Cash Flows for the Year Ended 31 March 2026
D3: =Input!$D$2 -> (₹ in Lakh) | E3: =Input!$D$2 -> (₹ in Lakh)
A4: Particulars | C4: Year Ended | D4: Year Ended | E4: Year Ended
C5: =PL!D5 -> 31 March 2026 | D5: =PL!E5 -> 31 March 2025 | E5: =Input!$C$6 -> 31 March 2022
A6: Cash Flow from Operating Activities
A7: (Loss) before Tax | C7: =PL!D21 -> -7540.24 | D7: =PL!E21 -> -2030.4612 | E7: -8360 | I7: 10669.917 | J7: =C7-I7 -> -18210.157
A8: Adjustments for: | J8: =C8-I8 -> 0
A9: Depreciation and amortisation | C9: =PL!D18 -> 3180.683 | D9: =PL!E18 -> 1294.91 | E9: =PL!F18 -> 6 | I9: 3767 | J9: =C9-I9 -> -586.31698
A10: Inventory Written Off | C10: ='PL Notes 19-27'!C102 -> 13 | D10: 0
A11: Interest Income | C11: =-'PL Notes 19-27'!C28-'PL Notes 19-27'!C29 -> -23 | D11: =-'PL Notes 19-27'!D28-'PL Notes 19-27'!D29 -> -20
A12: Profit on sale of mutual fund | C12: =-'PL Notes 19-27'!C30 -> 0 | D12: =-'PL Notes 19-27'!D30 -> -49
A13: Unrealized foreign exchange loss/ (gain) | C13: =C147 -> -72.325743 | D13: 0
A14: Allowance for expected credit loss on trade receivables | C14: ='PL Notes 19-27'!C108 -> 15 | D14: 0
A15: Finance costs | C15: =PL!D17 -> 2699 | D15: =PL!E17 -> 763.08652 | E15: =PL!F17 -> 38 | I15: 3744 | J15: =C15-I15 -> -1045
C16: =SUM(C9:C15)+C7 -> -1727.8827 | D16: =SUM(D9:D15)+D7 -> -41.4647 | E16: =SUM(E9:E15)+E7 -> -8316 | I16: 18180.917 | J16: =C16-I16 -> -19908.8
J17: =C17-I17 -> 0
A18: Changes in working capital: | J18: =C18-I18 -> 0
A19: (Increase)/Decrease in Trade Receivable | C19: =BS!H24-C145-C14 -> -2476.2564 | D19: -397.74 | I19: -5611 | J19: =C19-I19 -> 3134.7436
A20: (Increase)/Decrease in Inventory | C20: =BS!H22-C10 -> -5840 | D20: -797.4 | I20: -1391 | J20: =C20-I20 -> -4449
A21: (Increase)/Decrease in Other Financial Assets | C21: =BS!H15 -> 45 | D21: 4.28 | I21: 745060 | J21: =C21-I21 -> -745015
A22: (Increase)/Decrease in Other Non-Financial Assets | C22: =+BS!H29+BS!H18+H34 -> -856 | D22: -1277.86 | E22: =F132-E132 -> -296 | I22: -462302 | J22: =C22-I22 -> 461446
A23: Increase/(Decrease) in Trade payable | C23: =BS!H53+BS!H54-C144-2 -> 8076.027 | D23: 1659.3 | E23: =(E134-F134)+E135 -> 14 | I23: 8661 | J23: =C23-I23 -> -584.97303
A24: Increase/(Decrease) in Employee Benefit Liabilities | C24: =BS!H45+BS!H58+PL!D30+PL!D31 -> 53 | D24: 22.74
A25: Increase/(Decrease) in Other Financial Liabilities | C25: =BS!H55 -> -2063 | D25: 48.56
A26: Increase/(Decrease) in Non-Financial Liabilities | C26: =BS!H56+BS!H57-'BS Notes 3-18'!O468 -> 2047 | D26: -23.2 | E26: =(E139-F139)-1 -> -1 | I26: 6029 | J26: =C26-I26 -> -3982
A27: Cash used in Operations | C27: =C16+SUM(C19:C26) -> -2742.1121 | D27: =D16+SUM(D19:D26) -> -802.7847 | E27: =E16+SUM(E22:E26) -> -8599 | I27: 308626.92 | J27: =C27-I27 -> -311369.03
A28: Income Taxes Paid | C28: =BS!H16+BS!H17-PL!D25 -> 9.1153389 | D28: 0 | H28: =C28 -> 9.1153389 | I28: -26514.917 | J28: =C28-I28 -> 26524.033
A29: Net Cash Flow from Operating Activities (A) | C29: =C27+C28 -> -2732.9967 | D29: =D27 -> -802.7847 | E29: =E27 -> -8599 | I29: 282112 | J29: =C29-I29 -> -284845
J30: =C30-I30 -> 0
A31: Cash Flow from Investing Activities | J31: =C31-I31 -> 0
A32: Acquisition of Property, Plant and Equipment and Change in Capital Work in Progress | C32: =BS!H8+BS!H9+BS!H10+BS!H11-C9+'BS Notes 3-18'!O468 -> -3424.4646 | D32: -23239.35 | E32: ='PPE- note 3'!C140 -> 1652 | F32: =1846-C9 -> -1334.683 | I32: -3316196 | J32: =C32-I32 -> 3312771.5
A33: Acquisition of Investments | C33: =-F34 -> -94 | D33: 0 | F33: JSW | I33: -292929 | J33: =C33-I33 -> 292835
A34: Investment in fixed deposit and bank balances other than cash and cash equivalent | C34: =BS!H28 -> -54 | D34: 0 | F34: 94 | G34: 1 | H34: 79 | I34: -2637 | J34: =C34-I34 -> 2583
A35: Interest Received | C35: ='PL Notes 19-27'!C28+'PL Notes 19-27'!C29 -> 23 | D35: 20.08 | I35: =F34+G34-H34 -> 16
A36: Proceeds from sale of mutual fund | C36: 0 | D36: 5548.6245
A37: Investment in mutual fund | C37: 0 | D37: -5499.725
A38: Loan given to fellow subsidiary | C38: 0 | D38: -110.95979
A39: Repayment of loan by fellow subsidiary | C39: 0 | D39: 3040.2498
A40: Net Cash Flow from Investing Activities (B) | C40: =SUM(C32:C39) -> -3549.4646 | D40: =SUM(D32:D39) -> -20241.081 | E40: =-SUM(E32:E32) -> -1652 | I40: -3611762 | J40: =C40-I40 -> 3608212.5
J41: =C41-I41 -> 0
A42: Cash Flow from Financing Activities | J42: =C42-I42 -> 0
A43: Proceeds from Borrowing | C43: =11031.4017499-C146+6709 -> 17730.957 | D43: 18784.569 | E43: 196862 | H43: =-'BS Notes 3-18'!H257 -> 0 | I43: 2269061 | J43: =C43-I43 -> -2251330
A44: Repayment from Borrowing | C44: -8742 | D44: =-7337.28968-1 -> -7338.2897
A45: Payment of Interest | C45: =-C15 -> -2699 | D45: -555.73585 | H45: =-'PL Notes 19-27'!C83 -> 0
A46: Interest on lease liabilities | C46: ='Note 28-31'!F107 -> 0 | D46: 0 | H46: =SUM(F46:G46) -> 0
A47: Payment of principal portion of lease liabilities | C47: ='Note 28-31'!F108 -> 0 | D47: 0 | H47: =SUM(F47:G47) -> 0
A48: Conversion of Optionally convertible preference shares into equity shares | C48: =BS!L37*0 -> 0 | D48: 0 | H48: =SUM(F48:G48) -> 0
A49: Issue of equity share capital including Premium | C49: =(BS!N37+BS!N38)-6709 -> 2.14137 | D49: 0 | E49: 100 | I49: 80197 | J49: =C49-I49 -> -80194.859
A50: Issue of preference share capital (CCPS) including preference share premium | C50: =BS!H36 -> 0 | D50: 9999.86 | E50: 199999 | I50: 999988 | J50: =C50-I50 -> -999988
A51: Net Cash Flow from Financing Activities (C) | C51: =SUM(C43:C50) -> 6292.0983 | D51: =SUM(D43:D50) -> 20890.403 | E51: =SUM(E43:E50) -> 396961 | I51: 3345502 | J51: =C51-I51 -> -3339209.9
J52: =C52-I52 -> 0
A53: Net Increase / (Decrease) in Cash and Cash Equivalents (A+ B+ C) | C53: =C29+C40+C51 -> 9.6369279 | D53: =D29+D40+D51 -> -153.46208 | E53: =E29+E40+E51 -> 386710 | I53: 15852 | J53: =C53-I53 -> -15842.363
A54: Cash and Cash Equivalents at the beginning of the period | C54: =D59 -> 22 | D54: =17543/100 -> 175.43 | E54: 0 | I54: 1304 | J54: =C54-I54 -> -1282
A55: Cash and Cash Equivalents at the end of the period | C55: =C53+C54 -> 31.636928 | D55: =D53+D54 -> 21.967918 | E55: =E53+E54 -> 386710 | I55: 17156 | J55: =C55-I55 -> -17124.363
A56: Notes to Statement of Cash Flows | J56: =C56-I56 -> 0
A57: 1. Cash and cash equivalent includes: | J57: =C57-I57 -> 0
A58: Balances with banks | C58: ='BS Notes 3-18'!G117 -> 31 | D58: ='BS Notes 3-18'!H117 -> 22 | E58: ='BS Notes 3-18'!I117 -> 24 | I58: 17543 | J58: =C58-I58 -> -17512
A59: Total Cash and Cash Equivalents | C59: =SUM(C58:C58) -> 31 | D59: =SUM(D58:D58) -> 22 | E59: =SUM(E58:E58) -> 24 | F59: =C59-C55 -> -0.63692792 | G59: =D59-D55 -> 0.03208186 | I59: 17543 | J59: =C59-I59 -> -17512
A60: 2. The above Statement of Cash Flows has been prepared under the 'Indirect Method' as set out in the Indian Accounting Standard (Ind AS) 7 - "Statement of Cash Flows".
A61: 3. Reconciliation of Financing Activities
A62: Particulars | B62: Lease Liabilities | C62: Borrowings | D62: Instrument entirely equity in nature | H62: Loan to subsidiary
A63: Cash Flow from Financing Activities
A64: Proceeds from borrowing/ Preference share capital | B64: =E50/100 -> 1999.99 | C64: =196862/100 -> 1968.62 | D64: =196862/100 -> 1968.62 | H64: 196862
A65: Repayment of borrowing | B65: 0 | C65: 0 | D65: 0 | H65: =#REF! -> #REF!
A66: Total Cash Flow from Financing Activities | B66: =SUM(B64:B65) -> 1999.99 | C66: =SUM(C64:C65) -> 1968.62 | D66: =SUM(D64:D65) -> 1968.62 | H66: =SUM(H64:H65) -> #REF!
A67: Liability related other changes | B67: =-'BS Notes 3-18'!G389+'PL Notes 19-27'!E83-1 -> -256 | C67: =2978/100 -> 29.78 | D67: =2978/100 -> 29.78 | H67: 2978
A68: Balance as at 31 March 2022 | B68: =174526/100 -> 1745.26 | C68: =2978/100 -> 29.78 | D68: 0 | F68: =SOCIE!B30+BS!F43-B68 -> -0.26 | G68: =BS!F50-C68 -> 0.22 | H68: 0
A69: Cash Flow from Financing Activities
A70: Proceeds from borrowing/ Preference share capital | B70: 0 | C70: =113714/100 -> 1137.14 | D70: 0 | H70: 0
A71: Total Cash Flow from Financing Activities | B71: =SUM(B70:B70) -> 0 | C71: =SUM(C70:C70) -> 1137.14 | D71: =SUM(D70:D70) -> 0 | H71: 0
A72: Liability related other changes | B72: =3600/100 -> 36 | C72: =1539/100 -> 15.39 | D72: 0 | H72: 0
A73: Balance as at 31 March 2023 | B73: =B68+B71+B72 -> 1781.26 | C73: =C68+C71+C72 -> 1182.31 | D73: =D68+D71+D72 -> 0 | F73: =SOCIE!B36+'BS Notes 3-18'!H257-B73 -> -531.26 | G73: =BS!E50+'BS Notes 3-18'!H258-C73 -> 4617.69 | H73: =H68+H71+H72 -> 0
A74: Cash Flow from Financing Activities
A75: Proceeds from borrowing/ Preference share capital | B75: 0 | C75: =2322187/100 -> 23221.87 | D75: 0
A76: Issue of preference share capital (CCPS) including preference share premium | B76: =C50*0 -> 0 | C76: 0 | D76: =999988/100 -> 9999.88
A77: Loan to subsdiary (net) | H77: =C38+C39 -> 0
A78: Payment of Interest | B78: 0 | C78: -1.34 | D78: 0 | H78: =-'CFS Working'!C3 -> -232
A79: Total Cash Flow from Financing Activities | B79: =SUM(B75:B78) -> 0 | C79: =SUM(C75:C78) -> 23220.53 | D79: =SUM(D75:D78) -> 9999.88 | F79: =+B79+C79-C51 -> 16928.432 | H79: =SUM(H75:H78) -> -232
A80: Liability related other changes | B80: =-B73 -> -1781.26 | C80: =134/100 -> 1.34 | D80: 0 | F80: Current | H80: =-H78 -> 232
A81: Equity related other changes | B81: =-B73*0 -> 0 | C81: 0 | D81: 0
A82: Balance as at 31 March 2024 | B82: =B73+B79+B80+B81 -> 0 | C82: =C73+C79+C80 -> 24404.18 | D82: ='BS Notes 3-18'!H179 -> 4.4097 | F82: =+B82-BS!D36+D82 -> -4.7771 | G82: =C82-BS!D50-BS!D43 -> -7037.82 | H82: =H73+H79+H80 -> 0
A83: Cash Flow from Financing Activities | F83: =+BS!D43+BS!D50 -> 31442
A84: Proceeds from borrowing | B84: 0 | C84: =1878456.881/100 -> 18784.569 | D84: 0
A85: Repayment from Borrowing | C85: =-733728.968/100 -> -7337.2897 | D85: 0
A86: Issue of preference share capital (CCPS) including preference share premium | B86: =C59*0 -> 0 | C86: 0 | D86: ='BS Notes 3-18'!H187 -> 4.7771
A87: Loan to subsdiary (net)
A88: Payment of Interest | B88: 0 | C88: =-55573.5849999999/100 -> -555.73585 | D88: 0
A89: Total Cash Flow from Financing Activities | B89: =SUM(B84:B88) -> 0 | C89: =SUM(C84:C88) -> 10891.543 | D89: =SUM(D84:D88) -> 4.7771
A90: Liability related other changes | B90: =-B82 -> 0 | C90: =-614309.328/100 -> -6143.0933 | D90: 0
A91: Equity related other changes | B91: =-B82*0 -> 0 | C91: 0 | D91: 0
A92: Balance as at 31 March 2025 | B92: =B82+B89+B90+B91 -> 0 | C92: =C82+C89+C90+C91 -> 29152.63 | D92: =D82+D89+D90 -> 9.1868 | F92: =(BS!D50+BS!D43)-C92 -> 2289.37 | G92: =D92-BS!D36 -> 0
A93: Cash Flow from Financing Activities
A94: Proceeds from borrowing/ Preference share capital | B94: 0 | C94: =C43 -> 17730.957 | D94: 0
A95: Repayment from Borrowing / Lease Liabilities | B95: =C47 -> 0 | C95: =C44 -> -8742
A96: Issue of preference share capital (CCPS) including preference share premium | B96: 0 | C96: 0 | D96: 0
A97: Issue of equity share capital including Premium | D97: 0
A98: Loan to subsdiary (net)
A99: Payment of Interest | B99: =C46 -> 0 | C99: =-C45 -> 2699 | D99: 0
A100: Total Cash Flow from Financing Activities | B100: =SUM(B95:B99) -> 0 | C100: =SUM(C94:C99) -> 11687.957 | D100: =SUM(D94:D99) -> 0
...

Sheet SOCIE
A1: =Input!$B$1 -> BVC Specialities Private Limited
A2: Statement of Changes in Equity (SOCIE) for the Year Ended on 31 March 2026
A5: (A) Equity Share Capital | E5: =Input!$D$2 -> (₹ in Lakh)
A6: Particulars | D6: As at 31 March 2026 | E6: As at 31 March 2025
A7: Balance at the beginning of the reporting year | D7: =E9 -> 13.6597 | E7: =1072/100 -> 10.72
A8: Changes in equity share capital during the year | D8: ='BS Notes 3-18'!G146-SOCIE!D7 -> 2.3192 | E8: =293.97/100 -> 2.9397
A9: Balance at the end of the reporting year | D9: =SUM(D7:D8) -> 15.9789 | E9: =SUM(E7:E8) -> 13.6597
A11: (B) Instruments entirely equity in nature
A12: Compulsory Convertible Preference Shares - Share Application Money Pending Allotment
A13: Particulars | D13: =CONCATENATE("As at ",Input!$C$4) -> As at 31 March 2024 | E13: =CONCATENATE("As at ",Input!$C$5) -> As at 31 March 2023
A14: Balance at the beginning of the reporting period
A15: Addition in compulsorily convertible preference shares during the year
A16: Balance at the end of the reporting period
A18: (B) Instrument Entirely Equity in Nature
A19: Particulars | D19: =D6 -> As at 31 March 2026 | E19: =E6 -> As at 31 March 2025
A20: Balance at the beginning of the reporting year | D20: =E22 -> 9.1868 | E20: ='BS Notes 3-18'!H179 -> 4.4097
A21: Changes in instruments entirely equity in nature during the year | D21: ='BS Notes 3-18'!G187 -> 0 | E21: ='BS Notes 3-18'!H187 -> 4.7771
A22: Balance at the end of the reporting year | D22: =SUM(D20:D21) -> 9.1868 | E22: =SUM(E20:E21) -> 9.1868
A24: (C) Other Equity
A25: Particulars | B25: Attributable to the equity shareholders | E25: Total Other Equity
B26: Equity component of compound financial instrument | C26: Reserve and Surplus
C27: Securities Premium | D27: Retained earnings
A28: Loss for the year | B28: 0 | C28: 0 | D28: -82.88 | E28: =SUM(B28:D28) -> -82.88
A29: Total comprehensive income for the year | B29: =SUM(B28) -> 0 | C29: =SUM(C28) -> 0 | D29: =SUM(D28) -> -82.88 | E29: =SUM(E28) -> -82.88
A30: Issue of Optionally Convertible Preference Shares | B30: ='BS Notes 3-18'!I231 -> 1250 | C30: 0 | D30: 0 | E30: =SUM(B30:D30) -> 1250
A31: =CONCATENATE("Balance as at ",Input!$C$6) -> Balance as at 31 March 2022 | B31: =B29+B30 -> 1250 | C31: =C29+C30 -> 0 | D31: =D29+D30 -> -82.88 | E31: =E29+E30 -> 1167.12 | G31: =BS!F37-SOCIE!E31 -> #REF! | H31: Check
A33: Balance as at 1 April 2022 | B33: =B31 -> 1250 | C33: =C31 -> 0 | D33: =D31 -> -82.88 | E33: =SUM(B33:D33) -> 1167.12
A34: Loss for the year | B34: 0 | C34: 0 | D34: -95.26 | E34: =SUM(B34:D34) -> -95.26
A35: Total comprehensive income for the year | B35: =SUM(B34:B34) -> 0 | C35: =SUM(C34:C34) -> 0 | D35: =SUM(D34:D34) -> -95.26 | E35: =SUM(E34:E34) -> -95.26
A36: Balance as at 31 March 2023 | B36: =B33+B35 -> 1250 | C36: =C33+C35 -> 0 | D36: =D33+D35 -> -178.14 | E36: =E33+E35 -> 1071.86 | G36: =BS!E37-SOCIE!E36 -> 25683.576 | H36: Check
A37: Profit (Loss) for the year | B37: 0 | C37: 0 | D37: =7151.5736058087/100 -> 71.515736 | E37: =SUM(B37:D37) -> 71.515736
A38: Contribution by and distribution to owners | B38: 0 | C38: 0 | D38: 0 | E38: =SUM(B38:D38) -> 0
A39: Redemption of compound financial instruments | B39: ='BS Notes 3-18'!H231 -> -1250 | C39: =204224/100 -> 2042.24 | D39: =386.61503/100 -> 3.8661503 | E39: =SUM(B39:D39) -> 796.10615
A40: Total contribution by and distribution to owners | B40: =SUM(B37:B39) -> -1250 | C40: =SUM(C37:C39) -> 2042.24 | D40: =SUM(D37:D39) -> 75.381886 | E40: =SUM(E37:E39) -> 867.62189
A41: Balance as at 31 March 2024 | B41: =B36+B40 -> 0 | C41: ='BS Notes 3-18'!H235 -> 12037.707 | D41: =D36+D40 -> -102.75811 | E41: =C41+D41 -> 11934.949 | J41: ='BS Notes 3-18'!H227-E41 -> 14820.488
A42: (Loss) for the year | B42: 0 | C42: 0 | D42: =PL!E26 -> -2029.0352 | E42: =SUM(B42:D42) -> -2029.0352
A43: Addition during the year | B43: ='BS Notes 3-18'!G231 -> 0 | C43: 0 | D43: 0 | E43: =SUM(B43:D43) -> 0
A44: Other comprehensive Income for the year | B44: 0 | C44: 0 | D44: =PL!E30+PL!E31 -> 2 | E44: =SUM(B44:D44) -> 2
A45: Total comprehensive income for the year | B45: =SUM(B42:B43) -> 0 | C45: =SUM(C42:C43) -> 0 | D45: =SUM(D42:D44) -> -2027.0352 | E45: =SUM(E42:E44) -> -2027.0352
A47: Transactions with owners of the Company
A48: Addition during the year - CCPS issued during the year | C48: ='BS Notes 3-18'!H236-C49 -> 9995.5827 | E48: =SUM(B48:D48) -> 9995.5827
A49: Securities premium on Loan converted into equity | B49: 0 | C49: =685231/100 -> 6852.31 | D49: 0 | E49: =SUM(B49:D49) -> 6852.31
A50: Total contribution by and distribution to owners | B50: =B41+B45 -> 0 | C50: =SUM(C48:C49) -> 16847.893 | D50: =D49 -> 0 | E50: =SUM(E48:E49) -> 16847.893
A53: Balance as at 31 March 2025 | B53: =B44+B49 -> 0 | C53: =C45+C50+C41 -> 28885.6 | D53: =D45+D50+D41 -> -2129.7933 | E53: =E45+E50+E41 -> 26755.806 | J53: ='BS Notes 3-18'!G227-E53 -> 763.21221
A54: (Loss) for the year | B54: 0 | C54: 0 | D54: =PL!D26 -> -5952.24 | E54: =SUM(B54:D54) -> -5952.24
A55: Addition during the year | B55: ='BS Notes 3-18'!G242 -> 0 | C55: 0 | D55: 0 | E55: =SUM(B55:D55) -> 0
A56: Other comprehensive Income for the year | B56: 0 | C56: 0 | D56: =PL!D30+PL!D31 -> 7 | E56: =SUM(B56:D56) -> 7
A57: Total comprehensive income for the year | B57: =SUM(B54:B55) -> 0 | C57: =SUM(C54:C55) -> 0 | D57: =SUM(D54:D56) -> -5945.24 | E57: =SUM(E54:E56) -> -5945.24
A59: Transactions with owners of the Company
A60: Securities premium on Loan converted into equity | B60: 0 | C60: ='BS Notes 3-18'!G236 -> 6708.8222 | D60: 0 | E60: =SUM(B60:D60) -> 6708.8222
A61: Total contribution by and distribution to owners | B61: =B53+B57 -> 0 | C61: =C60 -> 6708.8222 | D61: =D60 -> 0 | E61: =E60 -> 6708.8222
A64: Balance as at 31 March 2026 | B64: =B56+B60 -> 0 | C64: =C57+C61+C53 -> 35594.422 | D64: =D57+D61+D53 -> -8075.0332 | E64: =E57+E61+E53 -> 27519.389 | J64: ='BS Notes 3-18'!G238-E64 -> -27519.389
A66: The accompanying notes are integral part of the Financial Statements.
A67: As per our report of even date attached.
A69: =BS!$A$66 -> For B S R and Co | D69: ='Cash Flow_FY26'!C108 -> For and on behalf of Board of
A70: =BS!$A$67 -> Chartered Accountants | D70: ='Cash Flow_FY26'!C109 -> BVC Specialities Private Limited
A71: =BS!$A$68 -> Firm's Registration No: 128510W | D71: ='Cash Flow_FY26'!C110 -> CIN : U24230GJ2021PTC123855
A74: =BS!$A$71 -> Jeyur Shah | D74: =BS!D71 -> Shishir Srivastava | E74: =BS!E71 -> Shaju Ouseph Chazhoor
A75: =BS!$A$72 -> Partner | D75: =BS!D72 -> Director | E75: =BS!E72 -> Director
A76: =BS!$A$73 -> Membership No. 045754 | D76: =BS!D73 -> DIN: 00330342
D80: ='Cash Flow_FY26'!C118 -> Ambrish Dixit | E80: ='Cash Flow_FY26'!D118 -> Mukesh Lodha
D81: ='Cash Flow_FY26'!C119 -> CEO | E81: ='Cash Flow_FY26'!D119 -> CFO
A85: =BS!$A$82 -> Place: Ahmedabad | D85: =BS!D82 -> Place: Vadodara | E85: =BS!E82 -> Place: Vadodara
A86: =BS!$A$83 -> Date: 17 July 2026 | D86: =BS!D83 -> Date: 17 July 2026 | E86: =BS!E83 -> Date: 17 July 2026

Sheet PPE- note 3
A1: =BS!A1 -> BVC Specialities Private Limited
A2: Notes to Financial Statements for the year ended 31 March 2026
A4: NOTE 3 | K4: =Input!$D$2 -> (₹ in Lakh)
B5: GROSS BLOCK | F5: ACCUMULATED DEPRECIATION | J5: NET BLOCK
A6: Particulars | B6: Balance as at 1 April 2025 | C6: Additions During the year | D6: Disposals / Adjustments During the year | E6: Balance as at 31 March 2026 | F6: =B6 -> Balance as at 1 April 2025 | G6: Additions During the year | H6: Disposals / Adjustments During the year | I6: =E6 -> Balance as at 31 March 2026 | J6: =I6 -> Balance as at 31 March 2026 | K6: Balance as at 31 March 2025
A9: (a) Property, Plant & Equipment
A10: Freehold land | B10: =E34 -> 935.99 | C10: 0 | D10: 0 | E10: =(B10+C10)-D10 -> 935.99 | F10: =I34 -> 0 | G10: 0 | H10: 0 | I10: =SUM(F10:H10) -> 0 | J10: =E10-I10 -> 935.99 | K10: =B10-F10 -> 935.99
A11: Building | B11: =E35 -> 14795.42 | C11: =593538.72/100000 -> 5.9353872 | D11: 0 | E11: =(B11+C11)-D11 -> 14801.355 | F11: =I35 -> 240 | G11: ='TB BVS 31.03.26'!G161/100000-0.5 -> 570.41697 | H11: 0 | I11: =SUM(F11:H11) -> 810.41697 | J11: =E11-I11 -> 13990.938 | K11: =B11-F11 -> 14555.42
A12: Plant and machinery | B12: =E36 -> 33852.14 | C12: =24338032.2/100000 -> 243.38032 | D12: 0 | E12: =(B12+C12)-D12 -> 34095.52 | F12: =I36 -> 983 | G12: ='TB BVS 31.03.26'!G162/100000 -> 2340.9066 | H12: 0 | I12: =SUM(F12:H12) -> 3323.9066 | J12: =E12-I12 -> 30771.614 | K12: =B12-F12 -> 32869.14
A13: Office Equipment | B13: =E37 -> 196 | C13: 0 | D13: 0 | E13: =(B13+C13)-D13 -> 196 | F13: =I37 -> 11 | G13: ='TB BVS 31.03.26'!G165/100000 -> 37.231881 | H13: 0 | I13: =SUM(F13:H13) -> 48.231881 | J13: =E13-I13 -> 147.76812 | K13: =B13-F13 -> 185
A14: Computers | B14: =E38 -> 168.95 | C14: 0 | D14: 0 | E14: =(B14+C14)-D14 -> 168.95 | F14: =I38 -> 15.42 | G14: ='TB BVS 31.03.26'!G163/100000 -> 36.132477 | H14: 0 | I14: =SUM(F14:H14) -> 51.552477 | J14: =E14-I14 -> 117.39752 | K14: =B14-F14 -> 153.53
A15: Furniture & Fixtures | B15: =E39 -> 206 | C15: 0 | D15: 0 | E15: =(B15+C15)-D15 -> 206 | F15: =I39 -> 6 | G15: ='TB BVS 31.03.26'!G166/100000 -> 19.558193 | H15: 0 | I15: =SUM(F15:H15) -> 25.558193 | J15: =E15-I15 -> 180.44181 | K15: =B15-F15 -> 200
A16: Electrical Fittings | B16: =E40 -> 1335 | C16: =461110.11/100000 -> 4.6111011 | D16: 0 | E16: =(B16+C16)-D16 -> 1339.6111 | F16: =I40 -> 39 | G16: ='TB BVS 31.03.26'!G167/100000 -> 126.94553 | H16: 0 | I16: =SUM(F16:H16) -> 165.94553 | J16: =E16-I16 -> 1173.6656 | K16: =B16-F16-1 -> 1295 | L16: =J17-J10+J27 -> 46411.007
A17: Total | B17: =SUM(B10:B16) -> 51489.5 | C17: =SUM(C10:C16) -> 253.92681 | D17: =SUM(D10:D16) -> 0 | E17: =SUM(E10:E16) -> 51743.427 | F17: =SUM(F10:F16) -> 1294.42 | G17: =SUM(G10:G16) -> 3131.1917 | H17: =SUM(H10:H16) -> 0 | I17: =SUM(I10:I16) -> 4425.6117 | ... K17: =SUM(K10:K16) -> 50194.08
A18: Capital work-in-progress | B18: =E42 -> 0 | C18: 1403.3538 | D18: 253.92681 | E18: =(B18+C18)-D18 -> 1149.427 | F18: 0 | G18: 0 | H18: 0 | I18: =SUM(F18:H18) -> 0 | J18: =E18-I18 -> 1149.427 | K18: =B18-F18 -> 0
A20: (b) Right of use assets
A21: Leasehold land | B21: =E45 -> 3244 | C21: 0 | D21: 0 | E21: =(B21+C21)-D21 -> 3244 | F21: =I45 -> 93 | G21: ='TB BVS 31.03.26'!G164/100000 -> 34.673342 | H21: 0 | I21: =SUM(F21:H21) -> 127.67334 | J21: =E21-I21 -> 3116.3267 | K21: =B21-F21 -> 3151 | M21: =G21/10^2 -> 0.34673342
A22: Building on lease | B22: 0 | C22: 0 | D22: 0 | E22: =(B22+C22)-D22 -> 0 | F22: 0 | G22: 0 | H22: 0 | I22: =SUM(F22:H22) -> 0 | J22: =E22-I22 -> 0 | K22: =B22-F22 -> 0
A23: Total Right of Use Assets | B23: =SUM(B21:B22) -> 3244 | C23: =SUM(C21:C22) -> 0 | D23: =SUM(D21:D22) -> 0 | E23: =SUM(E21:E22) -> 3244 | F23: =SUM(F21:F22) -> 93 | G23: =SUM(G21:G22) -> 34.673342 | H23: =SUM(H21:H22) -> 0 | I23: =SUM(I21:I22) -> 127.67334 | ... K23: =SUM(K21:K22) -> 3151
A25: (c) Intangible Assets
A26: Software | B26: =E49 -> 47 | C26: 0 | D26: 0 | E26: =SUM(B26:D26) -> 47 | F26: =I49 -> 3 | G26: ='TB BVS 31.03.26'!G168/100000 -> 14.818003 | H26: 0 | I26: =(F26+G26)-H26 -> 17.818003 | J26: =E26-I26 -> 29.181997 | K26: =B26-F26 -> 44
A27: Total | B27: =SUM(B26) -> 47 | C27: =SUM(C26) -> 0 | D27: =SUM(D26) -> 0 | E27: =SUM(E26) -> 47 | F27: =SUM(F26) -> 3 | G27: =SUM(G26) -> 14.818003 | H27: =SUM(H26) -> 0 | I27: =SUM(I26) -> 17.818003 | ... K27: =SUM(K26) -> 44
B29: GROSS BLOCK | F29: ACCUMULATED DEPRECIATION | J29: NET BLOCK
A30: Particulars | B30: Balance as at 1 April 2024 | C30: Additions During the year | D30: Disposals / Adjustments During the year | E30: Balance as at 31 March 2025 | F30: =B30 -> Balance as at 1 April 2024 | G30: Additions During the year | H30: Disposals / Adjustments During the year | I30: =E30 -> Balance as at 31 March 2025 | J30: =I30 -> Balance as at 31 March 2025 | K30: Balance as at 31 March 2024
A33: (a) Property, Plant & Equipment
A34: Freehold land | B34: =93599/100 -> 935.99 | C34: 0 | D34: 0 | E34: =(B34+C34)-D34 -> 935.99 | F34: 0 | G34: 0 | H34: 0 | I34: =SUM(F34:H34) -> 0 | J34: =E34-I34 -> 935.99 | K34: =B34-F34 -> 935.99
A35: Building | B35: =165422/100 -> 1654.22 | C35: =13141+0.2 -> 13141.2 | D35: 0 | E35: =(B35+C35)-D35 -> 14795.42 | F35: 11 | G35: 229 | H35: 0 | I35: =SUM(F35:H35) -> 240 | J35: =E35-I35 -> 14555.42 | K35: =B35-F35 -> 1643.22
A36: Plant and machinery | B36: =384414/100 -> 3844.14 | C36: 30008 | D36: 0 | E36: =(B36+C36)-D36 -> 33852.14 | F36: 26 | G36: 957 | H36: 0 | I36: =SUM(F36:H36) -> 983 | J36: =E36-I36 -> 32869.14 | K36: =B36-F36 -> 3818.14
A37: Office Equipment | B37: 0 | C37: =ROUND((19595727)/Input!$C$2,Input!$E$2) -> 196 | D37: 0 | E37: =(B37+C37)-D37 -> 196 | F37: 0 | G37: 11 | H37: 0 | I37: =SUM(F37:H37) -> 11 | J37: =E37-I37 -> 185 | K37: 0
A38: Computers | B38: =195/100 -> 1.95 | C38: =ROUND((16707552.65)/Input!$C$2,Input!$E$2) -> 167 | D38: 0 | E38: =(B38+C38)-D38 -> 168.95 | F38: 0.42 | G38: 15 | H38: 0 | I38: =SUM(F38:H38) -> 15.42 | J38: =E38-I38 -> 153.53 | K38: =B38-F38 -> 1.53
A39: Furniture & Fixtures | B39: 0 | C39: =ROUND((20587570.11)/Input!$C$2,Input!$E$2) -> 206 | D39: 0 | E39: =(B39+C39)-D39 -> 206 | F39: 0 | G39: 6 | H39: 0 | I39: =SUM(F39:H39) -> 6 | J39: =E39-I39 -> 200 | K39: 0
A40: Electrical Fittings | B40: 0 | C40: =ROUND((133494755.59)/Input!$C$2,Input!$E$2) -> 1335 | D40: 0 | E40: =(B40+C40)-D40 -> 1335 | F40: 0 | G40: 39 | H40: 0 | I40: =SUM(F40:H40) -> 39 | J40: =E40-I40-1 -> 1295 | K40: 0
A41: Total | B41: =SUM(B34:B40) -> 6436.3 | C41: =SUM(C34:C40) -> 45053.2 | D41: =SUM(D34:D40) -> 0 | E41: =SUM(E34:E40) -> 51489.5 | F41: =SUM(F34:F40) -> 37.42 | G41: =SUM(G34:G40) -> 1257 | H41: =SUM(H34:H40) -> 0 | I41: =SUM(I34:I40) -> 1294.42 | ... K41: =SUM(K34:K40) -> 6398.88
A42: Capital work-in-progress | B42: 26248 | C42: =1923263.76852/100 -> 19232.638 | D42: =4548092.49756997/100 -> 45480.925 | E42: 0 | F42: 0 | G42: 0 | H42: 0 | I42: 0 | J42: =E42-I42 -> 0 | K42: =B42-F42 -> 26248
A44: (b) Right of use assets
A45: Leasehold land | B45: 3244 | C45: 0 | D45: 0 | E45: =(B45+C45)-D45 -> 3244 | F45: 58 | G45: =ROUND('TB BVS 31.03.26'!I164/Input!$C$2,Input!$E$2) -> 35 | H45: 0 | I45: =SUM(F45:H45) -> 93 | J45: =E45-I45 -> 3151 | K45: =B45-F45 -> 3186 | M45: =G45/10^2 -> 0.35
A46: Total Right of Use Assets | B46: =SUM(B45) -> 3244 | C46: =SUM(C45) -> 0 | D46: =SUM(D45) -> 0 | E46: =SUM(E45) -> 3244 | F46: =SUM(F45) -> 58 | G46: =SUM(G45) -> 35 | H46: =SUM(H45) -> 0 | I46: =SUM(I45) -> 93 | ... K46: =SUM(K45) -> 3186
A48: (c) Intangible Assets
A49: Software | B49: =E114 -> 0 | C49: =ROUND((4679369.24)/Input!$C$2,Input!$E$2) -> 47 | D49: 0 | E49: =SUM(B49:D49) -> 47 | F49: =I114 -> 0 | G49: 3 | H49: 0 | I49: =(F49+G49)-H49 -> 3 | J49: =E49-I49 -> 44 | K49: =B49-F49 -> 0
A50: Total | B50: =SUM(B49) -> 0 | C50: =SUM(C49) -> 47 | D50: =SUM(D49) -> 0 | E50: =SUM(E49) -> 47 | F50: =SUM(F49) -> 0 | G50: =SUM(G49) -> 3 | H50: =SUM(H49) -> 0 | I50: =SUM(I49) -> 3 | ... K50: =SUM(K49) -> 0
A52: Capital Work in Progress (CWIP) Ageing Schedule as at 31 March 2026 | F52: =Input!$D$2 -> (₹ in Lakh)
A53: CWIP | B53: Amount in CWIP for a period of | F53: Total
B54: Less than 1 Year | C54: 1-2 Years | D54: 2-3 Years | E54: More than 3 Years
A55: Projects in Progress | B55: =114062452/100000+880309/100000 -> 1149.4276 | C55: 0 | D55: =ROUND(0/Input!$C$2,Input!$E$2) -> 0 | E55: 0 | F55: =SUM(B55:E55) -> 1149.4276
A56: Total | B56: =SUM(B55:B55) -> 1149.4276 | C56: =SUM(C55:C55) -> 0 | D56: =SUM(D55:D55) -> 0 | E56: =SUM(E55:E55) -> 0 | F56: =SUM(F55:F55) -> 1149.4276
A58: CWIP - Completion Schedule whose completion date is overdue or has exceeded its cost compared to its original plan: | F58: =Input!$D$2 -> (₹ in Lakh)
A59: CWIP | B59: To be completed in | F59: Total
B60: Less than 1 Year | C60: 1-2 Years | D60: 2-3 Years | E60: More than 3 Years
A61: Projects in Progress
A62: Change Control WBS | B62: 34.527088 | C62: 0 | D62: 0 | E62: 0 | F62: =SUM(B62:E62) -> 34.527088
A63: CIVIL WORK - MISC ON DAHEJ SITE | B63: 13.588511 | C63: 0 | D63: 0 | E63: 0 | F63: =SUM(B63:E63) -> 13.588511
A64: Change Control Realted MISC. work | B64: 20.391015 | C64: 0 | D64: 0 | E64: 0 | F64: =SUM(B64:E64) -> 20.391015
A65: STEAM SUPPLY LINE- WILLOWOOD TO BVCSPL | B65: 166.34045 | C65: 0 | D65: 0 | E65: 0 | F65: =SUM(B65:E65) -> 166.34045
A66: Civil Work for Storm water Diversion | B66: 19.443312 | C66: 0 | D66: 0 | E66: 0 | F66: =SUM(B66:E66) -> 19.443312
A67: PA SYSTEM UNIT-3 | B67: 18.7176 | C67: 0 | D67: 0 | E67: 0 | F67: =SUM(B67:E67) -> 18.7176
A68: MEE/ETP Plant Stabilization | B68: 54.924559 | C68: 0 | D68: 0 | E68: 0 | F68: =SUM(B68:E68) -> 54.924559
A69: UV LIGHT TRIAL IN FG BLENDER | B69: 16.535972 | C69: 0 | D69: 0 | E69: 0 | F69: =SUM(B69:E69) -> 16.535972
A70: Anethole Re-organization | B70: 80.617371 | C70: 0 | D70: 0 | E70: 0 | F70: =SUM(B70:E70) -> 80.617371
A71: PMA capacity enhancement | B71: 64.66087 | C71: 0 | D71: 0 | E71: 0 | F71: =SUM(B71:E71) -> 64.66087
A72: 232 Hydrogenation in REC-10302 | B72: 59.24684 | C72: 0 | D72: 0 | E72: 0 | F72: =SUM(B72:E72) -> 59.24684
A73: BRINE SYSTEM COMMISSIONING & OPERATIONAL | B73: 18.927676 | C73: 0 | D73: 0 | E73: 0 | F73: =SUM(B73:E73) -> 18.927676
... A82: OXIDATION REACTOR REPLACEMENT | B82: 47.097585 | C82: 0 | D82: 0 | E82: 0 | F82: =SUM(B82:E82) -> 47.097585
A83: Others | B83: 138 | F83: =SUM(B83:E83) -> 138
A84: Total | B84: =SUM(B62:B83) -> 1042.3683 | C84: =SUM(C57:C82) -> 0 | D84: =SUM(D57:D82) -> 0 | E84: =SUM(E57:E82) -> 0 | F84: =SUM(F62:F83) -> 1042.3683
B87: GROSS BLOCK | F87: ACCUMULATED DEPRECIATION | J87: NET BLOCK
A88: Particulars | B88: =CONCATENATE("Balance as at ",Input!$D$5) -> Balance as at 1 April 2023 | C88: Additions During the year | D88: Disposals / Adjustments During the year | E88: =CONCATENATE("Balance as at ",Input!$C$4) -> Balance as at 31 March 2024 | F88: =B88 -> Balance as at 1 April 2023 | G88: Additions During the year | H88: Disposals / Adjustments During the year | I88: =E88 -> Balance as at 31 March 2024 | J88: =CONCATENATE("Balance as at ",Input!$C$4) -> Balance as at 31 March 2024 | K88: =CONCATENATE("Balance as at ",Input!$C$5) -> Balance as at 31 March 2023
A91: (a) Property, Plant & Equipment
A92: Freehold land | B92: =E121 -> 929 | C92: =ROUND((695120)/Input!$C$2,Input!$E$2) -> 7 | D92: 0 | E92: =(B92+C92)-D92 -> 936 | F92: =I121 -> 0 | G92: 0 | H92: 0 | I92: =SUM(F92:H92) -> 0 | J92: =E92-I92 -> 936 | K92: =B92-F92 -> 929 | M92: 0
A93: Building | B93: 0 | C93: =ROUND(('TB BVS 31.3.25'!I151)/Input!$C$2,Input!$E$2) -> 0 | D93: 0 | E93: =(B93+C93)-D93 -> 0 | F93: 0 | G93: =ROUND('TB BVS 31.3.25'!I153/Input!$C$2,Input!$E$2) -> 0 | H93: 0 | I93: =SUM(F93:H93) -> 0 | J93: =E93-I93 -> 0 | K93: =B93-F93 -> 0
A94: Plant and machinery | B94: 0 | C94: =ROUND(('TB BVS 31.3.25'!I30)/Input!$C$2,Input!$E$2) -> -60 | D94: 0 | E94: =(B94+C94)-D94 -> -60 | F94: 0 | G94: =ROUND('TB BVS 31.3.25'!I102/Input!$C$2,Input!$E$2) -> 69 | H94: 0 | I94: =SUM(F94:H94) -> 69 | J94: =E94-I94 -> -129 | K94: =B94-F94 -> 0 | M94: =E94*7.5% -> -4.5
A95: Computers | B95: 0 | C95: =ROUND(('TB BVS 31.3.25'!I31)/Input!$C$2,Input!$E$2) -> -6 | D95: 0 | E95: =(B95+C95)-D95 -> -6 | F95: 0 | G95: =ROUND('TB BVS 31.3.25'!I103/Input!$C$2,Input!$E$2) -> 14 | H95: 0 | I95: =SUM(F95:H95) -> 14 | J95: =E95-I95 -> -20 | K95: =B95-F95 -> 0 | M95: =E95*20% -> -1.2
A96: Total | B96: =SUM(B92:B95) -> 929 | C96: =SUM(C92:C95) -> -59 | D96: =SUM(D92:D95) -> 0 | E96: =SUM(E92:E95) -> 870 | F96: =SUM(F92:F95) -> 0 | G96: =SUM(G92:G95) -> 83 | H96: =SUM(H92:H95) -> 0 | I96: =SUM(I92:I95) -> 83 | ... K96: =SUM(K92:K95) -> 929
A97: Capital work-in-progress | B97: =E123 -> 167 | C97: =3133325+(20631063.744/1000)+(1223695/1000)+(1269016/1000)+(1524042.31/1000) -> 3157972.8 | D97: =E94+E93 -> -60 | E97: =(B97+C97)-D97 -> 3158199.8 | F97: 0 | G97: 0 | H97: 0 | I97: 0 | J97: =E97-I97 -> 3158199.8 | K97: =B97-F97 -> 167
A99: (b) Right of use assets
A100: Leasehold land | B100: =E126 -> 1652 | C100: =ROUND( 159200000/Input!$C$2,Input!$E$2) -> 1592 | D100: 0 | E100: =(B100+C100)-D100 -> 3244 | F100: =I126 -> 24 | G100: =ROUND('TB BVS 31.3.25'!I104/Input!$C$2,Input!$E$2) -> 12 | H100: 0 | I100: =SUM(F100:H100) -> 36 | J100: =E100-I100 -> 3208 | K100: =B100-F100 -> 1628 | M100: =G100*0 -> 0
A101: Total Right of Use Assets | B101: =SUM(B100) -> 1652 | C101: =SUM(C100) -> 1592 | D101: =SUM(D100) -> 0 | E101: =SUM(E100) -> 3244 | F101: =SUM(F100) -> 24 | G101: =SUM(G100) -> 12 | H101: =SUM(H100) -> 0 | I101: =SUM(I100) -> 36 | ... K101: =SUM(K100) -> 1628
A103: =CONCATENATE("Capital Work in Progress (CWIP) Ageing Schedule as at ",Input!$C$4) -> Capital Work in Progress (CWIP) Ageing Schedule as at 31 March 2024 | F103: =Input!$D$2 -> (₹ in Lakh)
A104: CWIP | B104: Amount in CWIP for a period of | F104: Total
B105: Less than 1 Year | C105: 1-2 Years | D105: 2-3 Years | E105: More than 3 Years
A106: Projects in Progress | B106: =B97+C97-D97 -> 3158199.8 | C106: =ROUND(0/Input!$C$2,Input!$E$2) -> 0 | D106: =ROUND(0/Input!$C$2,Input!$E$2) -> 0 | E106: =ROUND(0/Input!$C$2,Input!$E$2) -> 0 | F106: =SUM(B106:E106) -> 3158199.8
A107: Total | B107: =SUM(B106:B106) -> 3158199.8 | C107: =SUM(C106:C106) -> 0 | D107: =SUM(D106:D106) -> 0 | E107: =SUM(E106:E106) -> 0 | F107: =SUM(F106:F106) -> 3158199.8
A109: CWIP - Completion Schedule whose completion date is overdue or has exceeded its cost compared to its original plan: | F109: =Input!$D$2 -> (₹ in Lakh)
A110: CWIP | B110: To be completed in | F110: Total
B111: Less than 1 Year | C111: 1-2 Years | D111: 2-3 Years | E111: More than 3 Years
A112: Projects in Progress
A113: Project Nirman | B113: =B107 -> 3158199.8 | C113: 0 | D113: 0 | E113: 0 | F113: =SUM(B113:E113) -> 3158199.8
A114: Total | B114: =SUM(B108:B113) -> 3158199.8 | C114: =SUM(C108:C113) -> 0 | D114: =SUM(D108:D113) -> 0 | E114: =SUM(E108:E113) -> 0 | F114: =SUM(F108:F113) -> 3158199.8
B116: GROSS BLOCK | F116: ACCUMULATED DEPRECIATION | J116: NET BLOCK
A117: Particulars | B117: =CONCATENATE("Balance as at ",Input!$D$6) -> Balance as at 1 April 2022 | C117: Additions During the year | D117: Disposals / Adjustments During the year | E117: =CONCATENATE("Balance as at ",Input!$C$5) -> Balance as at 31 March 2023 | F117: =CONCATENATE("Balance as at ",Input!$D$6) -> Balance as at 1 April 2022 | G117: Additions During the year | H117: Disposals / Adjustments During the year | I117: =CONCATENATE("Balance as at ",Input!$C$5) -> Balance as at 31 March 2023 | J117: =CONCATENATE("Balance as at ",Input!$C$5) -> Balance as at 31 March 2023 | K117: =CONCATENATE("Balance as at ",Input!$C$6) -> Balance as at 31 March 2022
A120: (a) Property, Plant & Equipment
A121: Freehold land | B121: 0 | C121: =ROUND(('TB BVS 31.3.23'!J22+'TB BVS 31.3.23'!J23)/Input!$C$2,Input!$E$2) -> 929 | D121: 0 | E121: =(B121+C121)-D121 -> 929 | F121: 0 | G121: 0 | H121: 0 | I121: =SUM(F121:H121) -> 0 | J121: =E121-I121 -> 929 | K121: =B121-F121 -> 0
A122: Total | B122: =SUM(B121:B121) -> 0 | C122: =SUM(C121:C121) -> 929 | D122: =SUM(D121:D121) -> 0 | E122: =SUM(E121:E121) -> 929 | F122: =SUM(F121:F121) -> 0 | G122: =SUM(G121:G121) -> 0 | H122: =SUM(H121:H121) -> 0 | I122: =SUM(I121:I121) -> 0 | ... K122: =SUM(K121:K121) -> 0
A123: Capital work in progress | B123: 0 | C123: =ROUND(('TB BVS 31.3.23'!J24)/Input!$C$2,Input!$E$2) -> 167 | D123: 0 | E123: =(B123+C123)-D123 -> 167 | J123: =E123 -> 167 | K123: 0
A125: (b) Right of use assets
A126: Leasehold land | B126: =E140 -> 1652 | C126: 0 | D126: 0 | E126: =(B126+C126)-D126 -> 1652 | F126: =I140 -> 6 | G126: =ROUND('TB BVS 31.3.23'!J36/Input!$C$2,Input!$E$2) -> 18 | H126: 0 | I126: =SUM(F126:H126) -> 24 | J126: =E126-I126 -> 1628 | K126: =B126-F126 -> 1646
A127: Total Right of Use Assets | B127: =SUM(B126) -> 1652 | C127: =SUM(C126) -> 0 | D127: =SUM(D126) -> 0 | E127: =SUM(E126) -> 1652 | F127: =SUM(F126) -> 6 | G127: =SUM(G126) -> 18 | H127: =SUM(H126) -> 0 | I127: =SUM(I126) -> 24 | ... K127: =SUM(K126) -> 1646
A129: =CONCATENATE("Capital Work in Progress (CWIP) Ageing Schedule as at ",Input!$C$5) -> Capital Work in Progress (CWIP) Ageing Schedule as at 31 March 2023 | F129: =Input!$D$2 -> (₹ in Lakh)
A130: CWIP | B130: Amount in CWIP for a period of | F130: Total
B131: Less than 1 Year | C131: 1-2 Years | D131: 2-3 Years | E131: More than 3 Years
A132: Projects in Progress | B132: =C123 -> 167 | C132: =ROUND(0/Input!$C$2,Input!$E$2) -> 0 | D132: =ROUND(0/Input!$C$2,Input!$E$2) -> 0 | E132: =ROUND(0/Input!$C$2,Input!$E$2) -> 0 | F132: =SUM(B132:E132) -> 167
...

Sheet Draft-TC
A1: 100000
B2: Name : | C2: BVC Specialities Private Limited | E2: PAN : | F2: AAJCB9629E
B3: Address : | C3: 801 to 809, 824, 8th FLOOR, BLOCK 1, BUILDING 73, EST AVENUE, SARABHAI COMPOUND VADODARA - 390023 | E3: A.Y. : | F3: 2026 - 2027
E4: P.Y. : | F4: 2025 - 2026
B7: STATEMENT SHOWING COMPUTATION OF INCOME
B8: PARTICULARS | E8: Amt In INR | F8: Amt In INR | I8: MSME
B10: I | C10: Income From Business
C11: Net Profit as per Statement of Profit and Loss before tax | F11: =PL!D21*100000 -> -7.54024e+08
B13: Add: | C13: Items disallowed
C14: Expenditure relating to trading activities/Other disallowances
C15: Penalty | E15: =+'[14]TB BVS 31.03.26'!I148 -> 130000
C16: Interest on lease liability | E16: 0
C17: Depreciation as per P&L | E17: =+[14]PL!D17*A1 -> 3.181183e+08
C18: Allowance for expected credit loss on trade receivables | E18: =-'[14]TB BVS 31.03.26'!I254 -> 1495028
C19: 43B | E19: =-'[14]43B'!J31 -> 7925794.5
F23: =SUM(E14:E23) -> 3.2766912e+08
B25: Less: | C25: Income considered under other head/ignored for tax
C26: Depreciation as per IT Act | E26: =-'[14]IT Dep_FY26'!P17 -> -633596523
C27: 35D - Preliminary expenses (5th year) | E27: -8400
C28: Interest Income Bank and DVG/MGVCL deposits | E28: =+'[14]TB BVS 31.03.26'!I111+'[14]TB BVS 31.03.26'!I112 -> -2084498.5
C29: Interest income IND AS | E29: =+'[14]TB BVS 31.03.26'!I114 -> -192594.37
C30: Interest on Income Tax refund
C31: Leasehold amortisation | E31: =-[14]Lease!C27 -> -3556823.5
F33: =SUM(E26:E33) -> -6.3943884e+08
C34: Income from business / profession | F34: =+F11+F23+F33 -> -1.0657937e+09
B36: III | C36: Income From Other Sources
C37: Interest Income Bank and DVG/MGVCL deposits | D37: =-E28-D38 -> 1961890.5
C38: Interest on Income Tax refund | D38: =(2351850-2229242) -> 122608 | H38: Other Income postd in books
D40: =SUM(D37:D39) -> 2084498.5
C41: Less:- Interest expenditure | D41: 0 | E41: =D40-D41 -> 2084498.5 | F41: =SUM(E37:E41) -> 2084498.5
C43: Total | F43: =F34+F41 -> -1.0637092e+09 | H43: =+F43-E26 -> -4.3011269e+08
B46: STATEMENT SHOWING COMPUTATION OF TAX
B47: PARTICULARS | E47: =E8 -> Amt In INR | F47: =F8 -> Amt In INR
C48: TOTAL INCOME | F48: 0
C50: Income Subject To Normal Rates | D50: 0.15 | E50: =IF(F43>0,F43,0) -> 0 | F50: =D50*E50 -> 0
C51: Income Subject To Special Rates | D51: 0.22 | E51: =(F34+F41)*0 -> 0 | F51: =D51*E51 -> 0
C52: Income Subject To Special Rates | D52: 0.1 | E52: 0 | F52: 0
C53: Total Income Tax | F53: =SUM(F50:F52) -> 0
B54: Add : | C54: Surcharge @ 10% | F54: =F53*10% -> 0
B55: Add : | C55: Education Cess @ 4% | F55: =(F53+F54)*4% -> 0
C56: Total Income Tax | F56: =SUM(F53:F55) -> 0
B58: Add : | C58: Interest Payable
C59: Interest Under Section 234 A | E59: 0
C60: Interest Under Section 234 B | E60: 0
C61: Interest Under Section 234 C | E61: =K59*0 -> 0 | F61: =SUM(E60:E61)*0 -> 0
C62: Total Tax Payable | F62: =F56+F61 -> 0
B64: Less: | C64: Prepaid Taxes
C65: Advance Tax
C66: TDS | E66: =[15]TDS!D26 -> 2941166
C67: TCS
C68: Self Assessment Tax Paid | F68: =SUM(E65:E68) -> 2941166
C70: Refund | F70: =F62-F68 -> -2941166
E75: FY22
C76: Particulars | D76: BVO | E76: BVS
C77: Loss as per Financial | D77: -16656915 | E77: -7940372.2
C79: *Expense Disallowed | D79: 2204673 | E79: 356064
C80: Expense Disallowed in Current FY but allowed in Subsequent FY | D80: 14144259 | E80: 7276273.6
C82: Preliminery expense claimed 1st Year of 5 Year | E82: 33600
C83: Preliminery expense claimed in 2nd Year of 5 Year | D83: -1000 | E83: 0
C84: Net Loss Carried Forward in Current FY | D84: -308982.95 | E84: -274434.53

Sheet DT-FY26
A3: Particulars | B3: Amount
A4: Loss as per computation | B4: =+'[16]Draft-TC'!H43 -> -4.3252493e+08 | C4: Current year Business loss
A5: Carried Forward loss - Business | B5: =-[16]Forecast!G84 -> -59756367 | C5: As per Return | F5: 43,75,67,746
A6: Total Loss | B6: =SUM(B4:B5) -> -4.9228129e+08
A7: Tax rate | B7: =+B6*17.16% -> -84475470 | C7: =B7/100000 -> -844.7547
A9: Unaborbed Depreciation carried forward as per return | B9: -385108815 | C9: As per Return | D9: IT & loss | E9: =B5-B9 -> 325352448
A10: IT Depreciation | B10: =+'[16]Draft-TC'!E26 -> -633596523 | C10: Current year depreciation
A11: Total Depreciation | B11: =+B9+B10 -> -1018705338
A12: Tax rate | B12: =+B11*17.16% -> -1.7480984e+08 | C12: =B12/100000 -> -1748.0984
A13: Total | B13: =+B12+B7 -> -2.5928531e+08
A16: Particulars | B16: ITWDV | C16: Book WDV | D16: DT | E16: @ 17.16%
A18: Building | B18: =+'[17]IT Dep_FY26'!Q8 -> 1.2517297e+09 | C18: =+'[17]PPE- note 3'!N11 -> 1.3990438e+09 | D18: =B18-C18 -> -1.4731415e+08 | E18: =D18*17.16% -> -25279109
A19: Plant & Machinery | B19: =+'[17]IT Dep_FY26'!Q10 -> 2.7590086e+09 | C19: =+'[17]PPE- note 3'!N12+'[17]PPE- note 3'!N13+'[17]PPE- note 3'!N16 -> 3.2093047e+09 | D19: =B19-C19 -> -4.5029618e+08 | E19: =D19*17.16% -> -77270824
A20: Furniture | B20: =+'[17]IT Dep_FY26'!Q12 -> 17602372 | C20: =+'[17]PPE- note 3'!N15 -> 18044181 | D20: =B20-C20 -> -441808.62 | E20: =D20*17.16% -> -75814.36
A21: Computers | B21: =+'[17]IT Dep_FY26'!Q14 -> 9737700.9 | C21: =+'[17]PPE- note 3'!N14+'[17]PPE- note 3'!N26 -> 14657952 | D21: =B21-C21 -> -4920251.2 | E21: =D21*17.16% -> -844315.1
B22: =SUM(B18:B21) -> 4.0380783e+09 | C22: =SUM(C18:C21) -> 4.6410507e+09 | D22: =SUM(D18:D21) -> -6.0297239e+08 | E22: =SUM(E18:E21) -> -1.0347006e+08 | F22: =E22/100000 -> -1034.7006
A24: Provision for Leave | B24: 0 | C24: =-'[17]43B'!E27-'[17]43B'!F13 -> -4772879 | D24: =+C24 -> -4772879 | E24: =D24*17.16% -> -819026.04
A25: Provision for Gratui | B25: 0 | C25: =-'[17]43B'!E28 -> -4499741 | D25: =+C25 -> -4499741 | E25: =D25*17.16% -> -772155.56
A26: Provision for Bonus | C26: =-'[17]43B'!E26 -> -5684697 | D26: =+C26 -> -5684697 | E26: =D26*17.16% -> -975494.01
A27: Credit Loss | C27: =-'[17]Draft-TC'!E18 -> -1495028 | D27: =+C27 -> -1495028 | E27: =D27*17.16% -> -256546.8
D28: =SUM(D24:D27) -> -16452345 | E28: =SUM(E24:E27) -> -2823222.4 | F28: =E28/100000 -> -28.232224
E29: =+E22+E28 -> -1.0629328e+08
E31: =+B13-E29 -> -1.5299202e+08 | F31: TBD
A36: Capital gains
A37: HDFC Overnight Fund - Direct Plan - Growth Option
A38: HDFC Liquid Fund-Direct Plan-Growth Option Cash,
A41: HDFC Arbitrage Fund - Wholesale Plan - Growth - Direct Plan Arbitrage Fund,
A49: Leasehold
A50: Expenditure deferred relating to leasehold rights amortisation (AY 2023-24)
A51: Amortisation
A54: Expenditure deferred relating to leasehold rights amortisation (AY 2022-23)
A55: Int on borrowing
A56: Amortisation
A60: Leasehold land
A61: Cost of acquisition
A66: Lease period
A67: 42789
A68: =(99*365)+A67 -> 78924
A69: Balance lease period
A70: 45292
A71: =A68 -> 78924
A73: Jan 24 to March 24
A78: AY 2023-24
A79: Expenditure deferred relating to manufacturing | B79: =+C104 -> 4519228
A80: AY 2022-23
A81: Expenditure deferred relating to manufacturing | B81: =+C113 -> 3321550.7
A82: Total | B82: =SUM(B79:B81) -> 7840778.7
A83: Deferred in FY2023-24 | B83: 1358384
A84: Deferred in FY2024-25 | B84: =+B82-B83 -> 6482394.7
A90: Purchase Expense Register
A91: G/L Account No: 4310036
A92: G/L Account Name : Legal & Professional Fees
A93: Posting Date | B93: Document Type | C93: Debit Amount
A94: 44712 | B94: Invoice | C94: 1000000
A95: 44712 | B95: Invoice | C95: 410075
A96: 44704 | B96: Invoice | C96: 640000
A97: 44755 | B97: Invoice | C97: 500000
A98: 44773 | B98: Invoice | C98: 78350
A99: 44773 | B99: Invoice | C99: 78350
A100: 44798 | B100: Invoice | C100: 809453
A101: 44804 | B101: Invoice | C101: 103000
A102: 44865 | B102: Invoice | C102: 1000000
A103: 44816 | B103: JV | C103: -100000
C104: =SUM(C94:C103) -> 4519228
A108: Posting Date | B108: Document Type | C108: Debit Amount
A109: 44561 | B109: Invoice | C109: 800000
A110: 44592 | B110: Invoice | C110: 1500000
A111: 44649 | B111: Invoice | C111: 1000000
C112: =+[18]LA!P217 -> 21550.685
C113: =SUM(C109:C112) -> 3321550.7

Sheet WA-Shares
A1: Sr No | B1: Nature of Shares | C1: Date of Issue | D1: No of Shares | E1: 46112 | F1: WA Days | G1: Basic | H1: Dilluted | J1: 45382 | L1: WA Days
A2: 1 | B2: Ordinary Equity Shares - Basic + Dilluted | C2: On Incorporation | D2: 10000 | E2: =D2 -> 10000 | G2: =E2 -> 10000 | H2: =E2 -> 10000 | J2: =D2 -> 10000
A4: 2 | B4: CCPS issued - Basic + Dilluted_1st Lot | C4: 45044 | D4: 44097 | E4: =D4 -> 44097 | G4: =E4 -> 44097 | H4: =E4 -> 44097 | J4: =D4/366*L4 -> 40843.943 | L4: =J1-C4+1 -> 339
A6: 2 | B6: OCPS Converted to Equity | C6: 45126 | D6: 97276 | E6: =D6 -> 97276 | G6: =E6 -> 97276 | H6: =E6 -> 97276 | J6: =D6/366*L6 -> 68305.825 | L6: =J1-C6+1 -> 257
A8: 3 | B8: Loan Converted to Equity | C8: 45471 | D8: 29321 | E8: =D8/365*F8 -> 51572.827 | F8: =E1-C8+1 -> 642 | G8: =E8 -> 51572.827 | H8: =E8 -> 51572.827 | J8: 0
A10: 4 | B10: CCPS issued - Basic + Dilluted_2nd Lot | C10: 45428 | D10: 42771 | E10: =D10/365*F10 -> 80268.863 | F10: =E1-C10+1 -> 685 | G10: =E10 -> 80268.863 | H10: =E10 -> 80268.863 | J10: 0
A12: 5 | B12: Loan Converted to Equity | C12: 46071 | D12: 23192 | E12: =D12/365*F12 -> 2668.6685 | F12: =E1-C12+1 -> 42 | G12: =E12 -> 2668.6685 | H12: =E12 -> 2668.6685
G13: =SUM(G2:G12) -> 285883.36 | H13: =SUM(H2:H12) -> 285883.36 | J13: =SUM(J2:J11) -> 119149.77

Sheet BS  Notes  3-18
A1: =PL!A1 -> BVC Specialities Private Limited
A2: ='PPE- note 3'!A2 -> Notes to Financial Statements for the year ended 31 March 2026 | H2: =Input!$D$2 -> (₹ in Lakh) | I2: =Input!$D$2 -> (₹ in Lakh)
A4: Particulars | G4: As at | H4: As at | I4: As at
G5: =BS!$D$5 -> 31 March 2026 | H5: =BS!$E$5 -> 31 March 2025 | I5: =BS!$F$5 -> 31 March 2022
A8: NOTE 4
A9: NON- CURRENT FINANCIAL ASSETS : INVESTMENTS
A10: Investments in Equity Instruments (unquoted) - JSW Renew Energy Twenty-Six Limited (initally recognised at fair value through Profit and Loss and subsequently measured at amortised cost)
A11: 9,48,000 (31 March 2025: NIL) fully paid up equity shares of par value of ₹ 10 each of JSW Renew Energy Twenty-Six Limited | G11: =ROUND(SUMIF('TB BVS 31.03.26'!E:E,A11,'TB BVS 31.03.26'!I:I)/Input!$C$2,Input!$E$2) -> 17 | H11: 0
A12: Total | G12: =SUM(G8:G11) -> 17 | H12: =SUM(H8:H11) -> 0
A13: Aggregate value of unquoted investments | G13: =G12 -> 17
A14: Note: The purpose of investment in JSW Renew Energy Twenty-Six Limited was to avail power through captive renewable energy sources to meet the power requirements for captive consumption of the Company. As per the terms of the agreement and in-line with the guidance under the standards, investment in JSW Renew Energy Twenty-Six Limited would not be a subsidiary or associate of the Company. Investments are initally recognised at fair value through Profit and Loss and subsequently measured at amortised cost.
A16: Particulars | G16: As at | H16: As at | I16: As at
G17: =BS!$D$5 -> 31 March 2026 | H17: =BS!$E$5 -> 31 March 2025 | I17: =BS!$F$5 -> 31 March 2022
A18: NOTE 5
A19: NON-CURRENT FINANCIAL ASSETS : LOANS
A20: Loans to related party - (Considered good - unsecured) | G20: =ROUND(SUMIF('TB BVS 31.03.26'!$E:$E,'BS Notes 3-18'!A20,'TB BVS 31.03.26'!$J:$J)/Input!$C$2,Input!$E$2) -> 0 | H20: =ROUND(SUMIF('TB BVS 31.3.25'!$E:$E,'BS Notes 3-18'!A20,'TB BVS 31.3.25'!$J:$J)/Input!$C$2,Input!$E$2) -> 0 | I20: =ROUND(SUMIF('[1]TB - SNS - 31.3.22'!$E:$E,A20,'[1]TB - SNS - 31.3.22'!$N:$N)/[1]Input!$C$2,[1]Input!$E$2) -> #VALUE! | K20: 2333.4037 | L20: =H20-K20 -> -2333.4037 | M20: Interest accrued on Loan given to related party not removed in IND AS, to check with Bhavya, to be shown under "Other Current Asset" | P20: {=SUMIF('[2]TB - SNS - 31.3.24'!F:F,'[2]BS Notes 4-18'!A199:E199,'[2]TB - SNS - 31.3.24'!J:J)/10^5-G20} -> #VALUE! | Q20: #VALUE! | R20: #VALUE! | S20: #VALUE! | T20: #VALUE!
A21: Total | G21: =SUM(G20:G20) -> 0 | H21: =SUM(H20:H20) -> 0 | I21: =SUM(I20:I20) -> #VALUE!
A22: (i) Current Year - Nil (Previous Year - These loans are repayable after 2 years from the date of loan given and carry the interest rate of 8.50%.)
A23: CURRENT FINANCIAL ASSETS : LOANS
A24: Loans to related party - subsidiaries (Considered good - unsecured) | G24: =ROUND(SUMIF('TB BVS 31.03.26'!$E:$E,'BS Notes 3-18'!A92,'TB BVS 31.03.26'!$J:$J)/Input!$C$2,Input!$E$2) -> 0 | H24: 0 | I24: =ROUND(SUMIF('[1]TB - SNS - 31.3.22'!$E:$E,A24,'[1]TB - SNS - 31.3.22'!$M:$M)/[1]Input!$C$2,[1]Input!$E$2) -> #VALUE! | K24: 2333.4037 | L24: =H24-K24 -> -2333.4037 | M24: Interest accrued on Loan given to related party not removed in IND AS, to check with Bhavya, to be shown under "Other Current Asset"
A25: Total | G25: =SUM(G24:G24) -> 0 | H25: =SUM(H24:H24) -> 0 | I25: =SUM(I24:I24) -> #VALUE!
A27: NOTE 5 | K27: =#REF!-#REF! -> #REF!
A28: NON-CURRENT FINANCIAL ASSETS : OTHERS | K28: =#REF!-#REF! -> #REF!
A29: Security Deposits | G29: =ROUND(SUMIF('TB BVS 31.03.26'!$E:$E,'BS Notes 3-18'!A29,'TB BVS 31.03.26'!$I:$I)/Input!$C$2,Input!$E$2) -> 298 | H29: =ROUND(SUMIF('TB BVS 31.3.25'!$E:$E,'BS Notes 3-18'!A29,'TB BVS 31.3.25'!$K:$K)/Input!$C$2,Input!$E$2) -> 290 | I29: =ROUND(SUMIF('[1]TB - SNS - 31.3.22'!$E:$E,'[2]BS Notes 4-18'!A208,'[1]TB - SNS - 31.3.22'!$N:$N)/[1]Input!$C$2,[1]Input!$E$2) -> #VALUE! | J29: =ROUND(SUMIF('[1]TB - SNS - 31.3.21'!$E:$E,'[2]BS Notes 4-18'!A208,'[1]TB - SNS - 31.3.21'!$N:$N)/[1]Input!$C$2,[1]Input!$E$2) -> #VALUE! | K29: 190.08999 | L29: =H29-K29 -> 99.910006 | M29: Security Deposit Reclass to ROU Asset Impact - INR 5,17,144 | P29: {=SUMIF('[2]TB - SNS - 31.3.24'!F:F,'[2]BS Notes 4-18'!A208:E208,'[2]TB - SNS - 31.3.24'!J:J)/10^5-G29-G62} -> #VALUE! | Q29: #VALUE! | R29: #VALUE! | S29: #VALUE! | T29: #VALUE!
A30: Finance lease receivable (Unsecured - considered good) | G30: =ROUND(SUMIF('TB BVS 31.03.26'!$E:$E,'BS Notes 3-18'!A30,'TB BVS 31.03.26'!$I:$I)/Input!$C$2,Input!$E$2) -> 9 | H30: =ROUND(SUMIF('TB BVS 31.3.25'!$E:$E,'BS Notes 3-18'!A30,'TB BVS 31.3.25'!$K:$K)/Input!$C$2,Input!$E$2) -> 12 | I30: =ROUND(SUMIF('[1]TB - SNS - 31.3.22'!$E:$E,'[2]BS Notes 4-18'!A209,'[1]TB - SNS - 31.3.22'!$N:$N)/[1]Input!$C$2,[1]Input!$E$2) -> #VALUE! | J30: =ROUND(SUMIF('[1]TB - SNS - 31.3.21'!$E:$E,'[2]BS Notes 4-18'!A209,'[1]TB - SNS - 31.3.21'!$N:$N)/[1]Input!$C$2,[1]Input!$E$2) -> #VALUE! | K30: 0 | L30: =H30-K30 -> 12 | M30: Receivable against Employee Car shown as Finance Lease - INR 43,49,959 - Non Current Portion | P30: {=SUMIF('[2]TB - SNS - 31.3.24'!F:F,'[2]BS Notes 4-18'!A209:E209,'[2]TB - SNS - 31.3.24'!J:J)/10^5-G30} -> #VALUE! | Q30: #VALUE! | R30: #VALUE! | S30: #VALUE! | T30: #VALUE!
A31: Balance with Bank | G31: =ROUND(SUMIF('TB BVS 31.03.26'!$E:$E,'BS Notes 3-18'!A31,'TB BVS 31.03.26'!$K:$K)/Input!$C$2,Input!$E$2) -> 0 | H31: 0
A32: Bank Deposit with more than 12 months of maturity | G32: =ROUND(SUMIF('TB BVS 31.03.26'!$E:$E,'BS Notes 3-18'!A32,'TB BVS 31.03.26'!$I:$I)/Input!$C$2,Input!$E$2) -> 0 | H32: =ROUND(SUMIF('TB BVS 31.3.25'!$E:$E,'BS Notes 3-18'!A32,'TB BVS 31.3.25'!$K:$K)/Input!$C$2,Input!$E$2) -> 50
A33: Total | G33: =SUM(G29:G32) -> 307 | H33: =SUM(H29:H32) -> 352 | I33: =SUM(I29:I30) -> #VALUE! | J33: =SUM(J29:J30) -> #VALUE! | K33: =SUM(K29:K30) -> 190.08999 | L33: =SUM(L29:L30) -> 111.91001
A35: CURRENT FINANCIAL ASSETS : OTHERS
A36: Other receivable | G36: =ROUND(SUMIF('TB BVS 31.03.26'!$E:$E,'BS Notes 3-18'!A36,'TB BVS 31.03.26'!$J:$J)/Input!$C$2,Input!$E$2) -> 0 | H36: =ROUND(SUMIF('TB BVS 31.3.25'!$E:$E,'BS Notes 3-18'!A36,'TB BVS 31.3.25'!$J:$J)/Input!$C$2,Input!$E$2) -> 0
A37: Total | G37: =SUM(G36) -> 0 | H37: 0
A40: NOTE 6
A41: NON CURRENT ASSETS : Other Tax Asset (Net)
A42: Other Receivables | G42: =ROUND(SUMIF('TB BVS 31.03.26'!$E:$E,'BS Notes 3-18'!A42,'TB BVS 31.03.26'!$I:$I)/Input!$C$2,Input!$E$2) -> 0 | H42: 0
A43: Other Tax Asset (Net) | G43: =ROUND(SUMIF('TB BVS 31.03.26'!$E:$E,'BS Notes 3-18'!A43,'TB BVS 31.03.26'!$I:$I)/Input!$C$2,Input!$E$2)-0.5 -> 5.5 | H43: =(ROUND(SUMIF('TB BVS 31.3.25'!$E:$E,'BS Notes 3-18'!A43,'TB BVS 31.3.25'!$K:$K)/Input!$C$2,Input!$E$2)+'TB BVS 31.3.25'!I51/1000) -> 13
A44: Total | G44: =SUM(G42:G43) -> 5.5 | H44: =SUM(H43) -> 13
A46: CURRENT ASSETS : OTHERS
A47: Other Tax Assets (Net) | G47: =ROUND(SUMIF('TB BVS 31.03.26'!$E:$E,'BS Notes 3-18'!A47,'TB BVS 31.03.26'!$J:$J)/Input!$C$2,Input!$E$2) -> 0 | H47: =ROUND(SUMIF('TB BVS 31.3.23'!$E:$E,'BS Notes 3-18'!A47,'TB BVS 31.3.23'!$M:$M)/Input!$C$2,Input!$E$2) -> 0
A48: Total | G48: =SUM(G47) -> 0 | H48: =SUM(H47) -> 0 | I48: =SUM(#REF!) -> #REF! | K48: =#REF!*10^3 -> #REF!
A50: NOTE 7
A51: NON CURRENT ASSETS : OTHERS
A52: Prepaid Expenses | G52: =ROUND(SUMIF('TB BVS 31.03.26'!$E:$E,'BS Notes 3-18'!A52,'TB BVS 31.03.26'!$K:$K)/Input!$C$2,Input!$E$2) -> 74 | H52: 0
A53: Capital Advance | G53: =ROUND(SUMIF('TB BVS 31.03.26'!$E:$E,'BS Notes 3-18'!A53,'TB BVS 31.03.26'!$I:$I)/Input!$C$2,Input!$E$2)-0.5 -> 1.5 | H53: =ROUND(SUMIF('TB BVS 31.3.25'!$E:$E,'BS Notes 3-18'!A53,'TB BVS 31.3.25'!$K:$K)/Input!$C$2,Input!$E$2) -> 84
A54: Total | G54: =SUM(G52:G53) -> 75.5 | H54: =SUM(H53) -> 84 | I54: =SUM(I48:I48) -> #REF! | K54: =K48*10^3 -> #REF!
A56: NOTE 27
A57: NON CURRENT ASSETS : OTHERS
A58: Other Tax Assets (Net) | G58: =ROUND(SUMIF('TB BVS 31.03.26'!$E:$E,'BS Notes 3-18'!A58,'TB BVS 31.03.26'!$K:$K)/Input!$C$2,Input!$E$2) -> 0 | H58: =ROUND(SUMIF('TB BVS 31.3.23'!$E:$E,'BS Notes 3-18'!A58,'TB BVS 31.3.23'!$M:$M)/Input!$C$2,Input!$E$2) -> 0
A59: Total | G59: =SUM(G58) -> 0 | H59: =SUM(H58) -> 0
A61: CURRENT FINANCIAL ASSETS : OTHERS
A62: Security Deposits | G62: =ROUND(SUMIF('TB BVS 31.03.26'!$E:$E,'BS Notes 3-18'!A62,'TB BVS 31.03.26'!$J:$J)/Input!$C$2,Input!$E$2) -> 0 | H62: 0 | I62: =ROUND(SUMIF('[1]TB - SNS - 31.3.22'!$E:$E,A62,'[1]TB - SNS - 31.3.22'!$M:$M)/[1]Input!$C$2,[1]Input!$E$2) -> #VALUE! | J62: =ROUND(SUMIF('[1]TB - SNS - 31.3.21'!$E:$E,'[2]BS Notes 4-18'!A215,'[1]TB - SNS - 31.3.21'!$M:$M)/[1]Input!$C$2,[1]Input!$E$2) -> #VALUE! | K62: 5.7639104 | L62: =H62-K62 -> -5.7639104 | M62: GL 21100006 - Loan to Others, should not come under Security Deposit grouping | P62: NA
A63: Finance lease receivable (Unsecured - considered good) | G63: =ROUND(SUMIF('TB BVS 31.03.26'!$E:$E,'BS Notes 3-18'!A63,'TB BVS 31.03.26'!$J:$J)/Input!$C$2,Input!$E$2) -> 0 | H63: 0 | I63: =ROUND(SUMIF('[1]TB - SNS - 31.3.22'!$E:$E,A63,'[1]TB - SNS - 31.3.22'!$M:$M)/[1]Input!$C$2,[1]Input!$E$2) -> #VALUE! | J63: =ROUND(SUMIF('[1]TB - SNS - 31.3.21'!$E:$E,'[2]BS Notes 4-18'!A216,'[1]TB - SNS - 31.3.21'!$M:$M)/[1]Input!$C$2,[1]Input!$E$2) -> #VALUE! | K63: 0 | L63: =H63-K63 -> 0 | M63: Receivable against Employee Car shown as Finance Lease - INR 7,07,498 - Current Portion | P63: NA
A64: Total | G64: =SUM(G62:G63) -> 0 | H64: =SUM(H62:H63) -> 0 | I64: =SUM(I62:I63) -> #VALUE! | J64: =SUM(J62:J63) -> #VALUE!
A65: NOTE 6
A66: NON-CURRENT FINANCIAL ASSETS : OTHERS
A67: Other Non Current Assets | G67: =ROUND(SUMIF('TB BVS 31.03.26'!$E:$E,'BS Notes 3-18'!A67,'TB BVS 31.03.26'!$J:$J)/Input!$C$2,Input!$E$2) -> 0 | H67: 0
A68: Total | G68: =SUM(G67:G67) -> 0 | H68: =SUM(H67:H67) -> 0
A69: NOTE 8
A70: INVENTORIES (Refer accounting policies for mode of valuation)
A71: Raw materials** | G71: =ROUND(SUMIF('TB BVS 31.03.26'!$E:$E,'BS Notes 3-18'!A71,'TB BVS 31.03.26'!$I:$I)/Input!$C$2,Input!$E$2) -> 1649 | H71: =ROUND(SUMIF('TB BVS 31.3.25'!$E:$E,'BS Notes 3-18'!A71,'TB BVS 31.3.25'!$J:$J)/Input!$C$2,Input!$E$2) -> 321 | I71: =ROUND(SUMIF('[1]TB - SNS - 31.3.22'!$E:$E,A71,'[1]TB - SNS - 31.3.22'!$M:$M)/[1]Input!$C$2,[1]Input!$E$2) -> #VALUE! | J71: =ROUND(SUMIF('[1]TB - SNS - 31.3.21'!$E:$E,'[2]BS Notes 4-18'!A161,'[1]TB - SNS - 31.3.21'!$M:$M)/[1]Input!$C$2,[1]Input!$E$2) -> #VALUE! | O71: =G71/1000 -> 1.649
A72: Packing material | G72: =ROUND(SUMIF('TB BVS 31.03.26'!$E:$E,'BS Notes 3-18'!A72,'TB BVS 31.03.26'!$I:$I)/Input!$C$2,Input!$E$2) -> 13 | H72: =ROUND(SUMIF('TB BVS 31.3.25'!$E:$E,'BS Notes 3-18'!A72,'TB BVS 31.3.25'!$J:$J)/Input!$C$2,Input!$E$2) -> 21 | O72: =G72/1000 -> 0.013
A73: Work-in-progress | G73: =ROUND(SUMIF('TB BVS 31.03.26'!$E:$E,'BS Notes 3-18'!A73,'TB BVS 31.03.26'!$I:$I)/Input!$C$2,Input!$E$2) -> 1831 | H73: =ROUND(SUMIF('TB BVS 31.3.25'!$E:$E,'BS Notes 3-18'!A73,'TB BVS 31.3.25'!$J:$J)/Input!$C$2,Input!$E$2) -> 399 | I73: =ROUND(SUMIF('[1]TB - SNS - 31.3.22'!$E:$E,A73,'[1]TB - SNS - 31.3.22'!$M:$M)/[1]Input!$C$2,[1]Input!$E$2) -> #VALUE! | J73: =ROUND(SUMIF('[1]TB - SNS - 31.3.21'!$E:$E,'[2]BS Notes 4-18'!A163,'[1]TB - SNS - 31.3.21'!$M:$M)/[1]Input!$C$2,[1]Input!$E$2) -> #VALUE! | O73: =G73/1000 -> 1.831 | Q73: =60.8-27.75 -> 33.05
A74: Finished goods* | G74: =ROUND(SUMIF('TB BVS 31.03.26'!$E:$E,'BS Notes 3-18'!A74,'TB BVS 31.03.26'!$I:$I)/Input!$C$2,Input!$E$2) -> 2783 | H74: =ROUND(SUMIF('TB BVS 31.3.25'!$E:$E,'BS Notes 3-18'!A74,'TB BVS 31.3.25'!$J:$J)/Input!$C$2,Input!$E$2) -> 0 | I74: =ROUND(SUMIF('[1]TB - SNS - 31.3.22'!$E:$E,A74,'[1]TB - SNS - 31.3.22'!$M:$M)/[1]Input!$C$2,[1]Input!$E$2) -> #VALUE! | J74: =ROUND(SUMIF('[1]TB - SNS - 31.3.21'!$E:$E,'[2]BS Notes 4-18'!A164,'[1]TB - SNS - 31.3.21'!$M:$M)/[1]Input!$C$2,[1]Input!$E$2) -> #VALUE! | O74: =G74/1000 -> 2.783
A75: Stores and spares | G75: =ROUND(SUMIF('TB BVS 31.03.26'!$E:$E,'BS Notes 3-18'!A75,'TB BVS 31.03.26'!$I:$I)/Input!$C$2,Input!$E$2) -> 362 | H75: =ROUND(SUMIF('TB BVS 31.3.25'!$E:$E,'BS Notes 3-18'!A75,'TB BVS 31.3.25'!$J:$J)/Input!$C$2,Input!$E$2) -> 70 | I75: =ROUND(SUMIF('[1]TB - SNS - 31.3.22'!$E:$E,A75,'[1]TB - SNS - 31.3.22'!$M:$M)/[1]Input!$C$2,[1]Input!$E$2) -> #VALUE! | J75: =ROUND(SUMIF('[1]TB - SNS - 31.3.21'!$E:$E,'[2]BS Notes 4-18'!A165,'[1]TB - SNS - 31.3.21'!$M:$M)/[1]Input!$C$2,[1]Input!$E$2) -> #VALUE! | O75: =G75/1000 -> 0.362
A76: Total | G76: =SUM(G71:G75) -> 6638 | H76: =SUM(H71:H75) -> 811 | I76: =SUM(I71:I75) -> #VALUE! | J76: =SUM(J71:J75) -> #VALUE!
A77: *includes goods in transit amounting to ₹2,171 Lakhs (31 March 2025: ₹ NIL) | O77: =G73+G74 -> 4614 | P77: 35150080
A78: **includes goods in transit amounting to ₹ 127 Lakhs (31 March 2025: ₹ NIL)
